Workbook

Sheet Read Me
A1: Nordic Opportunity Pipeline – Read Me
A2: Assignment F-01 (with F-02 scoring) · Nordic Construction Company Ltd · Version 0.4 (multi-source scanner) · 24 Sep 2026
A4: Purpose | B4: One place to record every relevant tender, RFP, prequalification and EOI, screen it, score it (F-02) and feed Panel 3 of the MD Dashboard (F-03).
A5: Scope | B5: Building, civil, fit-out, renovation (and MEP for referral) valued from TZS 200 million upward. Consultancy-only tenders are out of scope.
A6: Sheets | B6: Pipeline – main register (Appendix F columns + helper columns) · Bid-NoBid – F-02 score per ID · Scoring Guide – gates, criteria, weights, thresholds · Friday Summary – counts and the 14-day due list · Panel 3 Feed – linked rows for the MD Dashboard · Watch List – banks and corporates without public tenders · Scan Log – what was checked and when · Lists – drop-down options.
A7: Colour code | B7: Blue text = type here. Black = formula, do not overwrite. Green = linked from another sheet. Yellow fill = settings (weights, thresholds, report date).
A8: Adding a tender | B8: Type the Tender no. in the next empty Pipeline row – the ID (OP-###) appears automatically and the row appears on Bid-NoBid and Panel 3 Feed. Fill the blue cells; use the drop-downs.
A9: 'NeST login needed' | B9: NeST shows only title, entity, dates and tender no. to the public. CRB class, estimated value, site visit and bid security are inside the tender document, visible after logging in with Nordic's NeST account (login details held by the QS Director, not in this file).
A10: Recommendation | B10: Shows 'Screen: Pursue / Check / Drop' (a first view from the notice) until all 12 criteria are scored on Bid-NoBid; then it shows Bid / Conditional (MD) / No-Bid.
A11: Alerts | B11: Deadline alert follows the Appendix E rule: RED if submission ≤ 7 days and status is not 'Preparing'; AMBER ≤ 14 days; GREEN beyond. Escalate to MD = value ≥ TZS 3bn, or deadline under 10 days with no MD decision yet (F-01 rules). JV tenders: escalate manually.
A12: Rule on numbers | B12: Never type an estimated value, CRB class or bid security that you have not read in the tender document or the PE's procurement plan. Leave blank or 'unverified'.
A13: Automatic feed | B13: The Tanzania Tender Scanner runs every 15 minutes on an office PC and checks: NeST (all Mainland public tenders), the World Bank's notices for Tanzania (civil works), the TANROADS website, the ZPPDA Zanzibar tender portal, and the CRDB and NMB tender pages. It keeps construction and civil-works tenders only, screens them, and adds new ones here with Found by = 'Auto-scan' and the source in the Source column. Others go to the Screened Out sheet. It updates deadlines that change at the source and writes a Scan Log line whenever it changes something. It only writes into empty rows – it never changes your scores, decisions or notes. While this file is open it cannot save, so close it when you finish; new tenders are added at the first scan after it is closed.
A14: Do not | B14: Do not insert or delete rows or columns on Pipeline or Bid-NoBid, and do not add pictures or charts to this file – the scanner cannot preserve pictures. Keep the file name and folder the same, or update scanner_config.json.
A15: Data in v0.1 | B15: 31 opportunities from the NeST Published Tenders list, read 24 Sep 2026 (326 published; 85 in Works). Watch list seeded with target clients from the programme and the Likong'o close-out report. Criterion 8 (location) pre-scored only; all other scores await evidence.

Sheet Pipeline
A1: Nordic Opportunity Pipeline
A2: F-01 · Appendix F layout · one row per tender, RFP, prequalification or EOI · blue = type here, black = formula · v0.3, 24 Sep 2026 · new tenders are added automatically every 15 minutes by the Tanzania Tender Scanner
A3: APPENDIX F COLUMNS | AA3: HELPER COLUMNS (screening, alerts, dashboard feed)
A4: ID | B4: Tender no. | C4: Date found | D4: Source | E4: Source URL | F4: Client | G4: Client type | H4: Tender title | I4: Scope summary | J4: Location | K4: Category | L4: CRB class required | M4: Est. value TZS | N4: Funding confirmed | O4: Site visit date | P4: Clarification deadline | Q4: Submission date | R4: Bid security | S4: Documents purchased | T4: Bid/No-Bid score | U4: Recommendation | V4: MD decision | W4: Status | X4: Owner | Y4: Outcome | Z4: Lessons | AA4: Date advertised | AB4: Notice type | AC4: Initial screen | AD4: Screen reason | AE4: Days to deadline | AF4: Deadline alert | AG4: Escalate to MD? | AH4: Win probability | AI4: Next action | AJ4: Found by | AK4: Source ID | AL4: Due-14 key
A5: =IF(B5="","","OP-"&TEXT(ROW()-4,"000")) | B5: 7205/2026/2027/W/09 | C5: 46289 | D5: NeST | E5: https://nest.go.tz/tenders/published-tenders | F5: City Council of Dodoma | G5: government | H5: Proposed construction of the City Council of Dodoma Head Office | I5: New multi-storey council head office building in Dodoma City | J5: Dodoma | K5: building | L5: NeST login needed | N5: unknown | O5: NeST login needed | P5: NeST login needed | Q5: 46303.417 | R5: NeST login needed | S5: N | T5: =IF(A5="","",IFERROR(INDEX('Bid-NoBid'!$T:$T,MATCH(A5,'Bid-NoBid'!$A:$A,0)),"")) | U5: =IF(A5="","",IFERROR(IF(OR(INDEX('Bid-NoBid'!$U:$U,MATCH(A5,'Bid-NoBid'!$A:$A,0))="",LEFT(INDEX('Bid-NoBid'!$U:$U,MATCH(A5,'Bid-NoBid'!$A:$A,0)),10)="Incomplete"),"Screen: "&AC5,INDEX('Bid-NoBid'!$U:$U,MATCH(A5,'Bid-NoBid'!$A:$A,0))),"Screen: "&AC5)) | W5: Watching | X5: Frank | AA5: 46288 | AB5: Small Works | AC5: Pursue | AD5: Flagship public building; 15-day window gives time to price; likely large value, so MD must see it | AE5: =IF(ISNUMBER(Q5),ROUNDDOWN(Q5-NOW(),1),"") | AF5: =IF(OR(A5="",AE5=""),"",IF(NOT(OR(W5="Watching",W5="Preparing")),"",IF(AE5<0,"PASSED",IF(AND(AE5<=7,W5<>"Preparing"),"RED",IF(AE5<=14,"AMBER","GREEN"))))) | AG5: =IF(OR(A5="",NOT(OR(W5="Watching",W5="Preparing"))),"",IF(AND(ISNUMBER(M5),M5>=3000000000),"YES – ≥ TZS 3bn",IF(AND(ISNUMBER(AE5),AE5>=0,AE5<10,V5=""),"YES – <10 days",""))) | AI5: Log in to NeST, download document, confirm CRB class, value and site visit; brief MD | AJ5: Manual scan | AK5: 36adabf5-6ac2-4a6b-bc14-a74e83964305 | AL5: =IF(AND(OR(W5="Watching",W5="Preparing"),ISNUMBER(Q5)),IF(AND(Q5>='Friday Summary'!$C$4,Q5<='Friday Summary'!$C$4+14),Q5+ROW()/1000000,""),"")
A6: =IF(B6="","","OP-"&TEXT(ROW()-4,"000")) | B6: TR33/2026/2027/W/01 | C6: 46289 | D6: NeST | E6: https://nest.go.tz/tenders/published-tenders | F6: President's Office – Ethics Secretariat | G6: government | H6: Proposed construction of office buildings and structures at Eastern Zonal Office (Morogoro) | I6: Office buildings and associated structures for the Eastern Zone office | J6: Morogoro | K6: building | L6: NeST login needed | N6: unknown | O6: NeST login needed | P6: NeST login needed | Q6: 46301.521 | R6: NeST login needed | S6: N | T6: =IF(A6="","",IFERROR(INDEX('Bid-NoBid'!$T:$T,MATCH(A6,'Bid-NoBid'!$A:$A,0)),"")) | U6: =IF(A6="","",IFERROR(IF(OR(INDEX('Bid-NoBid'!$U:$U,MATCH(A6,'Bid-NoBid'!$A:$A,0))="",LEFT(INDEX('Bid-NoBid'!$U:$U,MATCH(A6,'Bid-NoBid'!$A:$A,0)),10)="Incomplete"),"Screen: "&AC6,INDEX('Bid-NoBid'!$U:$U,MATCH(A6,'Bid-NoBid'!$A:$A,0))),"Screen: "&AC6)) | W6: Watching | X6: Frank | AA6: 46283 | AB6: Small Works | AC6: Pursue | AD6: Building works within reach of Dar; 11 days left | AE6: =IF(ISNUMBER(Q6),ROUNDDOWN(Q6-NOW(),1),"") | AF6: =IF(OR(A6="",AE6=""),"",IF(NOT(OR(W6="Watching",W6="Preparing")),"",IF(AE6<0,"PASSED",IF(AND(AE6<=7,W6<>"Preparing"),"RED",IF(AE6<=14,"AMBER","GREEN"))))) | AG6: =IF(OR(A6="",NOT(OR(W6="Watching",W6="Preparing"))),"",IF(AND(ISNUMBER(M6),M6>=3000000000),"YES – ≥ TZS 3bn",IF(AND(ISNUMBER(AE6),AE6>=0,AE6<10,V6=""),"YES – <10 days",""))) | AI6: Deadline changed at source 02-Oct (was 05-Oct 12:30). Download document; check CRB class and bid security | AJ6: Manual scan | AK6: 8021c469-1ab2-4f17-8090-49aee45b3951 | AL6: =IF(AND(OR(W6="Watching",W6="Preparing"),ISNUMBER(Q6)),IF(AND(Q6>='Friday Summary'!$C$4,Q6<='Friday Summary'!$C$4+14),Q6+ROW()/1000000,""),"")
A7: =IF(B7="","","OP-"&TEXT(ROW()-4,"000")) | B7: TR126/2026/2027/W/10 | C7: 46289 | D7: NeST | E7: https://nest.go.tz/tenders/published-tenders | F7: Tanzania Railways Corporation (TRC) | G7: parastatal | H7: Construction of running rooms and houses for TRC staff | I7: Staff housing and running rooms (locations per tender document) | J7: TBC – per tender document | K7: building | L7: NeST login needed | N7: unknown | O7: NeST login needed | P7: NeST login needed | Q7: 46301.583 | R7: NeST login needed | S7: N | T7: =IF(A7="","",IFERROR(INDEX('Bid-NoBid'!$T:$T,MATCH(A7,'Bid-NoBid'!$A:$A,0)),"")) | U7: =IF(A7="","",IFERROR(IF(OR(INDEX('Bid-NoBid'!$U:$U,MATCH(A7,'Bid-NoBid'!$A:$A,0))="",LEFT(INDEX('Bid-NoBid'!$U:$U,MATCH(A7,'Bid-NoBid'!$A:$A,0)),10)="Incomplete"),"Screen: "&AC7,INDEX('Bid-NoBid'!$U:$U,MATCH(A7,'Bid-NoBid'!$A:$A,0))),"Screen: "&AC7)) | W7: Watching | X7: Frank | AA7: 46281 | AB7: Small Works | AC7: Pursue | AD7: Repeat-able parastatal housing client; confirm site locations | AE7: =IF(ISNUMBER(Q7),ROUNDDOWN(Q7-NOW(),1),"") | AF7: =IF(OR(A7="",AE7=""),"",IF(NOT(OR(W7="Watching",W7="Preparing")),"",IF(AE7<0,"PASSED",IF(AND(AE7<=7,W7<>"Preparing"),"RED",IF(AE7<=14,"AMBER","GREEN"))))) | AG7: =IF(OR(A7="",NOT(OR(W7="Watching",W7="Preparing"))),"",IF(AND(ISNUMBER(M7),M7>=3000000000),"YES – ≥ TZS 3bn",IF(AND(ISNUMBER(AE7),AE7>=0,AE7<10,V7=""),"YES – <10 days",""))) | AI7: Deadline changed at source 03-Oct (was 02-Oct 14:00). Download document; confirm sites and number of lots | AJ7: Manual scan | AK7: e617135e-e227-4d65-9771-bd3210e77e15 | AL7: =IF(AND(OR(W7="Watching",W7="Preparing"),ISNUMBER(Q7)),IF(AND(Q7>='Friday Summary'!$C$4,Q7<='Friday Summary'!$C$4+14),Q7+ROW()/1000000,""),"")
A8: =IF(B8="","","OP-"&TEXT(ROW()-4,"000")) | B8: 99/2026/2027/W/03 | C8: 46289 | D8: NeST | E8: https://nest.go.tz/tenders/published-tenders | F8: Ministry of Livestock and Fisheries | G8: government | H8: Proposed rehabilitation of buildings and construction of fence at Vikuge Pasture Seed Farm, Kibaha | I8: Rehabilitation of existing buildings plus perimeter fence | J8: Pwani (Kibaha) | K8: renovation | L8: NeST login needed | N8: unknown | O8: NeST login needed | P8: NeST login needed | Q8: 46297.562 | R8: NeST login needed | S8: N | T8: =IF(A8="","",IFERROR(INDEX('Bid-NoBid'!$T:$T,MATCH(A8,'Bid-NoBid'!$A:$A,0)),"")) | U8: =IF(A8="","",IFERROR(IF(OR(INDEX('Bid-NoBid'!$U:$U,MATCH(A8,'Bid-NoBid'!$A:$A,0))="",LEFT(INDEX('Bid-NoBid'!$U:$U,MATCH(A8,'Bid-NoBid'!$A:$A,0)),10)="Incomplete"),"Screen: "&AC8,INDEX('Bid-NoBid'!$U:$U,MATCH(A8,'Bid-NoBid'!$A:$A,0))),"Screen: "&AC8)) | W8: Watching | X8: Frank | AA8: 46287 | AB8: Small Works | AC8: Pursue | AD8: Renovation close to Dar base; 8 days left | AE8: =IF(ISNUMBER(Q8),ROUNDDOWN(Q8-NOW(),1),"") | AF8: =IF(OR(A8="",AE8=""),"",IF(NOT(OR(W8="Watching",W8="Preparing")),"",IF(AE8<0,"PASSED",IF(AND(AE8<=7,W8<>"Preparing"),"RED",IF(AE8<=14,"AMBER","GREEN"))))) | AG8: =IF(OR(A8="",NOT(OR(W8="Watching",W8="Preparing"))),"",IF(AND(ISNUMBER(M8),M8>=3000000000),"YES – ≥ TZS 3bn",IF(AND(ISNUMBER(AE8),AE8>=0,AE8<10,V8=""),"YES – <10 days",""))) | AI8: Download document; arrange site visit to Kibaha | AJ8: Manual scan | AK8: 31809cbd-0353-49b1-b8e7-1fd8dcd63d06 | AL8: =IF(AND(OR(W8="Watching",W8="Preparing"),ISNUMBER(Q8)),IF(AND(Q8>='Friday Summary'!$C$4,Q8<='Friday Summary'!$C$4+14),Q8+ROW()/1000000,""),"")
A9: =IF(B9="","","OP-"&TEXT(ROW()-4,"000")) | B9: 71B8/2026/2027/W/10 | C9: 46289 | D9: NeST | E9: https://nest.go.tz/tenders/published-tenders | F9: Chalinze District Council | G9: government | H9: Proposed construction of Machinga Complex market | I9: New market complex for small traders | J9: Pwani (Chalinze) | K9: building | L9: NeST login needed | N9: unknown | O9: NeST login needed | P9: NeST login needed | Q9: 46295.583 | R9: NeST login needed | S9: N | T9: =IF(A9="","",IFERROR(INDEX('Bid-NoBid'!$T:$T,MATCH(A9,'Bid-NoBid'!$A:$A,0)),"")) | U9: =IF(A9="","",IFERROR(IF(OR(INDEX('Bid-NoBid'!$U:$U,MATCH(A9,'Bid-NoBid'!$A:$A,0))="",LEFT(INDEX('Bid-NoBid'!$U:$U,MATCH(A9,'Bid-NoBid'!$A:$A,0)),10)="Incomplete"),"Screen: "&AC9,INDEX('Bid-NoBid'!$U:$U,MATCH(A9,'Bid-NoBid'!$A:$A,0))),"Screen: "&AC9)) | W9: Watching | X9: Frank | AA9: 46288 | AB9: Small Works | AC9: Pursue | AD9: Building works in Coast region; 6 days left – needs fast decision | AE9: =IF(ISNUMBER(Q9),ROUNDDOWN(Q9-NOW(),1),"") | AF9: =IF(OR(A9="",AE9=""),"",IF(NOT(OR(W9="Watching",W9="Preparing")),"",IF(AE9<0,"PASSED",IF(AND(AE9<=7,W9<>"Preparing"),"RED",IF(AE9<=14,"AMBER","GREEN"))))) | AG9: =IF(OR(A9="",NOT(OR(W9="Watching",W9="Preparing"))),"",IF(AND(ISNUMBER(M9),M9>=3000000000),"YES – ≥ TZS 3bn",IF(AND(ISNUMBER(AE9),AE9>=0,AE9<10,V9=""),"YES – <10 days",""))) | AI9: MD decision by Fri 25 Sep; download document today | AJ9: Manual scan | AK9: bd92ae93-02c6-4dfb-955f-d3ecbbd943f6 | AL9: =IF(AND(OR(W9="Watching",W9="Preparing"),ISNUMBER(Q9)),IF(AND(Q9>='Friday Summary'!$C$4,Q9<='Friday Summary'!$C$4+14),Q9+ROW()/1000000,""),"")
A10: =IF(B10="","","OP-"&TEXT(ROW()-4,"000")) | B10: 3400/2026/2027/W/04 | C10: 46289 | D10: NeST | E10: https://nest.go.tz/tenders/published-tenders | F10: Tanzania Concrete Poles Manufacturing Co. Ltd | G10: parastatal (verify) | H10: Prequalification of building contractors | I10: Prequalification to a list of building contractors (no price) | J10: TBC | K10: building | L10: NeST login needed | N10: unknown | O10: NeST login needed | P10: NeST login needed | Q10: 46290.583 | R10: NeST login needed | S10: N | T10: =IF(A10="","",IFERROR(INDEX('Bid-NoBid'!$T:$T,MATCH(A10,'Bid-NoBid'!$A:$A,0)),"")) | U10: =IF(A10="","",IFERROR(IF(OR(INDEX('Bid-NoBid'!$U:$U,MATCH(A10,'Bid-NoBid'!$A:$A,0))="",LEFT(INDEX('Bid-NoBid'!$U:$U,MATCH(A10,'Bid-NoBid'!$A:$A,0)),10)="Incomplete"),"Screen: "&AC10,INDEX('Bid-NoBid'!$U:$U,MATCH(A10,'Bid-NoBid'!$A:$A,0))),"Screen: "&AC10)) | W10: Watching | X10: Frank | AA10: 46283 | AB10: Standard Invitation for Quotations -Works | AC10: Pursue | AD10: Low-cost prequalification – gets Nordic onto a client list; closes tomorrow | AE10: =IF(ISNUMBER(Q10),ROUNDDOWN(Q10-NOW(),1),"") | AF10: =IF(OR(A10="",AE10=""),"",IF(NOT(OR(W10="Watching",W10="Preparing")),"",IF(AE10<0,"PASSED",IF(AND(AE10<=7,W10<>"Preparing"),"RED",IF(AE10<=14,"AMBER","GREEN"))))) | AG10: =IF(OR(A10="",NOT(OR(W10="Watching",W10="Preparing"))),"",IF(AND(ISNUMBER(M10),M10>=3000000000),"YES – ≥ TZS 3bn",IF(AND(ISNUMBER(AE10),AE10>=0,AE10<10,V10=""),"YES – <10 days",""))) | AI10: Submit company documents on NeST by 25 Sep 14:00 if MD agrees | AJ10: Manual scan | AK10: 7fb06603-91ec-4823-8ca1-9d2f4716d07c | AL10: =IF(AND(OR(W10="Watching",W10="Preparing"),ISNUMBER(Q10)),IF(AND(Q10>='Friday Summary'!$C$4,Q10<='Friday Summary'!$C$4+14),Q10+ROW()/1000000,""),"")
A11: =IF(B11="","","OP-"&TEXT(ROW()-4,"000")) | B11: 88Z4/2026/2027/W/42 | C11: 46289 | D11: NeST | E11: https://nest.go.tz/tenders/published-tenders | F11: Ubungo Municipal Council | G11: government | H11: Completion of construction of two-storey building for 6 classrooms and ramp at Kawawa Primary School | I11: Completion works to two-storey classroom block | J11: Dar es Salaam (Ubungo) | K11: building | L11: NeST login needed | N11: unknown | O11: NeST login needed | P11: NeST login needed | Q11: 46290.583 | R11: NeST login needed | S11: N | T11: =IF(A11="","",IFERROR(INDEX('Bid-NoBid'!$T:$T,MATCH(A11,'Bid-NoBid'!$A:$A,0)),"")) | U11: =IF(A11="","",IFERROR(IF(OR(INDEX('Bid-NoBid'!$U:$U,MATCH(A11,'Bid-NoBid'!$A:$A,0))="",LEFT(INDEX('Bid-NoBid'!$U:$U,MATCH(A11,'Bid-NoBid'!$A:$A,0)),10)="Incomplete"),"Screen: "&AC11,INDEX('Bid-NoBid'!$U:$U,MATCH(A11,'Bid-NoBid'!$A:$A,0))),"Screen: "&AC11)) | W11: Watching | X11: Frank | AA11: 46283 | AB11: Small Works | AC11: Check | AD11: Dar location and school experience (Likong'o) fit, but closes tomorrow – likely too late | AE11: =IF(ISNUMBER(Q11),ROUNDDOWN(Q11-NOW(),1),"") | AF11: =IF(OR(A11="",AE11=""),"",IF(NOT(OR(W11="Watching",W11="Preparing")),"",IF(AE11<0,"PASSED",IF(AND(AE11<=7,W11<>"Preparing"),"RED",IF(AE11<=14,"AMBER","GREEN"))))) | AG11: =IF(OR(A11="",NOT(OR(W11="Watching",W11="Preparing"))),"",IF(AND(ISNUMBER(M11),M11>=3000000000),"YES – ≥ TZS 3bn",IF(AND(ISNUMBER(AE11),AE11>=0,AE11<10,V11=""),"YES – <10 days",""))) | AI11: Ask QS Director today whether a bid is possible by 25 Sep 14:00 | AJ11: Manual scan | AK11: cf629183-3fd7-4914-a528-58a55f549165 | AL11: =IF(AND(OR(W11="Watching",W11="Preparing"),ISNUMBER(Q11)),IF(AND(Q11>='Friday Summary'!$C$4,Q11<='Friday Summary'!$C$4+14),Q11+ROW()/1000000,""),"")
A12: =IF(B12="","","OP-"&TEXT(ROW()-4,"000")) | B12: 52/072/2026/2027/W/13 | C12: 46289 | D12: NeST | E12: https://nest.go.tz/tenders/published-tenders | F12: Temeke Regional Referral Hospital | G12: government | H12: Renovation of hospital blocks | I12: Renovation of hospital blocks (quotation) | J12: Dar es Salaam (Temeke) | K12: renovation | L12: NeST login needed | N12: unknown | O12: NeST login needed | P12: NeST login needed | Q12: 46295.583 | R12: NeST login needed | S12: N | T12: =IF(A12="","",IFERROR(INDEX('Bid-NoBid'!$T:$T,MATCH(A12,'Bid-NoBid'!$A:$A,0)),"")) | U12: =IF(A12="","",IFERROR(IF(OR(INDEX('Bid-NoBid'!$U:$U,MATCH(A12,'Bid-NoBid'!$A:$A,0))="",LEFT(INDEX('Bid-NoBid'!$U:$U,MATCH(A12,'Bid-NoBid'!$A:$A,0)),10)="Incomplete"),"Screen: "&AC12,INDEX('Bid-NoBid'!$U:$U,MATCH(A12,'Bid-NoBid'!$A:$A,0))),"Screen: "&AC12)) | W12: Watching | X12: Frank | AA12: 46288 | AB12: Standard Invitation for Quotations -Works | AC12: Check | AD12: Dar renovation, but quotation route suggests value may be under TZS 200m | AE12: =IF(ISNUMBER(Q12),ROUNDDOWN(Q12-NOW(),1),"") | AF12: =IF(OR(A12="",AE12=""),"",IF(NOT(OR(W12="Watching",W12="Preparing")),"",IF(AE12<0,"PASSED",IF(AND(AE12<=7,W12<>"Preparing"),"RED",IF(AE12<=14,"AMBER","GREEN"))))) | AG12: =IF(OR(A12="",NOT(OR(W12="Watching",W12="Preparing"))),"",IF(AND(ISNUMBER(M12),M12>=3000000000),"YES – ≥ TZS 3bn",IF(AND(ISNUMBER(AE12),AE12>=0,AE12<10,V12=""),"YES – <10 days",""))) | AI12: Download document; check scope size against TZS 200m threshold | AJ12: Manual scan | AK12: d18f9ef1-b72a-460d-b8f1-44ec5ee41c81 | AL12: =IF(AND(OR(W12="Watching",W12="Preparing"),ISNUMBER(Q12)),IF(AND(Q12>='Friday Summary'!$C$4,Q12<='Friday Summary'!$C$4+14),Q12+ROW()/1000000,""),"")
A13: =IF(B13="","","OP-"&TEXT(ROW()-4,"000")) | B13: 35/2026/2027/W/01 | C13: 46289 | D13: NeST | E13: https://nest.go.tz/tenders/published-tenders | F13: National Prosecutions Service (NPS) | G13: government | H13: Proposed construction of NPS Regional Office building at Mara, Plot 611 Block C, Bweri, Musoma | I13: New regional office building | J13: Mara (Musoma) | K13: building | L13: NeST login needed | N13: unknown | O13: NeST login needed | P13: NeST login needed | Q13: 46295.583 | R13: NeST login needed | S13: N | T13: =IF(A13="","",IFERROR(INDEX('Bid-NoBid'!$T:$T,MATCH(A13,'Bid-NoBid'!$A:$A,0)),"")) | U13: =IF(A13="","",IFERROR(IF(OR(INDEX('Bid-NoBid'!$U:$U,MATCH(A13,'Bid-NoBid'!$A:$A,0))="",LEFT(INDEX('Bid-NoBid'!$U:$U,MATCH(A13,'Bid-NoBid'!$A:$A,0)),10)="Incomplete"),"Screen: "&AC13,INDEX('Bid-NoBid'!$U:$U,MATCH(A13,'Bid-NoBid'!$A:$A,0))),"Screen: "&AC13)) | W13: Watching | X13: Frank | AA13: 46288 | AB13: Small Works | AC13: Check | AD13: Good building type but remote from Dar and only 6 days left | AE13: =IF(ISNUMBER(Q13),ROUNDDOWN(Q13-NOW(),1),"") | AF13: =IF(OR(A13="",AE13=""),"",IF(NOT(OR(W13="Watching",W13="Preparing")),"",IF(AE13<0,"PASSED",IF(AND(AE13<=7,W13<>"Preparing"),"RED",IF(AE13<=14,"AMBER","GREEN"))))) | AG13: =IF(OR(A13="",NOT(OR(W13="Watching",W13="Preparing"))),"",IF(AND(ISNUMBER(M13),M13>=3000000000),"YES – ≥ TZS 3bn",IF(AND(ISNUMBER(AE13),AE13>=0,AE13<10,V13=""),"YES – <10 days",""))) | AI13: Check CRB class and whether a Mwanza/Mara team is available | AJ13: Manual scan | AK13: 039aa3e3-4ce1-4bfd-b38a-5bf4743ab974 | AL13: =IF(AND(OR(W13="Watching",W13="Preparing"),ISNUMBER(Q13)),IF(AND(Q13>='Friday Summary'!$C$4,Q13<='Friday Summary'!$C$4+14),Q13+ROW()/1000000,""),"")
A14: =IF(B14="","","OP-"&TEXT(ROW()-4,"000")) | B14: 43/2026/2027/W/04 | C14: 46289 | D14: NeST | E14: https://nest.go.tz/tenders/published-tenders | F14: Ministry of Agriculture | G14: government | H14: Proposed construction and rehabilitation of infrastructure for thirteen (13) Youth Agribusiness Incubation Centres (YABICs) | I14: Construction/rehabilitation at 13 centres (multi-site) | J14: Multiple regions | K14: building | L14: NeST login needed | N14: unknown | O14: NeST login needed | P14: NeST login needed | Q14: 46295.583 | R14: NeST login needed | S14: N | T14: =IF(A14="","",IFERROR(INDEX('Bid-NoBid'!$T:$T,MATCH(A14,'Bid-NoBid'!$A:$A,0)),"")) | U14: =IF(A14="","",IFERROR(IF(OR(INDEX('Bid-NoBid'!$U:$U,MATCH(A14,'Bid-NoBid'!$A:$A,0))="",LEFT(INDEX('Bid-NoBid'!$U:$U,MATCH(A14,'Bid-NoBid'!$A:$A,0)),10)="Incomplete"),"Screen: "&AC14,INDEX('Bid-NoBid'!$U:$U,MATCH(A14,'Bid-NoBid'!$A:$A,0))),"Screen: "&AC14)) | W14: Watching | X14: Frank | AA14: 46287 | AB14: Small Works | AC14: Check | AD14: Multi-site programme – logistics risk; check lots and locations | AE14: =IF(ISNUMBER(Q14),ROUNDDOWN(Q14-NOW(),1),"") | AF14: =IF(OR(A14="",AE14=""),"",IF(NOT(OR(W14="Watching",W14="Preparing")),"",IF(AE14<0,"PASSED",IF(AND(AE14<=7,W14<>"Preparing"),"RED",IF(AE14<=14,"AMBER","GREEN"))))) | AG14: =IF(OR(A14="",NOT(OR(W14="Watching",W14="Preparing"))),"",IF(AND(ISNUMBER(M14),M14>=3000000000),"YES – ≥ TZS 3bn",IF(AND(ISNUMBER(AE14),AE14>=0,AE14<10,V14=""),"YES – <10 days",""))) | AI14: Download document; see if lots can be bid separately | AJ14: Manual scan | AK14: 0b80faa8-5fe7-4559-800e-4609f3668ee9 | AL14: =IF(AND(OR(W14="Watching",W14="Preparing"),ISNUMBER(Q14)),IF(AND(Q14>='Friday Summary'!$C$4,Q14<='Friday Summary'!$C$4+14),Q14+ROW()/1000000,""),"")
A15: =IF(B15="","","OP-"&TEXT(ROW()-4,"000")) | B15: 7512/2026/2027/W/10 | C15: 46289 | D15: NeST | E15: https://nest.go.tz/tenders/published-tenders | F15: Moshi Municipal Council | G15: government | H15: Proposed construction of new secondary school at Karanga Ward | I15: New secondary school | J15: Kilimanjaro (Moshi) | K15: building | L15: NeST login needed | N15: unknown | O15: NeST login needed | P15: NeST login needed | Q15: 46295.417 | R15: NeST login needed | S15: N | T15: =IF(A15="","",IFERROR(INDEX('Bid-NoBid'!$T:$T,MATCH(A15,'Bid-NoBid'!$A:$A,0)),"")) | U15: =IF(A15="","",IFERROR(IF(OR(INDEX('Bid-NoBid'!$U:$U,MATCH(A15,'Bid-NoBid'!$A:$A,0))="",LEFT(INDEX('Bid-NoBid'!$U:$U,MATCH(A15,'Bid-NoBid'!$A:$A,0)),10)="Incomplete"),"Screen: "&AC15,INDEX('Bid-NoBid'!$U:$U,MATCH(A15,'Bid-NoBid'!$A:$A,0))),"Screen: "&AC15)) | W15: Watching | X15: Frank | AA15: 46288 | AB15: Small Works | AC15: Check | AD15: School experience fits; remote and 6 days left | AE15: =IF(ISNUMBER(Q15),ROUNDDOWN(Q15-NOW(),1),"") | AF15: =IF(OR(A15="",AE15=""),"",IF(NOT(OR(W15="Watching",W15="Preparing")),"",IF(AE15<0,"PASSED",IF(AND(AE15<=7,W15<>"Preparing"),"RED",IF(AE15<=14,"AMBER","GREEN"))))) | AG15: =IF(OR(A15="",NOT(OR(W15="Watching",W15="Preparing"))),"",IF(AND(ISNUMBER(M15),M15>=3000000000),"YES – ≥ TZS 3bn",IF(AND(ISNUMBER(AE15),AE15>=0,AE15<10,V15=""),"YES – <10 days",""))) | AI15: Check value and CRB class | AJ15: Manual scan | AK15: 7af4f481-9db1-4a99-a2f9-2d33bb37d0cd | AL15: =IF(AND(OR(W15="Watching",W15="Preparing"),ISNUMBER(Q15)),IF(AND(Q15>='Friday Summary'!$C$4,Q15<='Friday Summary'!$C$4+14),Q15+ROW()/1000000,""),"")
A16: =IF(B16="","","OP-"&TEXT(ROW()-4,"000")) | B16: 75F4/2026/2027/W/16 | C16: 46289 | D16: NeST | E16: https://nest.go.tz/tenders/published-tenders | F16: Hai District Council | G16: government | H16: Renovation works at Sere Ufundi and Kware primary schools | I16: Renovation of two primary schools | J16: Kilimanjaro (Hai) | K16: renovation | L16: NeST login needed | N16: unknown | O16: NeST login needed | P16: NeST login needed | Q16: 46295.583 | R16: NeST login needed | S16: N | T16: =IF(A16="","",IFERROR(INDEX('Bid-NoBid'!$T:$T,MATCH(A16,'Bid-NoBid'!$A:$A,0)),"")) | U16: =IF(A16="","",IFERROR(IF(OR(INDEX('Bid-NoBid'!$U:$U,MATCH(A16,'Bid-NoBid'!$A:$A,0))="",LEFT(INDEX('Bid-NoBid'!$U:$U,MATCH(A16,'Bid-NoBid'!$A:$A,0)),10)="Incomplete"),"Screen: "&AC16,INDEX('Bid-NoBid'!$U:$U,MATCH(A16,'Bid-NoBid'!$A:$A,0))),"Screen: "&AC16)) | W16: Watching | X16: Frank | AA16: 46288 | AB16: Small Works | AC16: Drop | AD16: Likely small value and remote | AE16: =IF(ISNUMBER(Q16),ROUNDDOWN(Q16-NOW(),1),"") | AF16: =IF(OR(A16="",AE16=""),"",IF(NOT(OR(W16="Watching",W16="Preparing")),"",IF(AE16<0,"PASSED",IF(AND(AE16<=7,W16<>"Preparing"),"RED",IF(AE16<=14,"AMBER","GREEN"))))) | AG16: =IF(OR(A16="",NOT(OR(W16="Watching",W16="Preparing"))),"",IF(AND(ISNUMBER(M16),M16>=3000000000),"YES – ≥ TZS 3bn",IF(AND(ISNUMBER(AE16),AE16>=0,AE16<10,V16=""),"YES – <10 days",""))) | AI16: Record only | AJ16: Manual scan | AK16: 5ad50d18-a16f-48b2-a35f-d06ad3239815 | AL16: =IF(AND(OR(W16="Watching",W16="Preparing"),ISNUMBER(Q16)),IF(AND(Q16>='Friday Summary'!$C$4,Q16<='Friday Summary'!$C$4+14),Q16+ROW()/1000000,""),"")
... A34: =IF(B34="","","OP-"&TEXT(ROW()-4,"000")) | B34: TR36/2026/2027/W/15 | C34: 46289 | D34: NeST | E34: https://nest.go.tz/tenders/published-tenders | F34: TANROADS (HQ) | G34: government | H34: Upgrading of Mika–Utegi–Shitati–Ruari Port Road to bitumen standard – Lot 1: Mika–Utegi–Bukama (27 km) including Mori Bridge | I34: 27 km road upgrade to bitumen including bridge | J34: Mara (Rorya) | K34: civil | L34: NeST login needed | N34: unknown | O34: NeST login needed | P34: NeST login needed | Q34: 46297.583 | R34: NeST login needed | S34: N | T34: =IF(A34="","",IFERROR(INDEX('Bid-NoBid'!$T:$T,MATCH(A34,'Bid-NoBid'!$A:$A,0)),"")) | U34: =IF(A34="","",IFERROR(IF(OR(INDEX('Bid-NoBid'!$U:$U,MATCH(A34,'Bid-NoBid'!$A:$A,0))="",LEFT(INDEX('Bid-NoBid'!$U:$U,MATCH(A34,'Bid-NoBid'!$A:$A,0)),10)="Incomplete"),"Screen: "&AC34,INDEX('Bid-NoBid'!$U:$U,MATCH(A34,'Bid-NoBid'!$A:$A,0))),"Screen: "&AC34)) | W34: Watching | X34: Frank | AA34: 46267 | AB34: Medium and Large Works | AC34: Drop | AD34: Large road works likely above Civil Class IV; only possible in a JV (MD decision) | AE34: =IF(ISNUMBER(Q34),ROUNDDOWN(Q34-NOW(),1),"") | AF34: =IF(OR(A34="",AE34=""),"",IF(NOT(OR(W34="Watching",W34="Preparing")),"",IF(AE34<0,"PASSED",IF(AND(AE34<=7,W34<>"Preparing"),"RED",IF(AE34<=14,"AMBER","GREEN"))))) | AG34: =IF(OR(A34="",NOT(OR(W34="Watching",W34="Preparing"))),"",IF(AND(ISNUMBER(M34),M34>=3000000000),"YES – ≥ TZS 3bn",IF(AND(ISNUMBER(AE34),AE34>=0,AE34<10,V34=""),"YES – <10 days",""))) | AI34: Escalate to MD: JV interest? Otherwise no-bid | AJ34: Manual scan | AK34: 623047f2-016b-435d-9afa-348a5f8058c5 | AL34: =IF(AND(OR(W34="Watching",W34="Preparing"),ISNUMBER(Q34)),IF(AND(Q34>='Friday Summary'!$C$4,Q34<='Friday Summary'!$C$4+14),Q34+ROW()/1000000,""),"")
A35: =IF(B35="","","OP-"&TEXT(ROW()-4,"000")) | B35: 8626/2026/2027/W/15 | C35: 46289 | D35: NeST | E35: https://nest.go.tz/tenders/published-tenders | F35: Tanga City Council | G35: government | H35: Proposed construction of administration block at Nguvumali Secondary School | I35: New administration block (quotation) | J35: Tanga | K35: building | L35: NeST login needed | N35: unknown | O35: NeST login needed | P35: NeST login needed | Q35: 46289.417 | R35: NeST login needed | S35: N | T35: =IF(A35="","",IFERROR(INDEX('Bid-NoBid'!$T:$T,MATCH(A35,'Bid-NoBid'!$A:$A,0)),"")) | U35: =IF(A35="","",IFERROR(IF(OR(INDEX('Bid-NoBid'!$U:$U,MATCH(A35,'Bid-NoBid'!$A:$A,0))="",LEFT(INDEX('Bid-NoBid'!$U:$U,MATCH(A35,'Bid-NoBid'!$A:$A,0)),10)="Incomplete"),"Screen: "&AC35,INDEX('Bid-NoBid'!$U:$U,MATCH(A35,'Bid-NoBid'!$A:$A,0))),"Screen: "&AC35)) | W35: Closed – missed | X35: Frank | Y35: Not submitted | Z35: Advertised 17 Sep with a 7-day window, closed before the first scan. NeST works windows are often 7 days – scan Mon and Thu without fail. | AA35: 46282 | AB35: Standard Invitation for Quotations -Works | AC35: Drop | AD35: Deadline passed 24 Sep 10:00 before first scan – relevant because Nordic is active in Tanga | AE35: =IF(ISNUMBER(Q35),ROUNDDOWN(Q35-NOW(),1),"") | AF35: =IF(OR(A35="",AE35=""),"",IF(NOT(OR(W35="Watching",W35="Preparing")),"",IF(AE35<0,"PASSED",IF(AND(AE35<=7,W35<>"Preparing"),"RED",IF(AE35<=14,"AMBER","GREEN"))))) | AG35: =IF(OR(A35="",NOT(OR(W35="Watching",W35="Preparing"))),"",IF(AND(ISNUMBER(M35),M35>=3000000000),"YES – ≥ TZS 3bn",IF(AND(ISNUMBER(AE35),AE35>=0,AE35<10,V35=""),"YES – <10 days",""))) | AI35: None – see Lessons | AJ35: Manual scan | AK35: 436fa632-e675-47fa-b97e-9289a191bd3c | AL35: =IF(AND(OR(W35="Watching",W35="Preparing"),ISNUMBER(Q35)),IF(AND(Q35>='Friday Summary'!$C$4,Q35<='Friday Summary'!$C$4+14),Q35+ROW()/1000000,""),"")
A36: =IF(B36="","","OP-"&TEXT(ROW()-4,"000")) | B36: TR214/2026/2027/W/10 | C36: 46291 | D36: NeST | E36: https://nest.go.tz/tenders/published-tenders | F36: Tanzania Fertilizer Company | G36: parastatal (verify) | H36: Construction of Retaining wall pre-casted (Jersey Blocks) for blending facility | I36: From NeST notice (1 lot) – read the tender document | J36: Dar es Salaam (Ubungo) (from client's office – confirm site) | K36: building | L36: NeST login needed | N36: unknown | O36: NeST login needed | P36: NeST login needed | Q36: 46297.583 | R36: NeST login needed | S36: N | T36: =IF(A36="","",IFERROR(INDEX('Bid-NoBid'!$T:$T,MATCH(A36,'Bid-NoBid'!$A:$A,0)),"")) | U36: =IF(A36="","",IFERROR(IF(OR(INDEX('Bid-NoBid'!$U:$U,MATCH(A36,'Bid-NoBid'!$A:$A,0))="",LEFT(INDEX('Bid-NoBid'!$U:$U,MATCH(A36,'Bid-NoBid'!$A:$A,0)),10)="Incomplete"),"Screen: "&AC36,INDEX('Bid-NoBid'!$U:$U,MATCH(A36,'Bid-NoBid'!$A:$A,0))),"Screen: "&AC36)) | W36: Watching | X36: Frank | AA36: 46290 | AB36: Standard Invitation for Quotations -Works / Planned Tender | AC36: Check | AD36: Auto (Standard Invitation for Quotations -Works / Planned Tender): Quotation route – value may be below TZS 200m | AE36: =IF(ISNUMBER(Q36),ROUNDDOWN(Q36-NOW(),1),"") | AF36: =IF(OR(A36="",AE36=""),"",IF(NOT(OR(W36="Watching",W36="Preparing")),"",IF(AE36<0,"PASSED",IF(AND(AE36<=7,W36<>"Preparing"),"RED",IF(AE36<=14,"AMBER","GREEN"))))) | AG36: =IF(OR(A36="",NOT(OR(W36="Watching",W36="Preparing"))),"",IF(AND(ISNUMBER(M36),M36>=3000000000),"YES – ≥ TZS 3bn",IF(AND(ISNUMBER(AE36),AE36>=0,AE36<10,V36=""),"YES – <10 days",""))) | AI36: Read the notice and decide with the QS Director whether to pursue | AJ36: Auto-scan | AK36: 3759493a-b118-4946-b97b-da9c8bdfc677 | AL36: =IF(AND(OR(W36="Watching",W36="Preparing"),ISNUMBER(Q36)),IF(AND(Q36>='Friday Summary'!$C$4,Q36<='Friday Summary'!$C$4+14),Q36+ROW()/1000000,""),"")
A37: =IF(B37="","","OP-"&TEXT(ROW()-4,"000")) | B37: 83/2026/2027/W/08 | C37: 46291 | D37: NeST | E37: https://nest.go.tz/tenders/published-tenders | F37: Shinyanga Regional Secretariat | G37: government | H37: To rehabilitate Regional Commissioner's Office, Confidential Registry and residence house for Assistant Administrative secretaries. | I37: From NeST notice (1 lot) – read the tender document | J37: Shinyanga (from client's office – confirm site) | K37: building | L37: NeST login needed | N37: unknown | O37: NeST login needed | P37: NeST login needed | Q37: 46300.583 | R37: NeST login needed | S37: N | T37: =IF(A37="","",IFERROR(INDEX('Bid-NoBid'!$T:$T,MATCH(A37,'Bid-NoBid'!$A:$A,0)),"")) | U37: =IF(A37="","",IFERROR(IF(OR(INDEX('Bid-NoBid'!$U:$U,MATCH(A37,'Bid-NoBid'!$A:$A,0))="",LEFT(INDEX('Bid-NoBid'!$U:$U,MATCH(A37,'Bid-NoBid'!$A:$A,0)),10)="Incomplete"),"Screen: "&AC37,INDEX('Bid-NoBid'!$U:$U,MATCH(A37,'Bid-NoBid'!$A:$A,0))),"Screen: "&AC37)) | W37: Watching | X37: Frank | AA37: 46290 | AB37: Small Works / Tender | AC37: Check | AD37: Auto (Small Works / Tender): Building works but remote from Dar | AE37: =IF(ISNUMBER(Q37),ROUNDDOWN(Q37-NOW(),1),"") | AF37: =IF(OR(A37="",AE37=""),"",IF(NOT(OR(W37="Watching",W37="Preparing")),"",IF(AE37<0,"PASSED",IF(AND(AE37<=7,W37<>"Preparing"),"RED",IF(AE37<=14,"AMBER","GREEN"))))) | AG37: =IF(OR(A37="",NOT(OR(W37="Watching",W37="Preparing"))),"",IF(AND(ISNUMBER(M37),M37>=3000000000),"YES – ≥ TZS 3bn",IF(AND(ISNUMBER(AE37),AE37>=0,AE37<10,V37=""),"YES – <10 days",""))) | AI37: Read the notice and decide with the QS Director whether to pursue | AJ37: Auto-scan | AK37: 31257613-ab2c-4569-b096-277031c9bd9d | AL37: =IF(AND(OR(W37="Watching",W37="Preparing"),ISNUMBER(Q37)),IF(AND(Q37>='Friday Summary'!$C$4,Q37<='Friday Summary'!$C$4+14),Q37+ROW()/1000000,""),"")
A38: =IF(B38="","","OP-"&TEXT(ROW()-4,"000")) | B38: (not shown) | C38: 46291 | D38: press | E38: https://www.ddotenders.co.tz/tender.php?page=home | F38: High Commission of India | G38: government | H38: Maintenance of building and equipments | I38: From press notice (1 lot) – read the tender document | J38: Dar es Salaam | K38: building | L38: See tender document | N38: unknown | O38: See tender document | P38: See tender document | Q38: 46295.417 | R38: See tender document | S38: N | T38: =IF(A38="","",IFERROR(INDEX('Bid-NoBid'!$T:$T,MATCH(A38,'Bid-NoBid'!$A:$A,0)),"")) | U38: =IF(A38="","",IFERROR(IF(OR(INDEX('Bid-NoBid'!$U:$U,MATCH(A38,'Bid-NoBid'!$A:$A,0))="",LEFT(INDEX('Bid-NoBid'!$U:$U,MATCH(A38,'Bid-NoBid'!$A:$A,0)),10)="Incomplete"),"Screen: "&AC38,INDEX('Bid-NoBid'!$U:$U,MATCH(A38,'Bid-NoBid'!$A:$A,0))),"Screen: "&AC38)) | W38: Watching | X38: Frank | AA38: 46288 | AB38: DDO Tenders (newspaper / private / donor) | AC38: Pursue | AD38: Auto (DDO Tenders): Building works within reach of Dar · deadline read from the web page – confirm | AE38: =IF(ISNUMBER(Q38),ROUNDDOWN(Q38-NOW(),1),"") | AF38: =IF(OR(A38="",AE38=""),"",IF(NOT(OR(W38="Watching",W38="Preparing")),"",IF(AE38<0,"PASSED",IF(AND(AE38<=7,W38<>"Preparing"),"RED",IF(AE38<=14,"AMBER","GREEN"))))) | AG38: =IF(OR(A38="",NOT(OR(W38="Watching",W38="Preparing"))),"",IF(AND(ISNUMBER(M38),M38>=3000000000),"YES – ≥ TZS 3bn",IF(AND(ISNUMBER(AE38),AE38>=0,AE38<10,V38=""),"YES – <10 days",""))) | AI38: Get the tender document, confirm value, CRB class, site visit and bid security; brief the MD | AJ38: Auto-scan | AK38: DDO:3048 | AL38: =IF(AND(OR(W38="Watching",W38="Preparing"),ISNUMBER(Q38)),IF(AND(Q38>='Friday Summary'!$C$4,Q38<='Friday Summary'!$C$4+14),Q38+ROW()/1000000,""),"")
A39: =IF(B39="","","OP-"&TEXT(ROW()-4,"000")) | B39: GIZ/DTC/7000022671/2026 | C39: 46291 | D39: press | E39: https://www.ddotenders.co.tz/tender.php?page=home | F39: giz | G39: government | H39: Capacity building project | I39: From press notice (1 lot) – read the tender document | J39: Dar es Salaam | K39: building | L39: See tender document | N39: unknown | O39: See tender document | P39: See tender document | Q39: 46300.417 | R39: See tender document | S39: N | T39: =IF(A39="","",IFERROR(INDEX('Bid-NoBid'!$T:$T,MATCH(A39,'Bid-NoBid'!$A:$A,0)),"")) | U39: =IF(A39="","",IFERROR(IF(OR(INDEX('Bid-NoBid'!$U:$U,MATCH(A39,'Bid-NoBid'!$A:$A,0))="",LEFT(INDEX('Bid-NoBid'!$U:$U,MATCH(A39,'Bid-NoBid'!$A:$A,0)),10)="Incomplete"),"Screen: "&AC39,INDEX('Bid-NoBid'!$U:$U,MATCH(A39,'Bid-NoBid'!$A:$A,0))),"Screen: "&AC39)) | W39: Watching | X39: Frank | AA39: 46289 | AB39: DDO Tenders (newspaper / private / donor) | AC39: Pursue | AD39: Auto (DDO Tenders): Building works within reach of Dar · deadline read from the web page – confirm | AE39: =IF(ISNUMBER(Q39),ROUNDDOWN(Q39-NOW(),1),"") | AF39: =IF(OR(A39="",AE39=""),"",IF(NOT(OR(W39="Watching",W39="Preparing")),"",IF(AE39<0,"PASSED",IF(AND(AE39<=7,W39<>"Preparing"),"RED",IF(AE39<=14,"AMBER","GREEN"))))) | AG39: =IF(OR(A39="",NOT(OR(W39="Watching",W39="Preparing"))),"",IF(AND(ISNUMBER(M39),M39>=3000000000),"YES – ≥ TZS 3bn",IF(AND(ISNUMBER(AE39),AE39>=0,AE39<10,V39=""),"YES – <10 days",""))) | AI39: Get the tender document, confirm value, CRB class, site visit and bid security; brief the MD | AJ39: Auto-scan | AK39: DDO:3053 | AL39: =IF(AND(OR(W39="Watching",W39="Preparing"),ISNUMBER(Q39)),IF(AND(Q39>='Friday Summary'!$C$4,Q39<='Friday Summary'!$C$4+14),Q39+ROW()/1000000,""),"")
A40: =IF(B40="","","OP-"&TEXT(ROW()-4,"000")) | B40: TPL/2026/ENG/0010 | C40: 46291 | D40: press | E40: https://www.ddotenders.co.tz/tender.php?page=home | F40: See advert | G40: government | H40: Construction of toilets for police camps | I40: From press notice (1 lot) – read the tender document | J40: Dar es Salaam | K40: building | L40: See tender document | N40: unknown | O40: See tender document | P40: See tender document | Q40: 46304.417 | R40: See tender document | S40: N | T40: =IF(A40="","",IFERROR(INDEX('Bid-NoBid'!$T:$T,MATCH(A40,'Bid-NoBid'!$A:$A,0)),"")) | U40: =IF(A40="","",IFERROR(IF(OR(INDEX('Bid-NoBid'!$U:$U,MATCH(A40,'Bid-NoBid'!$A:$A,0))="",LEFT(INDEX('Bid-NoBid'!$U:$U,MATCH(A40,'Bid-NoBid'!$A:$A,0)),10)="Incomplete"),"Screen: "&AC40,INDEX('Bid-NoBid'!$U:$U,MATCH(A40,'Bid-NoBid'!$A:$A,0))),"Screen: "&AC40)) | W40: Watching | X40: Frank | AA40: 46288 | AB40: DDO Tenders (newspaper / private / donor) | AC40: Pursue | AD40: Auto (DDO Tenders): Building works within reach of Dar · deadline read from the web page – confirm | AE40: =IF(ISNUMBER(Q40),ROUNDDOWN(Q40-NOW(),1),"") | AF40: =IF(OR(A40="",AE40=""),"",IF(NOT(OR(W40="Watching",W40="Preparing")),"",IF(AE40<0,"PASSED",IF(AND(AE40<=7,W40<>"Preparing"),"RED",IF(AE40<=14,"AMBER","GREEN"))))) | AG40: =IF(OR(A40="",NOT(OR(W40="Watching",W40="Preparing"))),"",IF(AND(ISNUMBER(M40),M40>=3000000000),"YES – ≥ TZS 3bn",IF(AND(ISNUMBER(AE40),AE40>=0,AE40<10,V40=""),"YES – <10 days",""))) | AI40: Get the tender document, confirm value, CRB class, site visit and bid security; brief the MD | AJ40: Auto-scan | AK40: DDO:3050 | AL40: =IF(AND(OR(W40="Watching",W40="Preparing"),ISNUMBER(Q40)),IF(AND(Q40>='Friday Summary'!$C$4,Q40<='Friday Summary'!$C$4+14),Q40+ROW()/1000000,""),"")
A41: =IF(B41="","","OP-"&TEXT(ROW()-4,"000")) | B41: (not shown) | C41: 46291 | D41: press | E41: https://www.ddotenders.co.tz/tender.php?page=home | F41: TAZAMA Pipelines Limited | G41: parastatal (verify) | H41: Construction of Petroleum Pipeline | I41: From press notice (1 lot) – read the tender document | J41: Dar es Salaam | K41: civil | L41: See tender document | N41: unknown | O41: See tender document | P41: See tender document | Q41: 46318.417 | R41: See tender document | S41: N | T41: =IF(A41="","",IFERROR(INDEX('Bid-NoBid'!$T:$T,MATCH(A41,'Bid-NoBid'!$A:$A,0)),"")) | U41: =IF(A41="","",IFERROR(IF(OR(INDEX('Bid-NoBid'!$U:$U,MATCH(A41,'Bid-NoBid'!$A:$A,0))="",LEFT(INDEX('Bid-NoBid'!$U:$U,MATCH(A41,'Bid-NoBid'!$A:$A,0)),10)="Incomplete"),"Screen: "&AC41,INDEX('Bid-NoBid'!$U:$U,MATCH(A41,'Bid-NoBid'!$A:$A,0))),"Screen: "&AC41)) | W41: Watching | X41: Frank | AA41: 46281 | AB41: DDO Tenders (newspaper / private / donor) | AC41: Check | AD41: Auto (DDO Tenders): Civil works in Dar/Coast – confirm CRB class and margin · deadline read from the web page – confirm | AE41: =IF(ISNUMBER(Q41),ROUNDDOWN(Q41-NOW(),1),"") | AF41: =IF(OR(A41="",AE41=""),"",IF(NOT(OR(W41="Watching",W41="Preparing")),"",IF(AE41<0,"PASSED",IF(AND(AE41<=7,W41<>"Preparing"),"RED",IF(AE41<=14,"AMBER","GREEN"))))) | AG41: =IF(OR(A41="",NOT(OR(W41="Watching",W41="Preparing"))),"",IF(AND(ISNUMBER(M41),M41>=3000000000),"YES – ≥ TZS 3bn",IF(AND(ISNUMBER(AE41),AE41>=0,AE41<10,V41=""),"YES – <10 days",""))) | AI41: Read the notice and decide with the QS Director whether to pursue | AJ41: Auto-scan | AK41: DDO:3033 | AL41: =IF(AND(OR(W41="Watching",W41="Preparing"),ISNUMBER(Q41)),IF(AND(Q41>='Friday Summary'!$C$4,Q41<='Friday Summary'!$C$4+14),Q41+ROW()/1000000,""),"")
A42: =IF(B42="","","OP-"&TEXT(ROW()-4,"000")) | B42: 71B6/2026/2027/W/01 | C42: 46291 | D42: NeST | E42: https://nest.go.tz/tenders/published-tenders | F42: Mkuranga District Council | G42: government | H42: Proposed construction of One Market center for Entrepreneurship purposes at Mkuranga DC | I42: From NeST notice (1 lot) – read the tender document | J42: Pwani (Mkuranga) | K42: building | L42: NeST login needed | N42: unknown | O42: NeST login needed | P42: NeST login needed | Q42: 46297.417 | R42: NeST login needed | S42: N | T42: =IF(A42="","",IFERROR(INDEX('Bid-NoBid'!$T:$T,MATCH(A42,'Bid-NoBid'!$A:$A,0)),"")) | U42: =IF(A42="","",IFERROR(IF(OR(INDEX('Bid-NoBid'!$U:$U,MATCH(A42,'Bid-NoBid'!$A:$A,0))="",LEFT(INDEX('Bid-NoBid'!$U:$U,MATCH(A42,'Bid-NoBid'!$A:$A,0)),10)="Incomplete"),"Screen: "&AC42,INDEX('Bid-NoBid'!$U:$U,MATCH(A42,'Bid-NoBid'!$A:$A,0))),"Screen: "&AC42)) | W42: Watching | X42: Frank | AA42: 46290 | AB42: Small Works / Tender | AC42: Pursue | AD42: Auto (Small Works / Tender): Building works within reach of Dar | AE42: =IF(ISNUMBER(Q42),ROUNDDOWN(Q42-NOW(),1),"") | AF42: =IF(OR(A42="",AE42=""),"",IF(NOT(OR(W42="Watching",W42="Preparing")),"",IF(AE42<0,"PASSED",IF(AND(AE42<=7,W42<>"Preparing"),"RED",IF(AE42<=14,"AMBER","GREEN"))))) | AG42: =IF(OR(A42="",NOT(OR(W42="Watching",W42="Preparing"))),"",IF(AND(ISNUMBER(M42),M42>=3000000000),"YES – ≥ TZS 3bn",IF(AND(ISNUMBER(AE42),AE42>=0,AE42<10,V42=""),"YES – <10 days",""))) | AI42: Get the tender document, confirm value, CRB class, site visit and bid security; brief the MD | AJ42: Auto-scan | AK42: 81ede21a-8848-41d2-acc1-19a0f401563d | AL42: =IF(AND(OR(W42="Watching",W42="Preparing"),ISNUMBER(Q42)),IF(AND(Q42>='Friday Summary'!$C$4,Q42<='Friday Summary'!$C$4+14),Q42+ROW()/1000000,""),"")
A43: =IF(B43="","","OP-"&TEXT(ROW()-4,"000")) | B43: S10/001/2026/2027/W/33 | C43: 46292 | D43: NeST | E43: https://nest.go.tz/tenders/published-tenders | F43: TARURA - Arusha Regional Office | G43: government | H43: Construction of RC Bridge along Selela - Mbaash road | I43: From NeST notice (1 lot) – read the tender document | J43: Arusha (from client's office – confirm site) | K43: civil | L43: NeST login needed | N43: unknown | O43: NeST login needed | P43: NeST login needed | Q43: 46296.417 | R43: NeST login needed | S43: N | T43: =IF(A43="","",IFERROR(INDEX('Bid-NoBid'!$T:$T,MATCH(A43,'Bid-NoBid'!$A:$A,0)),"")) | U43: =IF(A43="","",IFERROR(IF(OR(INDEX('Bid-NoBid'!$U:$U,MATCH(A43,'Bid-NoBid'!$A:$A,0))="",LEFT(INDEX('Bid-NoBid'!$U:$U,MATCH(A43,'Bid-NoBid'!$A:$A,0)),10)="Incomplete"),"Screen: "&AC43,INDEX('Bid-NoBid'!$U:$U,MATCH(A43,'Bid-NoBid'!$A:$A,0))),"Screen: "&AC43)) | W43: Watching | X43: Frank | AA43: 46289 | AB43: Small Works / Tender | AC43: Check | AD43: Auto (Small Works / Tender): Construction tender kept for review (would have been dropped: Remote civil works) | AE43: =IF(ISNUMBER(Q43),ROUNDDOWN(Q43-NOW(),1),"") | AF43: =IF(OR(A43="",AE43=""),"",IF(NOT(OR(W43="Watching",W43="Preparing")),"",IF(AE43<0,"PASSED",IF(AND(AE43<=7,W43<>"Preparing"),"RED",IF(AE43<=14,"AMBER","GREEN"))))) | AG43: =IF(OR(A43="",NOT(OR(W43="Watching",W43="Preparing"))),"",IF(AND(ISNUMBER(M43),M43>=3000000000),"YES – ≥ TZS 3bn",IF(AND(ISNUMBER(AE43),AE43>=0,AE43<10,V43=""),"YES – <10 days",""))) | AI43: Read the notice and decide with the QS Director whether to pursue | AJ43: Auto-scan | AK43: 21d250d4-c78a-4692-b47e-c2aa6d201f38 | AL43: =IF(AND(OR(W43="Watching",W43="Preparing"),ISNUMBER(Q43)),IF(AND(Q43>='Friday Summary'!$C$4,Q43<='Friday Summary'!$C$4+14),Q43+ROW()/1000000,""),"")
A44: =IF(B44="","","OP-"&TEXT(ROW()-4,"000")) | B44: S10/025/2026/2027/W/69 | C44: 46292 | D44: NeST | E44: https://nest.go.tz/tenders/published-tenders | F44: TARURA - Tabora Regional Office | G44: government | H44: Periodic Maintenance Works 19.53km And Construction of 14 Box Culverts Along Simbo - Utuja - Uyui Border Road, Periodic Maintenance Works 12.67km And Construction of 6 Box Culverts Along Mwakadele - Chalamo Road and Periodic Maintenance Works 15km And Construction of 5 Box Culverts Along Igoweko - Simbo Road In Igunga District | I44: From NeST notice (1 lot) – read the tender document | J44: Tabora (Igunga) | K44: civil | L44: NeST login needed | N44: unknown | O44: NeST login needed | P44: NeST login needed | Q44: 46296.542 | R44: NeST login needed | S44: N | T44: =IF(A44="","",IFERROR(INDEX('Bid-NoBid'!$T:$T,MATCH(A44,'Bid-NoBid'!$A:$A,0)),"")) | U44: =IF(A44="","",IFERROR(IF(OR(INDEX('Bid-NoBid'!$U:$U,MATCH(A44,'Bid-NoBid'!$A:$A,0))="",LEFT(INDEX('Bid-NoBid'!$U:$U,MATCH(A44,'Bid-NoBid'!$A:$A,0)),10)="Incomplete"),"Screen: "&AC44,INDEX('Bid-NoBid'!$U:$U,MATCH(A44,'Bid-NoBid'!$A:$A,0))),"Screen: "&AC44)) | W44: Watching | X44: Frank | AA44: 46289 | AB44: Small Works / Tender | AC44: Check | AD44: Auto (Small Works / Tender): Construction tender kept for review (would have been dropped: Remote civil works) | AE44: =IF(ISNUMBER(Q44),ROUNDDOWN(Q44-NOW(),1),"") | AF44: =IF(OR(A44="",AE44=""),"",IF(NOT(OR(W44="Watching",W44="Preparing")),"",IF(AE44<0,"PASSED",IF(AND(AE44<=7,W44<>"Preparing"),"RED",IF(AE44<=14,"AMBER","GREEN"))))) | AG44: =IF(OR(A44="",NOT(OR(W44="Watching",W44="Preparing"))),"",IF(AND(ISNUMBER(M44),M44>=3000000000),"YES – ≥ TZS 3bn",IF(AND(ISNUMBER(AE44),AE44>=0,AE44<10,V44=""),"YES – <10 days",""))) | AI44: Read the notice and decide with the QS Director whether to pursue | AJ44: Auto-scan | AK44: 7f37e5d6-d2b8-40eb-ab77-6716c4186aef | AL44: =IF(AND(OR(W44="Watching",W44="Preparing"),ISNUMBER(Q44)),IF(AND(Q44>='Friday Summary'!$C$4,Q44<='Friday Summary'!$C$4+14),Q44+ROW()/1000000,""),"")
A45: =IF(B45="","","OP-"&TEXT(ROW()-4,"000")) | B45: TR219/003/2026/2027/W/08 | C45: 46292 | D45: NeST | E45: https://nest.go.tz/tenders/published-tenders | F45: TANAPA - Southern Zone | G45: government | H45: Construction of 400 Meters Long Boardwalk at Kitulo National Park | I45: From NeST notice (1 lot) – read the tender document | J45: Mbeya (Mbarali) (from client's office – confirm site) | K45: building | L45: NeST login needed | N45: unknown | O45: NeST login needed | P45: NeST login needed | Q45: 46297.583 | R45: NeST login needed | S45: N | T45: =IF(A45="","",IFERROR(INDEX('Bid-NoBid'!$T:$T,MATCH(A45,'Bid-NoBid'!$A:$A,0)),"")) | U45: =IF(A45="","",IFERROR(IF(OR(INDEX('Bid-NoBid'!$U:$U,MATCH(A45,'Bid-NoBid'!$A:$A,0))="",LEFT(INDEX('Bid-NoBid'!$U:$U,MATCH(A45,'Bid-NoBid'!$A:$A,0)),10)="Incomplete"),"Screen: "&AC45,INDEX('Bid-NoBid'!$U:$U,MATCH(A45,'Bid-NoBid'!$A:$A,0))),"Screen: "&AC45)) | W45: Watching | X45: Frank | AA45: 46290 | AB45: Standard Invitation for Quotations -Works / Planned Tender | AC45: Check | AD45: Auto (Standard Invitation for Quotations -Works / Planned Tender): Construction tender kept for review (would have been dropped: Remote and closing soon) | AE45: =IF(ISNUMBER(Q45),ROUNDDOWN(Q45-NOW(),1),"") | AF45: =IF(OR(A45="",AE45=""),"",IF(NOT(OR(W45="Watching",W45="Preparing")),"",IF(AE45<0,"PASSED",IF(AND(AE45<=7,W45<>"Preparing"),"RED",IF(AE45<=14,"AMBER","GREEN"))))) | AG45: =IF(OR(A45="",NOT(OR(W45="Watching",W45="Preparing"))),"",IF(AND(ISNUMBER(M45),M45>=3000000000),"YES – ≥ TZS 3bn",IF(AND(ISNUMBER(AE45),AE45>=0,AE45<10,V45=""),"YES – <10 days",""))) | AI45: Read the notice and decide with the QS Director whether to pursue | AJ45: Auto-scan | AK45: d2ae202b-08fd-4650-b448-193f5e653238 | AL45: =IF(AND(OR(W45="Watching",W45="Preparing"),ISNUMBER(Q45)),IF(AND(Q45>='Friday Summary'!$C$4,Q45<='Friday Summary'!$C$4+14),Q45+ROW()/1000000,""),"")
A46: =IF(B46="","","OP-"&TEXT(ROW()-4,"000")) | B46: TR36/001/2026/2027/W/48 | C46: 46292 | D46: NeST | E46: https://nest.go.tz/tenders/published-tenders | F46: TANROADS - Arusha Regional Office | G46: government | H46: Rehabilitation works of Karatu JCT - Mang'ola - Matala, Karatu Njiapanda - Matala, Makao Kimba - Matala Roads (Gravel Standard) and Construction of Drainage Structures at Njiapanda - Matala. | I46: From NeST notice (1 lot) – read the tender document | J46: Arusha (from client's office – confirm site) | K46: renovation | L46: NeST login needed | N46: unknown | O46: NeST login needed | P46: NeST login needed | Q46: 46297.583 | R46: NeST login needed | S46: N | T46: =IF(A46="","",IFERROR(INDEX('Bid-NoBid'!$T:$T,MATCH(A46,'Bid-NoBid'!$A:$A,0)),"")) | U46: =IF(A46="","",IFERROR(IF(OR(INDEX('Bid-NoBid'!$U:$U,MATCH(A46,'Bid-NoBid'!$A:$A,0))="",LEFT(INDEX('Bid-NoBid'!$U:$U,MATCH(A46,'Bid-NoBid'!$A:$A,0)),10)="Incomplete"),"Screen: "&AC46,INDEX('Bid-NoBid'!$U:$U,MATCH(A46,'Bid-NoBid'!$A:$A,0))),"Screen: "&AC46)) | W46: Watching | X46: Frank | AA46: 46290 | AB46: Small Works / Tender | AC46: Check | AD46: Auto (Small Works / Tender): Construction tender kept for review (would have been dropped: Remote and closing soon) | AE46: =IF(ISNUMBER(Q46),ROUNDDOWN(Q46-NOW(),1),"") | AF46: =IF(OR(A46="",AE46=""),"",IF(NOT(OR(W46="Watching",W46="Preparing")),"",IF(AE46<0,"PASSED",IF(AND(AE46<=7,W46<>"Preparing"),"RED",IF(AE46<=14,"AMBER","GREEN"))))) | AG46: =IF(OR(A46="",NOT(OR(W46="Watching",W46="Preparing"))),"",IF(AND(ISNUMBER(M46),M46>=3000000000),"YES – ≥ TZS 3bn",IF(AND(ISNUMBER(AE46),AE46>=0,AE46<10,V46=""),"YES – <10 days",""))) | AI46: Read the notice and decide with the QS Director whether to pursue | AJ46: Auto-scan | AK46: 215bdca8-8314-4274-892b-08df2a6cd22e | AL46: =IF(AND(OR(W46="Watching",W46="Preparing"),ISNUMBER(Q46)),IF(AND(Q46>='Friday Summary'!$C$4,Q46<='Friday Summary'!$C$4+14),Q46+ROW()/1000000,""),"")
A47: =IF(B47="","","OP-"&TEXT(ROW()-4,"000")) | B47: S10/074/2026/2027/W/56 | C47: 46292 | D47: NeST | E47: https://nest.go.tz/tenders/published-tenders | F47: TARURA - Kigoma Regional Office | G47: government | H47: Construction of Box Culvert at Ruzuguma River Along Mlati - Kagongo Road in Kigoma DC | I47: From NeST notice (1 lot) – read the tender document | J47: Kigoma | K47: civil | L47: NeST login needed | N47: unknown | O47: NeST login needed | P47: NeST login needed | Q47: 46297.583 | R47: NeST login needed | S47: N | T47: =IF(A47="","",IFERROR(INDEX('Bid-NoBid'!$T:$T,MATCH(A47,'Bid-NoBid'!$A:$A,0)),"")) | U47: =IF(A47="","",IFERROR(IF(OR(INDEX('Bid-NoBid'!$U:$U,MATCH(A47,'Bid-NoBid'!$A:$A,0))="",LEFT(INDEX('Bid-NoBid'!$U:$U,MATCH(A47,'Bid-NoBid'!$A:$A,0)),10)="Incomplete"),"Screen: "&AC47,INDEX('Bid-NoBid'!$U:$U,MATCH(A47,'Bid-NoBid'!$A:$A,0))),"Screen: "&AC47)) | W47: Watching | X47: Frank | AA47: 46290 | AB47: Small Works / Tender | AC47: Check | AD47: Auto (Small Works / Tender): Construction tender kept for review (would have been dropped: Remote civil works) | AE47: =IF(ISNUMBER(Q47),ROUNDDOWN(Q47-NOW(),1),"") | AF47: =IF(OR(A47="",AE47=""),"",IF(NOT(OR(W47="Watching",W47="Preparing")),"",IF(AE47<0,"PASSED",IF(AND(AE47<=7,W47<>"Preparing"),"RED",IF(AE47<=14,"AMBER","GREEN"))))) | AG47: =IF(OR(A47="",NOT(OR(W47="Watching",W47="Preparing"))),"",IF(AND(ISNUMBER(M47),M47>=3000000000),"YES – ≥ TZS 3bn",IF(AND(ISNUMBER(AE47),AE47>=0,AE47<10,V47=""),"YES – <10 days",""))) | AI47: Read the notice and decide with the QS Director whether to pursue | AJ47: Auto-scan | AK47: 2b7dd442-571f-46df-9686-9e5e50c548f5 | AL47: =IF(AND(OR(W47="Watching",W47="Preparing"),ISNUMBER(Q47)),IF(AND(Q47>='Friday Summary'!$C$4,Q47<='Friday Summary'!$C$4+14),Q47+ROW()/1000000,""),"")
... A59: =IF(B59="","","OP-"&TEXT(ROW()-4,"000")) | B59: TR36/008/2026/2027/W/42 | C59: 46296 | D59: NeST | E59: https://nest.go.tz/tenders/published-tenders | F59: TANROADS - Kigoma Regional Office | G59: government | H59: Construction Box Culvert and Catchwater Drain along Kigoma - Ujiji Paved Trunk Road | I59: From NeST notice (1 lot) – read the tender document | J59: Kigoma | K59: civil | L59: NeST login needed | N59: unknown | O59: NeST login needed | P59: NeST login needed | Q59: 46303.583 | R59: NeST login needed | S59: N | T59: =IF(A59="","",IFERROR(INDEX('Bid-NoBid'!$T:$T,MATCH(A59,'Bid-NoBid'!$A:$A,0)),"")) | U59: =IF(A59="","",IFERROR(IF(OR(INDEX('Bid-NoBid'!$U:$U,MATCH(A59,'Bid-NoBid'!$A:$A,0))="",LEFT(INDEX('Bid-NoBid'!$U:$U,MATCH(A59,'Bid-NoBid'!$A:$A,0)),10)="Incomplete"),"Screen: "&AC59,INDEX('Bid-NoBid'!$U:$U,MATCH(A59,'Bid-NoBid'!$A:$A,0))),"Screen: "&AC59)) | W59: Watching | X59: Frank | AA59: 46296 | AB59: Small Works / Tender | AC59: Check | AD59: Auto (Small Works / Tender): Construction tender kept for review (would have been dropped: Remote civil works) | AE59: =IF(ISNUMBER(Q59),ROUNDDOWN(Q59-NOW(),1),"") | AF59: =IF(OR(A59="",AE59=""),"",IF(NOT(OR(W59="Watching",W59="Preparing")),"",IF(AE59<0,"PASSED",IF(AND(AE59<=7,W59<>"Preparing"),"RED",IF(AE59<=14,"AMBER","GREEN"))))) | AG59: =IF(OR(A59="",NOT(OR(W59="Watching",W59="Preparing"))),"",IF(AND(ISNUMBER(M59),M59>=3000000000),"YES – ≥ TZS 3bn",IF(AND(ISNUMBER(AE59),AE59>=0,AE59<10,V59=""),"YES – <10 days",""))) | AI59: Read the notice and decide with the QS Director whether to pursue | AJ59: Auto-scan | AK59: 2ecad80f-1cb6-40a7-8d62-4ada928b9c16 | AL59: =IF(AND(OR(W59="Watching",W59="Preparing"),ISNUMBER(Q59)),IF(AND(Q59>='Friday Summary'!$C$4,Q59<='Friday Summary'!$C$4+14),Q59+ROW()/1000000,""),"")
A60: =IF(B60="","","OP-"&TEXT(ROW()-4,"000")) | B60: (not shown) | C60: 46296 | D60: press | E60: https://www.tanzaniatenders.com/tender/usambazaji-na-ufungaji-wa-milango-ya-mbao-katika-ujenzi-wa-ofisi-za-tarafa-zoisa-makang-wa-kibakwe-8f3c6e5.php | F60: See advert | G60: government | H60: Usambazaji Na Ufungaji Wa Milango Ya Mbao Katika Ujenzi Wa Ofisi Za Tarafa Zoisa, Makang'wa, Kibakwe, Mundemu, Pahi Na Goima | I60: From press notice (1 lot) – read the tender document | J60: Not stated – read the notice | K60: building | L60: See tender document | N60: unknown | O60: See tender document | P60: See tender document | Q60: 46303.417 | R60: See tender document | S60: N | T60: =IF(A60="","",IFERROR(INDEX('Bid-NoBid'!$T:$T,MATCH(A60,'Bid-NoBid'!$A:$A,0)),"")) | U60: =IF(A60="","",IFERROR(IF(OR(INDEX('Bid-NoBid'!$U:$U,MATCH(A60,'Bid-NoBid'!$A:$A,0))="",LEFT(INDEX('Bid-NoBid'!$U:$U,MATCH(A60,'Bid-NoBid'!$A:$A,0)),10)="Incomplete"),"Screen: "&AC60,INDEX('Bid-NoBid'!$U:$U,MATCH(A60,'Bid-NoBid'!$A:$A,0))),"Screen: "&AC60)) | W60: Watching | X60: Frank | AB60: TanzaniaTenders.com (newspapers / portals / private) | AC60: Check | AD60: Auto (TanzaniaTenders.com): Site not stated in the listing – read the notice · deadline read from the web page – confirm | AE60: =IF(ISNUMBER(Q60),ROUNDDOWN(Q60-NOW(),1),"") | AF60: =IF(OR(A60="",AE60=""),"",IF(NOT(OR(W60="Watching",W60="Preparing")),"",IF(AE60<0,"PASSED",IF(AND(AE60<=7,W60<>"Preparing"),"RED",IF(AE60<=14,"AMBER","GREEN"))))) | AG60: =IF(OR(A60="",NOT(OR(W60="Watching",W60="Preparing"))),"",IF(AND(ISNUMBER(M60),M60>=3000000000),"YES – ≥ TZS 3bn",IF(AND(ISNUMBER(AE60),AE60>=0,AE60<10,V60=""),"YES – <10 days",""))) | AI60: Read the notice and decide with the QS Director whether to pursue | AJ60: Auto-scan | AK60: TZT:150193893 | AL60: =IF(AND(OR(W60="Watching",W60="Preparing"),ISNUMBER(Q60)),IF(AND(Q60>='Friday Summary'!$C$4,Q60<='Friday Summary'!$C$4+14),Q60+ROW()/1000000,""),"")
A61: =IF(B61="","","OP-"&TEXT(ROW()-4,"000")) | B61: (not shown) | C61: 46296 | D61: press | E61: https://www.tanzaniatenders.com/tender/tza23002-10012-construction-materials-kidyama-water-supply-scheme-8f33822.php | F61: See advert | G61: government | H61: Tza23002-10012 - Construction Materials for Kidyama Water Supply Scheme | I61: From press notice (1 lot) – read the tender document | J61: Not stated – read the notice | K61: civil | L61: See tender document | N61: unknown | O61: See tender document | P61: See tender document | Q61: 46311.417 | R61: See tender document | S61: N | T61: =IF(A61="","",IFERROR(INDEX('Bid-NoBid'!$T:$T,MATCH(A61,'Bid-NoBid'!$A:$A,0)),"")) | U61: =IF(A61="","",IFERROR(IF(OR(INDEX('Bid-NoBid'!$U:$U,MATCH(A61,'Bid-NoBid'!$A:$A,0))="",LEFT(INDEX('Bid-NoBid'!$U:$U,MATCH(A61,'Bid-NoBid'!$A:$A,0)),10)="Incomplete"),"Screen: "&AC61,INDEX('Bid-NoBid'!$U:$U,MATCH(A61,'Bid-NoBid'!$A:$A,0))),"Screen: "&AC61)) | W61: Watching | X61: Frank | AB61: TanzaniaTenders.com (newspapers / portals / private) | AC61: Check | AD61: Auto (TanzaniaTenders.com): Civil works – confirm site, CRB class and margin · deadline read from the web page – confirm | AE61: =IF(ISNUMBER(Q61),ROUNDDOWN(Q61-NOW(),1),"") | AF61: =IF(OR(A61="",AE61=""),"",IF(NOT(OR(W61="Watching",W61="Preparing")),"",IF(AE61<0,"PASSED",IF(AND(AE61<=7,W61<>"Preparing"),"RED",IF(AE61<=14,"AMBER","GREEN"))))) | AG61: =IF(OR(A61="",NOT(OR(W61="Watching",W61="Preparing"))),"",IF(AND(ISNUMBER(M61),M61>=3000000000),"YES – ≥ TZS 3bn",IF(AND(ISNUMBER(AE61),AE61>=0,AE61<10,V61=""),"YES – <10 days",""))) | AI61: Read the notice and decide with the QS Director whether to pursue | AJ61: Auto-scan | AK61: TZT:150157346 | AL61: =IF(AND(OR(W61="Watching",W61="Preparing"),ISNUMBER(Q61)),IF(AND(Q61>='Friday Summary'!$C$4,Q61<='Friday Summary'!$C$4+14),Q61+ROW()/1000000,""),"")
A62: =IF(B62="","","OP-"&TEXT(ROW()-4,"000")) | B62: 52/063/2026/2027/W/03 | C62: 46297 | D62: NeST | E62: https://nest.go.tz/tenders/published-tenders | F62: Sokoine Regional Referral Hospital (lindi) | G62: government | H62: Proposed construction of Oxygen Plant Building at Sokoine Regional Referral Hospital - Lindi | I62: From NeST notice (1 lot) – read the tender document | J62: Lindi | K62: building | L62: NeST login needed | N62: unknown | O62: NeST login needed | P62: NeST login needed | Q62: 46303.583 | R62: NeST login needed | S62: N | T62: =IF(A62="","",IFERROR(INDEX('Bid-NoBid'!$T:$T,MATCH(A62,'Bid-NoBid'!$A:$A,0)),"")) | U62: =IF(A62="","",IFERROR(IF(OR(INDEX('Bid-NoBid'!$U:$U,MATCH(A62,'Bid-NoBid'!$A:$A,0))="",LEFT(INDEX('Bid-NoBid'!$U:$U,MATCH(A62,'Bid-NoBid'!$A:$A,0)),10)="Incomplete"),"Screen: "&AC62,INDEX('Bid-NoBid'!$U:$U,MATCH(A62,'Bid-NoBid'!$A:$A,0))),"Screen: "&AC62)) | W62: Watching | X62: Frank | AA62: 46296 | AB62: Small Works / Tender | AC62: Check | AD62: Auto (Small Works / Tender): Lindi/Mtwara – Nordic has worked there (Likong'o) | AE62: =IF(ISNUMBER(Q62),ROUNDDOWN(Q62-NOW(),1),"") | AF62: =IF(OR(A62="",AE62=""),"",IF(NOT(OR(W62="Watching",W62="Preparing")),"",IF(AE62<0,"PASSED",IF(AND(AE62<=7,W62<>"Preparing"),"RED",IF(AE62<=14,"AMBER","GREEN"))))) | AG62: =IF(OR(A62="",NOT(OR(W62="Watching",W62="Preparing"))),"",IF(AND(ISNUMBER(M62),M62>=3000000000),"YES – ≥ TZS 3bn",IF(AND(ISNUMBER(AE62),AE62>=0,AE62<10,V62=""),"YES – <10 days",""))) | AI62: Read the notice and decide with the QS Director whether to pursue | AJ62: Auto-scan | AK62: 1f05d8e5-1e65-4474-b335-be9236a50eca | AL62: =IF(AND(OR(W62="Watching",W62="Preparing"),ISNUMBER(Q62)),IF(AND(Q62>='Friday Summary'!$C$4,Q62<='Friday Summary'!$C$4+14),Q62+ROW()/1000000,""),"")
A63: =IF(B63="","","OP-"&TEXT(ROW()-4,"000")) | B63: TR36/014/2026/2027/W/51 | C63: 46297 | D63: NeST | E63: https://nest.go.tz/tenders/published-tenders | F63: TANROADS - Morogoro Regional Office | G63: government | H63: Drainage works in improvement along Mahenge -Mwaya- Ilonga in Ulanga District | I63: From NeST notice (1 lot) – read the tender document | J63: Morogoro (from client's office – confirm site) | K63: civil | L63: NeST login needed | N63: unknown | O63: NeST login needed | P63: NeST login needed | Q63: 46303.583 | R63: NeST login needed | S63: N | T63: =IF(A63="","",IFERROR(INDEX('Bid-NoBid'!$T:$T,MATCH(A63,'Bid-NoBid'!$A:$A,0)),"")) | U63: =IF(A63="","",IFERROR(IF(OR(INDEX('Bid-NoBid'!$U:$U,MATCH(A63,'Bid-NoBid'!$A:$A,0))="",LEFT(INDEX('Bid-NoBid'!$U:$U,MATCH(A63,'Bid-NoBid'!$A:$A,0)),10)="Incomplete"),"Screen: "&AC63,INDEX('Bid-NoBid'!$U:$U,MATCH(A63,'Bid-NoBid'!$A:$A,0))),"Screen: "&AC63)) | W63: Watching | X63: Frank | AA63: 46296 | AB63: Small Works / Tender | AC63: Check | AD63: Auto (Small Works / Tender): Civil works – confirm site, CRB class and margin | AE63: =IF(ISNUMBER(Q63),ROUNDDOWN(Q63-NOW(),1),"") | AF63: =IF(OR(A63="",AE63=""),"",IF(NOT(OR(W63="Watching",W63="Preparing")),"",IF(AE63<0,"PASSED",IF(AND(AE63<=7,W63<>"Preparing"),"RED",IF(AE63<=14,"AMBER","GREEN"))))) | AG63: =IF(OR(A63="",NOT(OR(W63="Watching",W63="Preparing"))),"",IF(AND(ISNUMBER(M63),M63>=3000000000),"YES – ≥ TZS 3bn",IF(AND(ISNUMBER(AE63),AE63>=0,AE63<10,V63=""),"YES – <10 days",""))) | AI63: Read the notice and decide with the QS Director whether to pursue | AJ63: Auto-scan | AK63: 982a1526-b688-4ad0-8a0e-197a7fd0e7db | AL63: =IF(AND(OR(W63="Watching",W63="Preparing"),ISNUMBER(Q63)),IF(AND(Q63>='Friday Summary'!$C$4,Q63<='Friday Summary'!$C$4+14),Q63+ROW()/1000000,""),"")
A64: =IF(B64="","","OP-"&TEXT(ROW()-4,"000")) | B64: TR152/2026/2027/W/09 | C64: 46297 | D64: NeST | E64: https://nest.go.tz/tenders/published-tenders | F64: Bank of Tanzania | G64: government | H64: Proposed Design and Construction of Staff Residential Houses at Bank of Tanzania Dodoma | I64: From NeST notice (1 lot) – read the tender document | J64: Dodoma | K64: building | L64: NeST login needed | N64: unknown | O64: NeST login needed | P64: NeST login needed | Q64: 46325.667 | R64: NeST login needed | S64: N | T64: =IF(A64="","",IFERROR(INDEX('Bid-NoBid'!$T:$T,MATCH(A64,'Bid-NoBid'!$A:$A,0)),"")) | U64: =IF(A64="","",IFERROR(IF(OR(INDEX('Bid-NoBid'!$U:$U,MATCH(A64,'Bid-NoBid'!$A:$A,0))="",LEFT(INDEX('Bid-NoBid'!$U:$U,MATCH(A64,'Bid-NoBid'!$A:$A,0)),10)="Incomplete"),"Screen: "&AC64,INDEX('Bid-NoBid'!$U:$U,MATCH(A64,'Bid-NoBid'!$A:$A,0))),"Screen: "&AC64)) | W64: Watching | X64: Frank | AA64: 46296 | AB64: Design and Build / Tender | AC64: Pursue | AD64: Auto (Design and Build / Tender): Building works within reach of Dar | AE64: =IF(ISNUMBER(Q64),ROUNDDOWN(Q64-NOW(),1),"") | AF64: =IF(OR(A64="",AE64=""),"",IF(NOT(OR(W64="Watching",W64="Preparing")),"",IF(AE64<0,"PASSED",IF(AND(AE64<=7,W64<>"Preparing"),"RED",IF(AE64<=14,"AMBER","GREEN"))))) | AG64: =IF(OR(A64="",NOT(OR(W64="Watching",W64="Preparing"))),"",IF(AND(ISNUMBER(M64),M64>=3000000000),"YES – ≥ TZS 3bn",IF(AND(ISNUMBER(AE64),AE64>=0,AE64<10,V64=""),"YES – <10 days",""))) | AI64: Deadline changed at source 16-Oct (was 16-Oct 16:00). Get the tender document, confirm value, CRB class, site visit and bid security; brief the MD | AJ64: Auto-scan | AK64: 116e9c36-d566-49b7-bb20-6dce4ba4e87c | AL64: =IF(AND(OR(W64="Watching",W64="Preparing"),ISNUMBER(Q64)),IF(AND(Q64>='Friday Summary'!$C$4,Q64<='Friday Summary'!$C$4+14),Q64+ROW()/1000000,""),"")
A65: =IF(B65="","","OP-"&TEXT(ROW()-4,"000")) | B65: (not shown) | C65: 46297 | D65: press | E65: https://www.tanzaniatenders.com/tender/provision-decoration-services-tra-tanga-regional-office-and-its-district-8f51f4a.php | F65: See advert | G65: government | H65: Provision of Decoration Services to Tra Tanga Regional Office and its District | I65: From press notice (1 lot) – read the tender document | J65: Tanga | K65: building | L65: See tender document | N65: unknown | O65: See tender document | P65: See tender document | Q65: 46304.417 | R65: See tender document | S65: N | T65: =IF(A65="","",IFERROR(INDEX('Bid-NoBid'!$T:$T,MATCH(A65,'Bid-NoBid'!$A:$A,0)),"")) | U65: =IF(A65="","",IFERROR(IF(OR(INDEX('Bid-NoBid'!$U:$U,MATCH(A65,'Bid-NoBid'!$A:$A,0))="",LEFT(INDEX('Bid-NoBid'!$U:$U,MATCH(A65,'Bid-NoBid'!$A:$A,0)),10)="Incomplete"),"Screen: "&AC65,INDEX('Bid-NoBid'!$U:$U,MATCH(A65,'Bid-NoBid'!$A:$A,0))),"Screen: "&AC65)) | W65: Watching | X65: Frank | AB65: TanzaniaTenders.com (newspapers / portals / private) | AC65: Pursue | AD65: Auto (TanzaniaTenders.com): Building works within reach of Dar · deadline read from the web page – confirm | AE65: =IF(ISNUMBER(Q65),ROUNDDOWN(Q65-NOW(),1),"") | AF65: =IF(OR(A65="",AE65=""),"",IF(NOT(OR(W65="Watching",W65="Preparing")),"",IF(AE65<0,"PASSED",IF(AND(AE65<=7,W65<>"Preparing"),"RED",IF(AE65<=14,"AMBER","GREEN"))))) | AG65: =IF(OR(A65="",NOT(OR(W65="Watching",W65="Preparing"))),"",IF(AND(ISNUMBER(M65),M65>=3000000000),"YES – ≥ TZS 3bn",IF(AND(ISNUMBER(AE65),AE65>=0,AE65<10,V65=""),"YES – <10 days",""))) | AI65: Get the tender document, confirm value, CRB class, site visit and bid security; brief the MD | AJ65: Auto-scan | AK65: TZT:150282058 | AL65: =IF(AND(OR(W65="Watching",W65="Preparing"),ISNUMBER(Q65)),IF(AND(Q65>='Friday Summary'!$C$4,Q65<='Friday Summary'!$C$4+14),Q65+ROW()/1000000,""),"")
A66: =IF(B66="","","OP-"&TEXT(ROW()-4,"000")) | B66: (not shown) | C66: 46297 | D66: press | E66: https://www.tanzaniatenders.com/tender/ujenzi-katika-ujenzi-wa-ofisi-za-tarafa-pahi-mundemu-zoisa-makang-wa-kibakwe-na-goima-8f51f41.php | F66: See advert | G66: government | H66: Ujenzi Katika Ujenzi Wa Ofisi Za Tarafa Pahi, Mundemu, Zoisa, Makang'wa, Kibakwe Na Goima | I66: From press notice (1 lot) – read the tender document | J66: Not stated – read the notice | K66: building | L66: See tender document | N66: unknown | O66: See tender document | P66: See tender document | Q66: 46304.417 | R66: See tender document | S66: N | T66: =IF(A66="","",IFERROR(INDEX('Bid-NoBid'!$T:$T,MATCH(A66,'Bid-NoBid'!$A:$A,0)),"")) | U66: =IF(A66="","",IFERROR(IF(OR(INDEX('Bid-NoBid'!$U:$U,MATCH(A66,'Bid-NoBid'!$A:$A,0))="",LEFT(INDEX('Bid-NoBid'!$U:$U,MATCH(A66,'Bid-NoBid'!$A:$A,0)),10)="Incomplete"),"Screen: "&AC66,INDEX('Bid-NoBid'!$U:$U,MATCH(A66,'Bid-NoBid'!$A:$A,0))),"Screen: "&AC66)) | W66: Watching | X66: Frank | AB66: TanzaniaTenders.com (newspapers / portals / private) | AC66: Check | AD66: Auto (TanzaniaTenders.com): Site not stated in the listing – read the notice · deadline read from the web page – confirm | AE66: =IF(ISNUMBER(Q66),ROUNDDOWN(Q66-NOW(),1),"") | AF66: =IF(OR(A66="",AE66=""),"",IF(NOT(OR(W66="Watching",W66="Preparing")),"",IF(AE66<0,"PASSED",IF(AND(AE66<=7,W66<>"Preparing"),"RED",IF(AE66<=14,"AMBER","GREEN"))))) | AG66: =IF(OR(A66="",NOT(OR(W66="Watching",W66="Preparing"))),"",IF(AND(ISNUMBER(M66),M66>=3000000000),"YES – ≥ TZS 3bn",IF(AND(ISNUMBER(AE66),AE66>=0,AE66<10,V66=""),"YES – <10 days",""))) | AI66: Read the notice and decide with the QS Director whether to pursue | AJ66: Auto-scan | AK66: TZT:150282049 | AL66: =IF(AND(OR(W66="Watching",W66="Preparing"),ISNUMBER(Q66)),IF(AND(Q66>='Friday Summary'!$C$4,Q66<='Friday Summary'!$C$4+14),Q66+ROW()/1000000,""),"")
A67: =IF(B67="","","OP-"&TEXT(ROW()-4,"000")) | B67: (not shown) | C67: 46297 | D67: press | E67: https://www.tanzaniatenders.com/tender/procurement-laboratory-equipments-tari-ilonga-under-afdp-project-8f51f66.php | F67: See advert | G67: government | H67: Procurement of Laboratory Equipments for Tari Ilonga under Afdp Project | I67: From press notice (1 lot) – read the tender document | J67: Not stated – read the notice | K67: building | L67: See tender document | N67: unknown | O67: See tender document | P67: See tender document | Q67: 46310.417 | R67: See tender document | S67: N | T67: =IF(A67="","",IFERROR(INDEX('Bid-NoBid'!$T:$T,MATCH(A67,'Bid-NoBid'!$A:$A,0)),"")) | U67: =IF(A67="","",IFERROR(IF(OR(INDEX('Bid-NoBid'!$U:$U,MATCH(A67,'Bid-NoBid'!$A:$A,0))="",LEFT(INDEX('Bid-NoBid'!$U:$U,MATCH(A67,'Bid-NoBid'!$A:$A,0)),10)="Incomplete"),"Screen: "&AC67,INDEX('Bid-NoBid'!$U:$U,MATCH(A67,'Bid-NoBid'!$A:$A,0))),"Screen: "&AC67)) | W67: Watching | X67: Frank | AB67: TanzaniaTenders.com (newspapers / portals / private) | AC67: Check | AD67: Auto (TanzaniaTenders.com): Site not stated in the listing – read the notice · deadline read from the web page – confirm | AE67: =IF(ISNUMBER(Q67),ROUNDDOWN(Q67-NOW(),1),"") | AF67: =IF(OR(A67="",AE67=""),"",IF(NOT(OR(W67="Watching",W67="Preparing")),"",IF(AE67<0,"PASSED",IF(AND(AE67<=7,W67<>"Preparing"),"RED",IF(AE67<=14,"AMBER","GREEN"))))) | AG67: =IF(OR(A67="",NOT(OR(W67="Watching",W67="Preparing"))),"",IF(AND(ISNUMBER(M67),M67>=3000000000),"YES – ≥ TZS 3bn",IF(AND(ISNUMBER(AE67),AE67>=0,AE67<10,V67=""),"YES – <10 days",""))) | AI67: Read the notice and decide with the QS Director whether to pursue | AJ67: Auto-scan | AK67: TZT:150282086 | AL67: =IF(AND(OR(W67="Watching",W67="Preparing"),ISNUMBER(Q67)),IF(AND(Q67>='Friday Summary'!$C$4,Q67<='Friday Summary'!$C$4+14),Q67+ROW()/1000000,""),"")
A68: =IF(B68="","","OP-"&TEXT(ROW()-4,"000")) | B68: (not shown) | C68: 46297 | D68: press | E68: https://www.tanzaniatenders.com/tender/the-tender-construction-new-facilities-state-university-zanzibar-including-new-administration-block-8f57dc3.php | F68: See advert | G68: government | H68: The tender is for the construction of new facilities at the State University of Zanzibar, including a New Administration Block, School of Education and Language Block, Students Centre Block, Staff Apartment Blocks, and Sports Facilities. The project | I68: From press notice (1 lot) – read the tender document | J68: Zanzibar | K68: building | L68: See tender document | N68: unknown | O68: See tender document | P68: See tender document | Q68: 46307.417 | R68: See tender document | S68: N | T68: =IF(A68="","",IFERROR(INDEX('Bid-NoBid'!$T:$T,MATCH(A68,'Bid-NoBid'!$A:$A,0)),"")) | U68: =IF(A68="","",IFERROR(IF(OR(INDEX('Bid-NoBid'!$U:$U,MATCH(A68,'Bid-NoBid'!$A:$A,0))="",LEFT(INDEX('Bid-NoBid'!$U:$U,MATCH(A68,'Bid-NoBid'!$A:$A,0)),10)="Incomplete"),"Screen: "&AC68,INDEX('Bid-NoBid'!$U:$U,MATCH(A68,'Bid-NoBid'!$A:$A,0))),"Screen: "&AC68)) | W68: Watching | X68: Frank | AB68: TanzaniaTenders.com (newspapers / portals / private) | AC68: Pursue | AD68: Auto (TanzaniaTenders.com): Building works within reach of Dar · deadline read from the web page – confirm | AE68: =IF(ISNUMBER(Q68),ROUNDDOWN(Q68-NOW(),1),"") | AF68: =IF(OR(A68="",AE68=""),"",IF(NOT(OR(W68="Watching",W68="Preparing")),"",IF(AE68<0,"PASSED",IF(AND(AE68<=7,W68<>"Preparing"),"RED",IF(AE68<=14,"AMBER","GREEN"))))) | AG68: =IF(OR(A68="",NOT(OR(W68="Watching",W68="Preparing"))),"",IF(AND(ISNUMBER(M68),M68>=3000000000),"YES – ≥ TZS 3bn",IF(AND(ISNUMBER(AE68),AE68>=0,AE68<10,V68=""),"YES – <10 days",""))) | AI68: Get the tender document, confirm value, CRB class, site visit and bid security; brief the MD | AJ68: Auto-scan | AK68: TZT:150306243 | AL68: =IF(AND(OR(W68="Watching",W68="Preparing"),ISNUMBER(Q68)),IF(AND(Q68>='Friday Summary'!$C$4,Q68<='Friday Summary'!$C$4+14),Q68+ROW()/1000000,""),"")
A69: =IF(B69="","","OP-"&TEXT(ROW()-4,"000")) | B69: (not shown) | C69: 46298 | D69: press | E69: https://www.tanzaniatenders.com/tender/bdi25003-10004-public-work-contract-construction-perimeter-fence-and-site-development-works-nsu-8f6414e.php | F69: See advert | G69: government | H69: Bdi25003-10004 - Public Work Contract for “Construction of Perimeter Fence and Site Development Works at Nsumbu Environmental and Climatic Monitoring Center and at the Lake Tanganyika Research Unit” | I69: From press notice (1 lot) – read the tender document | J69: Not stated – read the notice | K69: building | L69: See tender document | N69: unknown | O69: See tender document | P69: See tender document | Q69: 46318.417 | R69: See tender document | S69: N | T69: =IF(A69="","",IFERROR(INDEX('Bid-NoBid'!$T:$T,MATCH(A69,'Bid-NoBid'!$A:$A,0)),"")) | U69: =IF(A69="","",IFERROR(IF(OR(INDEX('Bid-NoBid'!$U:$U,MATCH(A69,'Bid-NoBid'!$A:$A,0))="",LEFT(INDEX('Bid-NoBid'!$U:$U,MATCH(A69,'Bid-NoBid'!$A:$A,0)),10)="Incomplete"),"Screen: "&AC69,INDEX('Bid-NoBid'!$U:$U,MATCH(A69,'Bid-NoBid'!$A:$A,0))),"Screen: "&AC69)) | W69: Watching | X69: Frank | AB69: TanzaniaTenders.com (newspapers / portals / private) | AC69: Check | AD69: Auto (TanzaniaTenders.com): Site not stated in the listing – read the notice · deadline read from the web page – confirm | AE69: =IF(ISNUMBER(Q69),ROUNDDOWN(Q69-NOW(),1),"") | AF69: =IF(OR(A69="",AE69=""),"",IF(NOT(OR(W69="Watching",W69="Preparing")),"",IF(AE69<0,"PASSED",IF(AND(AE69<=7,W69<>"Preparing"),"RED",IF(AE69<=14,"AMBER","GREEN"))))) | AG69: =IF(OR(A69="",NOT(OR(W69="Watching",W69="Preparing"))),"",IF(AND(ISNUMBER(M69),M69>=3000000000),"YES – ≥ TZS 3bn",IF(AND(ISNUMBER(AE69),AE69>=0,AE69<10,V69=""),"YES – <10 days",""))) | AI69: Read the notice and decide with the QS Director whether to pursue | AJ69: Auto-scan | AK69: TZT:150356302 | AL69: =IF(AND(OR(W69="Watching",W69="Preparing"),ISNUMBER(Q69)),IF(AND(Q69>='Friday Summary'!$C$4,Q69<='Friday Summary'!$C$4+14),Q69+ROW()/1000000,""),"")
A70: =IF(B70="","","OP-"&TEXT(ROW()-4,"000")) | B70: (not shown) | C70: 46298 | D70: press | E70: https://www.tanzaniatenders.com/tender/provision-hiring-civil-works-equipments-excavator-and-dumper-truck-8f64b24.php | F70: See advert | G70: government | H70: Provision of Hiring of Civil Works Equipments (Excavator and Dumper Truck) | I70: From press notice (1 lot) – read the tender document | J70: Not stated – read the notice | K70: civil | L70: See tender document | N70: unknown | O70: See tender document | P70: See tender document | Q70: 46304.417 | R70: See tender document | S70: N | T70: =IF(A70="","",IFERROR(INDEX('Bid-NoBid'!$T:$T,MATCH(A70,'Bid-NoBid'!$A:$A,0)),"")) | U70: =IF(A70="","",IFERROR(IF(OR(INDEX('Bid-NoBid'!$U:$U,MATCH(A70,'Bid-NoBid'!$A:$A,0))="",LEFT(INDEX('Bid-NoBid'!$U:$U,MATCH(A70,'Bid-NoBid'!$A:$A,0)),10)="Incomplete"),"Screen: "&AC70,INDEX('Bid-NoBid'!$U:$U,MATCH(A70,'Bid-NoBid'!$A:$A,0))),"Screen: "&AC70)) | W70: Watching | X70: Frank | AB70: TanzaniaTenders.com (newspapers / portals / private) | AC70: Check | AD70: Auto (TanzaniaTenders.com): Civil works – confirm site, CRB class and margin · deadline read from the web page – confirm | AE70: =IF(ISNUMBER(Q70),ROUNDDOWN(Q70-NOW(),1),"") | AF70: =IF(OR(A70="",AE70=""),"",IF(NOT(OR(W70="Watching",W70="Preparing")),"",IF(AE70<0,"PASSED",IF(AND(AE70<=7,W70<>"Preparing"),"RED",IF(AE70<=14,"AMBER","GREEN"))))) | AG70: =IF(OR(A70="",NOT(OR(W70="Watching",W70="Preparing"))),"",IF(AND(ISNUMBER(M70),M70>=3000000000),"YES – ≥ TZS 3bn",IF(AND(ISNUMBER(AE70),AE70>=0,AE70<10,V70=""),"YES – <10 days",""))) | AI70: Read the notice and decide with the QS Director whether to pursue | AJ70: Auto-scan | AK70: TZT:150358820 | AL70: =IF(AND(OR(W70="Watching",W70="Preparing"),ISNUMBER(Q70)),IF(AND(Q70>='Friday Summary'!$C$4,Q70<='Friday Summary'!$C$4+14),Q70+ROW()/1000000,""),"")
A71: =IF(B71="","","OP-"&TEXT(ROW()-4,"000")) | B71: (not shown) | C71: 46298 | D71: press | E71: https://www.tanzaniatenders.com/tender/replacement-regional-offices-internet-routers-8f64b1c.php | F71: See advert | G71: government | H71: Replacement of Regional Offices Internet Routers | I71: From press notice (1 lot) – read the tender document | J71: Not stated – read the notice | K71: building | L71: See tender document | N71: unknown | O71: See tender document | P71: See tender document | Q71: 46304.417 | R71: See tender document | S71: N | T71: =IF(A71="","",IFERROR(INDEX('Bid-NoBid'!$T:$T,MATCH(A71,'Bid-NoBid'!$A:$A,0)),"")) | U71: =IF(A71="","",IFERROR(IF(OR(INDEX('Bid-NoBid'!$U:$U,MATCH(A71,'Bid-NoBid'!$A:$A,0))="",LEFT(INDEX('Bid-NoBid'!$U:$U,MATCH(A71,'Bid-NoBid'!$A:$A,0)),10)="Incomplete"),"Screen: "&AC71,INDEX('Bid-NoBid'!$U:$U,MATCH(A71,'Bid-NoBid'!$A:$A,0))),"Screen: "&AC71)) | W71: Watching | X71: Frank | AB71: TanzaniaTenders.com (newspapers / portals / private) | AC71: Check | AD71: Auto (TanzaniaTenders.com): Site not stated in the listing – read the notice · deadline read from the web page – confirm | AE71: =IF(ISNUMBER(Q71),ROUNDDOWN(Q71-NOW(),1),"") | AF71: =IF(OR(A71="",AE71=""),"",IF(NOT(OR(W71="Watching",W71="Preparing")),"",IF(AE71<0,"PASSED",IF(AND(AE71<=7,W71<>"Preparing"),"RED",IF(AE71<=14,"AMBER","GREEN"))))) | AG71: =IF(OR(A71="",NOT(OR(W71="Watching",W71="Preparing"))),"",IF(AND(ISNUMBER(M71),M71>=3000000000),"YES – ≥ TZS 3bn",IF(AND(ISNUMBER(AE71),AE71>=0,AE71<10,V71=""),"YES – <10 days",""))) | AI71: Read the notice and decide with the QS Director whether to pursue | AJ71: Auto-scan | AK71: TZT:150358812 | AL71: =IF(AND(OR(W71="Watching",W71="Preparing"),ISNUMBER(Q71)),IF(AND(Q71>='Friday Summary'!$C$4,Q71<='Friday Summary'!$C$4+14),Q71+ROW()/1000000,""),"")
A72: =IF(B72="","","OP-"&TEXT(ROW()-4,"000")) | B72: 77H2/2026/2027/W/26 | C72: 46300 | D72: NeST | E72: https://nest.go.tz/tenders/published-tenders | F72: Tarime District Council | G72: government | H72: MAINTENANCE OF NYANGOTO VILLAGE ROADS, CONSTRUCTION OF COMPOSITE CULVERTS (5NOs) AND 3160m LINED STONE PITCHING SIDE DRAIN. | I72: From NeST notice (1 lot) – read the tender document | J72: Mara (from client's office – confirm site) | K72: civil | L72: NeST login needed | N72: unknown | O72: NeST login needed | P72: NeST login needed | Q72: 46307.583 | R72: NeST login needed | S72: N | T72: =IF(A72="","",IFERROR(INDEX('Bid-NoBid'!$T:$T,MATCH(A72,'Bid-NoBid'!$A:$A,0)),"")) | U72: =IF(A72="","",IFERROR(IF(OR(INDEX('Bid-NoBid'!$U:$U,MATCH(A72,'Bid-NoBid'!$A:$A,0))="",LEFT(INDEX('Bid-NoBid'!$U:$U,MATCH(A72,'Bid-NoBid'!$A:$A,0)),10)="Incomplete"),"Screen: "&AC72,INDEX('Bid-NoBid'!$U:$U,MATCH(A72,'Bid-NoBid'!$A:$A,0))),"Screen: "&AC72)) | W72: Watching | X72: Frank | AA72: 46300 | AB72: Small Works / Planned Tender | AC72: Check | AD72: Auto (Small Works / Planned Tender): Construction tender kept for review (would have been dropped: Remote civil works) | AE72: =IF(ISNUMBER(Q72),ROUNDDOWN(Q72-NOW(),1),"") | AF72: =IF(OR(A72="",AE72=""),"",IF(NOT(OR(W72="Watching",W72="Preparing")),"",IF(AE72<0,"PASSED",IF(AND(AE72<=7,W72<>"Preparing"),"RED",IF(AE72<=14,"AMBER","GREEN"))))) | AG72: =IF(OR(A72="",NOT(OR(W72="Watching",W72="Preparing"))),"",IF(AND(ISNUMBER(M72),M72>=3000000000),"YES – ≥ TZS 3bn",IF(AND(ISNUMBER(AE72),AE72>=0,AE72<10,V72=""),"YES – <10 days",""))) | AI72: Read the notice and decide with the QS Director whether to pursue | AJ72: Auto-scan | AK72: 36497a17-ca65-4da6-9604-17124a4cfd84 | AL72: =IF(AND(OR(W72="Watching",W72="Preparing"),ISNUMBER(Q72)),IF(AND(Q72>='Friday Summary'!$C$4,Q72<='Friday Summary'!$C$4+14),Q72+ROW()/1000000,""),"")
A73: =IF(B73="","","OP-"&TEXT(ROW()-4,"000")) | B73: S10/023/2026/2027/W/85 | C73: 46300 | D73: NeST | E73: https://nest.go.tz/tenders/published-tenders | F73: TARURA - Singida Regional Office | G73: government | H73: UPGRADING OF SOKOINE ROAD 14 TO STONE PAVEMENT SURFACE AND SPOT IMPROVEMENT AND CONSTRUCTION OF CULVERTS ALONG MINYUGHE, UNYAMIKUMBI AND UNYAMBWA ROADS IN SINGIDA MC | I73: From NeST notice (1 lot) – read the tender document | J73: Singida | K73: civil | L73: NeST login needed | N73: unknown | O73: NeST login needed | P73: NeST login needed | Q73: 46307.583 | R73: NeST login needed | S73: N | T73: =IF(A73="","",IFERROR(INDEX('Bid-NoBid'!$T:$T,MATCH(A73,'Bid-NoBid'!$A:$A,0)),"")) | U73: =IF(A73="","",IFERROR(IF(OR(INDEX('Bid-NoBid'!$U:$U,MATCH(A73,'Bid-NoBid'!$A:$A,0))="",LEFT(INDEX('Bid-NoBid'!$U:$U,MATCH(A73,'Bid-NoBid'!$A:$A,0)),10)="Incomplete"),"Screen: "&AC73,INDEX('Bid-NoBid'!$U:$U,MATCH(A73,'Bid-NoBid'!$A:$A,0))),"Screen: "&AC73)) | W73: Watching | X73: Frank | AA73: 46300 | AB73: Small Works / Tender | AC73: Check | AD73: Auto (Small Works / Tender): Construction tender kept for review (would have been dropped: Remote civil works) | AE73: =IF(ISNUMBER(Q73),ROUNDDOWN(Q73-NOW(),1),"") | AF73: =IF(OR(A73="",AE73=""),"",IF(NOT(OR(W73="Watching",W73="Preparing")),"",IF(AE73<0,"PASSED",IF(AND(AE73<=7,W73<>"Preparing"),"RED",IF(AE73<=14,"AMBER","GREEN"))))) | AG73: =IF(OR(A73="",NOT(OR(W73="Watching",W73="Preparing"))),"",IF(AND(ISNUMBER(M73),M73>=3000000000),"YES – ≥ TZS 3bn",IF(AND(ISNUMBER(AE73),AE73>=0,AE73<10,V73=""),"YES – <10 days",""))) | AI73: Read the notice and decide with the QS Director whether to pursue | AJ73: Auto-scan | AK73: 8025c8bf-013d-4f83-8975-822e05cdc3d0 | AL73: =IF(AND(OR(W73="Watching",W73="Preparing"),ISNUMBER(Q73)),IF(AND(Q73>='Friday Summary'!$C$4,Q73<='Friday Summary'!$C$4+14),Q73+ROW()/1000000,""),"")
A74: =IF(B74="","","OP-"&TEXT(ROW()-4,"000")) | B74: (not shown) | C74: 46300 | D74: press | E74: https://www.tanzaniatenders.com/tender/renting-warehouse-geita-region-8f74e5f.php | F74: See advert | G74: government | H74: Renting Warehouse in Geita Region | I74: From press notice (1 lot) – read the tender document | J74: Geita | K74: building | L74: See tender document | N74: unknown | O74: See tender document | P74: See tender document | Q74: 46307.417 | R74: See tender document | S74: N | T74: =IF(A74="","",IFERROR(INDEX('Bid-NoBid'!$T:$T,MATCH(A74,'Bid-NoBid'!$A:$A,0)),"")) | U74: =IF(A74="","",IFERROR(IF(OR(INDEX('Bid-NoBid'!$U:$U,MATCH(A74,'Bid-NoBid'!$A:$A,0))="",LEFT(INDEX('Bid-NoBid'!$U:$U,MATCH(A74,'Bid-NoBid'!$A:$A,0)),10)="Incomplete"),"Screen: "&AC74,INDEX('Bid-NoBid'!$U:$U,MATCH(A74,'Bid-NoBid'!$A:$A,0))),"Screen: "&AC74)) | W74: Watching | X74: Frank | AB74: TanzaniaTenders.com (newspapers / portals / private) | AC74: Check | AD74: Auto (TanzaniaTenders.com): Building works but remote from Dar · deadline read from the web page – confirm | AE74: =IF(ISNUMBER(Q74),ROUNDDOWN(Q74-NOW(),1),"") | AF74: =IF(OR(A74="",AE74=""),"",IF(NOT(OR(W74="Watching",W74="Preparing")),"",IF(AE74<0,"PASSED",IF(AND(AE74<=7,W74<>"Preparing"),"RED",IF(AE74<=14,"AMBER","GREEN"))))) | AG74: =IF(OR(A74="",NOT(OR(W74="Watching",W74="Preparing"))),"",IF(AND(ISNUMBER(M74),M74>=3000000000),"YES – ≥ TZS 3bn",IF(AND(ISNUMBER(AE74),AE74>=0,AE74<10,V74=""),"YES – <10 days",""))) | AI74: Read the notice and decide with the QS Director whether to pursue | AJ74: Auto-scan | AK74: TZT:150425183 | AL74: =IF(AND(OR(W74="Watching",W74="Preparing"),ISNUMBER(Q74)),IF(AND(Q74>='Friday Summary'!$C$4,Q74<='Friday Summary'!$C$4+14),Q74+ROW()/1000000,""),"")
A75: =IF(B75="","","OP-"&TEXT(ROW()-4,"000")) | B75: (not shown) | C75: 46300 | D75: press | E75: https://www.ddotenders.co.tz/tender.php?page=home | F75: Geita Greenfields Mineral Exploration Limited | G75: parastatal (verify) | H75: Renovation for offices | I75: From press notice (1 lot) – read the tender document | J75: Dodoma | K75: renovation | L75: See tender document | N75: unknown | O75: See tender document | P75: See tender document | Q75: 46303.417 | R75: See tender document | S75: N | T75: =IF(A75="","",IFERROR(INDEX('Bid-NoBid'!$T:$T,MATCH(A75,'Bid-NoBid'!$A:$A,0)),"")) | U75: =IF(A75="","",IFERROR(IF(OR(INDEX('Bid-NoBid'!$U:$U,MATCH(A75,'Bid-NoBid'!$A:$A,0))="",LEFT(INDEX('Bid-NoBid'!$U:$U,MATCH(A75,'Bid-NoBid'!$A:$A,0)),10)="Incomplete"),"Screen: "&AC75,INDEX('Bid-NoBid'!$U:$U,MATCH(A75,'Bid-NoBid'!$A:$A,0))),"Screen: "&AC75)) | W75: Watching | X75: Frank | AA75: 46300 | AB75: DDO Tenders (newspaper / private / donor) | AC75: Check | AD75: Auto (DDO Tenders): Good fit but little time left · deadline read from the web page – confirm | AE75: =IF(ISNUMBER(Q75),ROUNDDOWN(Q75-NOW(),1),"") | AF75: =IF(OR(A75="",AE75=""),"",IF(NOT(OR(W75="Watching",W75="Preparing")),"",IF(AE75<0,"PASSED",IF(AND(AE75<=7,W75<>"Preparing"),"RED",IF(AE75<=14,"AMBER","GREEN"))))) | AG75: =IF(OR(A75="",NOT(OR(W75="Watching",W75="Preparing"))),"",IF(AND(ISNUMBER(M75),M75>=3000000000),"YES – ≥ TZS 3bn",IF(AND(ISNUMBER(AE75),AE75>=0,AE75<10,V75=""),"YES – <10 days",""))) | AI75: Read the notice and decide with the QS Director whether to pursue | AJ75: Auto-scan | AK75: DDO:3067 | AL75: =IF(AND(OR(W75="Watching",W75="Preparing"),ISNUMBER(Q75)),IF(AND(Q75>='Friday Summary'!$C$4,Q75<='Friday Summary'!$C$4+14),Q75+ROW()/1000000,""),"")
A76: =IF(B76="","","OP-"&TEXT(ROW()-4,"000")) | B76: 2026TZAWAT5023 | C76: 46300 | D76: press | E76: https://www.ddotenders.co.tz/tender.php?page=home | F76: DIRECT AID SOCIETY | G76: government | H76: Maintenance Works at School | I76: From press notice (1 lot) – read the tender document | J76: Kilimanjaro (Moshi) | K76: building | L76: See tender document | N76: unknown | O76: See tender document | P76: See tender document | Q76: 46311.417 | R76: See tender document | S76: N | T76: =IF(A76="","",IFERROR(INDEX('Bid-NoBid'!$T:$T,MATCH(A76,'Bid-NoBid'!$A:$A,0)),"")) | U76: =IF(A76="","",IFERROR(IF(OR(INDEX('Bid-NoBid'!$U:$U,MATCH(A76,'Bid-NoBid'!$A:$A,0))="",LEFT(INDEX('Bid-NoBid'!$U:$U,MATCH(A76,'Bid-NoBid'!$A:$A,0)),10)="Incomplete"),"Screen: "&AC76,INDEX('Bid-NoBid'!$U:$U,MATCH(A76,'Bid-NoBid'!$A:$A,0))),"Screen: "&AC76)) | W76: Watching | X76: Frank | AA76: 46300 | AB76: DDO Tenders (newspaper / private / donor) | AC76: Check | AD76: Auto (DDO Tenders): Building works but remote from Dar · deadline read from the web page – confirm | AE76: =IF(ISNUMBER(Q76),ROUNDDOWN(Q76-NOW(),1),"") | AF76: =IF(OR(A76="",AE76=""),"",IF(NOT(OR(W76="Watching",W76="Preparing")),"",IF(AE76<0,"PASSED",IF(AND(AE76<=7,W76<>"Preparing"),"RED",IF(AE76<=14,"AMBER","GREEN"))))) | AG76: =IF(OR(A76="",NOT(OR(W76="Watching",W76="Preparing"))),"",IF(AND(ISNUMBER(M76),M76>=3000000000),"YES – ≥ TZS 3bn",IF(AND(ISNUMBER(AE76),AE76>=0,AE76<10,V76=""),"YES – <10 days",""))) | AI76: Read the notice and decide with the QS Director whether to pursue | AJ76: Auto-scan | AK76: DDO:3071 | AL76: =IF(AND(OR(W76="Watching",W76="Preparing"),ISNUMBER(Q76)),IF(AND(Q76>='Friday Summary'!$C$4,Q76<='Friday Summary'!$C$4+14),Q76+ROW()/1000000,""),"")
A77: =IF(B77="","","OP-"&TEXT(ROW()-4,"000")) | B77: 87V4/2026/2027/W/11 | C77: 46301 | D77: NeST | E77: https://nest.go.tz/tenders/published-tenders | F77: Muleba District Council | G77: government | H77: CONSTRUCTION OF THE EXECUTIVE DIRECTOR'S RESIDENTIAL HOUSE AT MULEBA DISTRICT COUNCIL | I77: From NeST notice (1 lot) – read the tender document | J77: Kagera (from client's office – confirm site) | K77: building | L77: NeST login needed | N77: unknown | O77: NeST login needed | P77: NeST login needed | Q77: 46307.417 | R77: NeST login needed | S77: N | T77: =IF(A77="","",IFERROR(INDEX('Bid-NoBid'!$T:$T,MATCH(A77,'Bid-NoBid'!$A:$A,0)),"")) | U77: =IF(A77="","",IFERROR(IF(OR(INDEX('Bid-NoBid'!$U:$U,MATCH(A77,'Bid-NoBid'!$A:$A,0))="",LEFT(INDEX('Bid-NoBid'!$U:$U,MATCH(A77,'Bid-NoBid'!$A:$A,0)),10)="Incomplete"),"Screen: "&AC77,INDEX('Bid-NoBid'!$U:$U,MATCH(A77,'Bid-NoBid'!$A:$A,0))),"Screen: "&AC77)) | W77: Watching | X77: Frank | AA77: 46300 | AB77: Small Works / Tender | AC77: Check | AD77: Auto (Small Works / Tender): Construction tender kept for review (would have been dropped: Remote and closing soon) | AE77: =IF(ISNUMBER(Q77),ROUNDDOWN(Q77-NOW(),1),"") | AF77: =IF(OR(A77="",AE77=""),"",IF(NOT(OR(W77="Watching",W77="Preparing")),"",IF(AE77<0,"PASSED",IF(AND(AE77<=7,W77<>"Preparing"),"RED",IF(AE77<=14,"AMBER","GREEN"))))) | AG77: =IF(OR(A77="",NOT(OR(W77="Watching",W77="Preparing"))),"",IF(AND(ISNUMBER(M77),M77>=3000000000),"YES – ≥ TZS 3bn",IF(AND(ISNUMBER(AE77),AE77>=0,AE77<10,V77=""),"YES – <10 days",""))) | AI77: Read the notice and decide with the QS Director whether to pursue | AJ77: Auto-scan | AK77: f07667a1-2f4d-4022-aab2-3012d0645bb0 | AL77: =IF(AND(OR(W77="Watching",W77="Preparing"),ISNUMBER(Q77)),IF(AND(Q77>='Friday Summary'!$C$4,Q77<='Friday Summary'!$C$4+14),Q77+ROW()/1000000,""),"")
A78: =IF(B78="","","OP-"&TEXT(ROW()-4,"000")) | B78: S10/020/2026/2027/W/51 | C78: 46301 | D78: NeST | E78: https://nest.go.tz/tenders/published-tenders | F78: TARURA - Ruvuma Regional Office | G78: government | H78: Construction of Three Cell Box Culvert (5.0m x 2.5m) and Single Cell (2.5m x 2.0m) Box Culvert along Ligunga - Kindamba Road | I78: From NeST notice (1 lot) – read the tender document | J78: Ruvuma (Songea) (from client's office – confirm site) | K78: civil | L78: NeST login needed | N78: unknown | O78: NeST login needed | P78: NeST login needed | Q78: 46307.5 | R78: NeST login needed | S78: N | T78: =IF(A78="","",IFERROR(INDEX('Bid-NoBid'!$T:$T,MATCH(A78,'Bid-NoBid'!$A:$A,0)),"")) | U78: =IF(A78="","",IFERROR(IF(OR(INDEX('Bid-NoBid'!$U:$U,MATCH(A78,'Bid-NoBid'!$A:$A,0))="",LEFT(INDEX('Bid-NoBid'!$U:$U,MATCH(A78,'Bid-NoBid'!$A:$A,0)),10)="Incomplete"),"Screen: "&AC78,INDEX('Bid-NoBid'!$U:$U,MATCH(A78,'Bid-NoBid'!$A:$A,0))),"Screen: "&AC78)) | W78: Watching | X78: Frank | AA78: 46300 | AB78: Small Works / Tender | AC78: Check | AD78: Auto (Small Works / Tender): Construction tender kept for review (would have been dropped: Remote civil works) | AE78: =IF(ISNUMBER(Q78),ROUNDDOWN(Q78-NOW(),1),"") | AF78: =IF(OR(A78="",AE78=""),"",IF(NOT(OR(W78="Watching",W78="Preparing")),"",IF(AE78<0,"PASSED",IF(AND(AE78<=7,W78<>"Preparing"),"RED",IF(AE78<=14,"AMBER","GREEN"))))) | AG78: =IF(OR(A78="",NOT(OR(W78="Watching",W78="Preparing"))),"",IF(AND(ISNUMBER(M78),M78>=3000000000),"YES – ≥ TZS 3bn",IF(AND(ISNUMBER(AE78),AE78>=0,AE78<10,V78=""),"YES – <10 days",""))) | AI78: Read the notice and decide with the QS Director whether to pursue | AJ78: Auto-scan | AK78: cf3c3d0f-9a71-40a5-b4f2-51e041a3e270 | AL78: =IF(AND(OR(W78="Watching",W78="Preparing"),ISNUMBER(Q78)),IF(AND(Q78>='Friday Summary'!$C$4,Q78<='Friday Summary'!$C$4+14),Q78+ROW()/1000000,""),"")
A79: =IF(B79="","","OP-"&TEXT(ROW()-4,"000")) | B79: AE/001/2026/27/HQ/W/18 (TZ-TANROADS-564086-CW-RFB) | C79: 46301 | D79: client site | E79: https://www.tanroads.go.tz/view/200 | F79: TANROADS | G79: government | H79: CONSTRUCTION OF LWANJI I BRIDGE (200M) SPAN ALONG MTOWISA – ILEMBA ROAD SECTION | I79: From client site notice (1 lot) – read the tender document | J79: Headquarters (from client's office – confirm site) | K79: civil | L79: See tender document | N79: unknown | O79: See tender document | P79: See tender document | Q79: 46328.417 | R79: See tender document | S79: N | T79: =IF(A79="","",IFERROR(INDEX('Bid-NoBid'!$T:$T,MATCH(A79,'Bid-NoBid'!$A:$A,0)),"")) | U79: =IF(A79="","",IFERROR(IF(OR(INDEX('Bid-NoBid'!$U:$U,MATCH(A79,'Bid-NoBid'!$A:$A,0))="",LEFT(INDEX('Bid-NoBid'!$U:$U,MATCH(A79,'Bid-NoBid'!$A:$A,0)),10)="Incomplete"),"Screen: "&AC79,INDEX('Bid-NoBid'!$U:$U,MATCH(A79,'Bid-NoBid'!$A:$A,0))),"Screen: "&AC79)) | W79: Watching | X79: Frank | AB79: TANROADS website | AC79: Check | AD79: Auto (TANROADS website): Construction tender kept for review (would have been dropped: Remote civil works) | AE79: =IF(ISNUMBER(Q79),ROUNDDOWN(Q79-NOW(),1),"") | AF79: =IF(OR(A79="",AE79=""),"",IF(NOT(OR(W79="Watching",W79="Preparing")),"",IF(AE79<0,"PASSED",IF(AND(AE79<=7,W79<>"Preparing"),"RED",IF(AE79<=14,"AMBER","GREEN"))))) | AG79: =IF(OR(A79="",NOT(OR(W79="Watching",W79="Preparing"))),"",IF(AND(ISNUMBER(M79),M79>=3000000000),"YES – ≥ TZS 3bn",IF(AND(ISNUMBER(AE79),AE79>=0,AE79<10,V79=""),"YES – <10 days",""))) | AI79: Read the notice and decide with the QS Director whether to pursue | AJ79: Auto-scan | AK79: TANROADS:ae001202627hqw18tztanroads564086cwrfb | AL79: =IF(AND(OR(W79="Watching",W79="Preparing"),ISNUMBER(Q79)),IF(AND(Q79>='Friday Summary'!$C$4,Q79<='Friday Summary'!$C$4+14),Q79+ROW()/1000000,""),"")
A80: =IF(B80="","","OP-"&TEXT(ROW()-4,"000")) | B80: 2165A/2026/2027/W/01 | C80: 46302 | D80: NeST | E80: https://nest.go.tz/tenders/published-tenders | F80: Forestry and Wood Industries Training Centre (fwitc) | G80: government | H80: Construction of Dormitory | I80: From NeST notice (1 lot) – read the tender document | J80: Iringa (Mufindi) (from client's office – confirm site) | K80: building | L80: NeST login needed | N80: unknown | O80: NeST login needed | P80: NeST login needed | Q80: 46308.583 | R80: NeST login needed | S80: N | T80: =IF(A80="","",IFERROR(INDEX('Bid-NoBid'!$T:$T,MATCH(A80,'Bid-NoBid'!$A:$A,0)),"")) | U80: =IF(A80="","",IFERROR(IF(OR(INDEX('Bid-NoBid'!$U:$U,MATCH(A80,'Bid-NoBid'!$A:$A,0))="",LEFT(INDEX('Bid-NoBid'!$U:$U,MATCH(A80,'Bid-NoBid'!$A:$A,0)),10)="Incomplete"),"Screen: "&AC80,INDEX('Bid-NoBid'!$U:$U,MATCH(A80,'Bid-NoBid'!$A:$A,0))),"Screen: "&AC80)) | W80: Watching | X80: Frank | AA80: 46301 | AB80: Small Works / Tender | AC80: Check | AD80: Auto (Small Works / Tender): Construction tender kept for review (would have been dropped: Remote and closing soon) | AE80: =IF(ISNUMBER(Q80),ROUNDDOWN(Q80-NOW(),1),"") | AF80: =IF(OR(A80="",AE80=""),"",IF(NOT(OR(W80="Watching",W80="Preparing")),"",IF(AE80<0,"PASSED",IF(AND(AE80<=7,W80<>"Preparing"),"RED",IF(AE80<=14,"AMBER","GREEN"))))) | AG80: =IF(OR(A80="",NOT(OR(W80="Watching",W80="Preparing"))),"",IF(AND(ISNUMBER(M80),M80>=3000000000),"YES – ≥ TZS 3bn",IF(AND(ISNUMBER(AE80),AE80>=0,AE80<10,V80=""),"YES – <10 days",""))) | AI80: Read the notice and decide with the QS Director whether to pursue | AJ80: Auto-scan | AK80: ce68c688-8de4-46a2-80bc-c2261f265b0e | AL80: =IF(AND(OR(W80="Watching",W80="Preparing"),ISNUMBER(Q80)),IF(AND(Q80>='Friday Summary'!$C$4,Q80<='Friday Summary'!$C$4+14),Q80+ROW()/1000000,""),"")
A81: =IF(B81="","","OP-"&TEXT(ROW()-4,"000")) | B81: 44/002/2026/2027/W/17 | C81: 46302 | D81: NeST | E81: https://nest.go.tz/tenders/published-tenders | F81: Tanzania Investment and Special Economic Zones | G81: government | H81: Rehabilitation and Construction of fence Wall at TISEZA Office Mabibo | I81: From NeST notice (1 lot) – read the tender document | J81: Dar es Salaam (Ilala) (from client's office – confirm site) | K81: renovation | L81: NeST login needed | N81: unknown | O81: NeST login needed | P81: NeST login needed | Q81: 46308.583 | R81: NeST login needed | S81: N | T81: =IF(A81="","",IFERROR(INDEX('Bid-NoBid'!$T:$T,MATCH(A81,'Bid-NoBid'!$A:$A,0)),"")) | U81: =IF(A81="","",IFERROR(IF(OR(INDEX('Bid-NoBid'!$U:$U,MATCH(A81,'Bid-NoBid'!$A:$A,0))="",LEFT(INDEX('Bid-NoBid'!$U:$U,MATCH(A81,'Bid-NoBid'!$A:$A,0)),10)="Incomplete"),"Screen: "&AC81,INDEX('Bid-NoBid'!$U:$U,MATCH(A81,'Bid-NoBid'!$A:$A,0))),"Screen: "&AC81)) | W81: Watching | X81: Frank | AA81: 46301 | AB81: Standard Invitation for Quotations -Works / Planned Tender | AC81: Check | AD81: Auto (Standard Invitation for Quotations -Works / Planned Tender): Quotation route – value may be below TZS 200m | AE81: =IF(ISNUMBER(Q81),ROUNDDOWN(Q81-NOW(),1),"") | AF81: =IF(OR(A81="",AE81=""),"",IF(NOT(OR(W81="Watching",W81="Preparing")),"",IF(AE81<0,"PASSED",IF(AND(AE81<=7,W81<>"Preparing"),"RED",IF(AE81<=14,"AMBER","GREEN"))))) | AG81: =IF(OR(A81="",NOT(OR(W81="Watching",W81="Preparing"))),"",IF(AND(ISNUMBER(M81),M81>=3000000000),"YES – ≥ TZS 3bn",IF(AND(ISNUMBER(AE81),AE81>=0,AE81<10,V81=""),"YES – <10 days",""))) | AI81: Read the notice and decide with the QS Director whether to pursue | AJ81: Auto-scan | AK81: dbec7a25-c9a5-48dd-88bb-663f1f3ac036 | AL81: =IF(AND(OR(W81="Watching",W81="Preparing"),ISNUMBER(Q81)),IF(AND(Q81>='Friday Summary'!$C$4,Q81<='Friday Summary'!$C$4+14),Q81+ROW()/1000000,""),"")
A82: =IF(B82="","","OP-"&TEXT(ROW()-4,"000")) | B82: TR72/2026/2027/W/06 | C82: 46302 | D82: NeST | E82: https://nest.go.tz/tenders/published-tenders | F82: National Museum of Tanzania | G82: government | H82: Construction and installation of tourism facilities (inc. reception point, exhibition gallery, pedestal, walkways, information panel) at Mbuamaji information Centre | I82: From NeST notice (1 lot) – read the tender document | J82: Dar es Salaam (Ilala) (from client's office – confirm site) | K82: building | L82: NeST login needed | N82: unknown | O82: NeST login needed | P82: NeST login needed | Q82: 46308.583 | R82: NeST login needed | S82: N | T82: =IF(A82="","",IFERROR(INDEX('Bid-NoBid'!$T:$T,MATCH(A82,'Bid-NoBid'!$A:$A,0)),"")) | U82: =IF(A82="","",IFERROR(IF(OR(INDEX('Bid-NoBid'!$U:$U,MATCH(A82,'Bid-NoBid'!$A:$A,0))="",LEFT(INDEX('Bid-NoBid'!$U:$U,MATCH(A82,'Bid-NoBid'!$A:$A,0)),10)="Incomplete"),"Screen: "&AC82,INDEX('Bid-NoBid'!$U:$U,MATCH(A82,'Bid-NoBid'!$A:$A,0))),"Screen: "&AC82)) | W82: Watching | X82: Frank | AA82: 46301 | AB82: Small Works / Tender | AC82: Pursue | AD82: Auto (Small Works / Tender): Building works within reach of Dar | AE82: =IF(ISNUMBER(Q82),ROUNDDOWN(Q82-NOW(),1),"") | AF82: =IF(OR(A82="",AE82=""),"",IF(NOT(OR(W82="Watching",W82="Preparing")),"",IF(AE82<0,"PASSED",IF(AND(AE82<=7,W82<>"Preparing"),"RED",IF(AE82<=14,"AMBER","GREEN"))))) | AG82: =IF(OR(A82="",NOT(OR(W82="Watching",W82="Preparing"))),"",IF(AND(ISNUMBER(M82),M82>=3000000000),"YES – ≥ TZS 3bn",IF(AND(ISNUMBER(AE82),AE82>=0,AE82<10,V82=""),"YES – <10 days",""))) | AI82: Get the tender document, confirm value, CRB class, site visit and bid security; brief the MD | AJ82: Auto-scan | AK82: 99f4eb7a-9c4e-46e4-96e2-268bccd3f027 | AL82: =IF(AND(OR(W82="Watching",W82="Preparing"),ISNUMBER(Q82)),IF(AND(Q82>='Friday Summary'!$C$4,Q82<='Friday Summary'!$C$4+14),Q82+ROW()/1000000,""),"")
A83: =IF(B83="","","OP-"&TEXT(ROW()-4,"000")) | B83: 83P9/2026/2027/W/03 | C83: 46302 | D83: NeST | E83: https://nest.go.tz/tenders/published-tenders | F83: Ushetu District Council | G83: government | H83: CONSTRUCTION OF ISANGA SECONDARY SCHOOL, USHETU DC- PRIMARY EDUCATION | I83: From NeST notice (1 lot) – read the tender document | J83: Shinyanga (Kahama) (from client's office – confirm site) | K83: building | L83: NeST login needed | N83: unknown | O83: NeST login needed | P83: NeST login needed | Q83: 46308.583 | R83: NeST login needed | S83: N | T83: =IF(A83="","",IFERROR(INDEX('Bid-NoBid'!$T:$T,MATCH(A83,'Bid-NoBid'!$A:$A,0)),"")) | U83: =IF(A83="","",IFERROR(IF(OR(INDEX('Bid-NoBid'!$U:$U,MATCH(A83,'Bid-NoBid'!$A:$A,0))="",LEFT(INDEX('Bid-NoBid'!$U:$U,MATCH(A83,'Bid-NoBid'!$A:$A,0)),10)="Incomplete"),"Screen: "&AC83,INDEX('Bid-NoBid'!$U:$U,MATCH(A83,'Bid-NoBid'!$A:$A,0))),"Screen: "&AC83)) | W83: Watching | X83: Frank | AA83: 46301 | AB83: Small Works / Tender | AC83: Check | AD83: Auto (Small Works / Tender): Construction tender kept for review (would have been dropped: Remote and closing soon) | AE83: =IF(ISNUMBER(Q83),ROUNDDOWN(Q83-NOW(),1),"") | AF83: =IF(OR(A83="",AE83=""),"",IF(NOT(OR(W83="Watching",W83="Preparing")),"",IF(AE83<0,"PASSED",IF(AND(AE83<=7,W83<>"Preparing"),"RED",IF(AE83<=14,"AMBER","GREEN"))))) | AG83: =IF(OR(A83="",NOT(OR(W83="Watching",W83="Preparing"))),"",IF(AND(ISNUMBER(M83),M83>=3000000000),"YES – ≥ TZS 3bn",IF(AND(ISNUMBER(AE83),AE83>=0,AE83<10,V83=""),"YES – <10 days",""))) | AI83: Read the notice and decide with the QS Director whether to pursue | AJ83: Auto-scan | AK83: d92c4de5-ae51-4854-9cdd-6a549d3c83c0 | AL83: =IF(AND(OR(W83="Watching",W83="Preparing"),ISNUMBER(Q83)),IF(AND(Q83>='Friday Summary'!$C$4,Q83<='Friday Summary'!$C$4+14),Q83+ROW()/1000000,""),"")
A84: =IF(B84="","","OP-"&TEXT(ROW()-4,"000")) | B84: 8626/2026/2027/W/16 | C84: 46302 | D84: NeST | E84: https://nest.go.tz/tenders/published-tenders | F84: Tanga City Council | G84: government | H84: To facilitate completion of dormitory at usagara secondary school | I84: From NeST notice (1 lot) – read the tender document | J84: Tanga (from client's office – confirm site) | K84: building | L84: NeST login needed | N84: unknown | O84: NeST login needed | P84: NeST login needed | Q84: 46310.583 | R84: NeST login needed | S84: N | T84: =IF(A84="","",IFERROR(INDEX('Bid-NoBid'!$T:$T,MATCH(A84,'Bid-NoBid'!$A:$A,0)),"")) | U84: =IF(A84="","",IFERROR(IF(OR(INDEX('Bid-NoBid'!$U:$U,MATCH(A84,'Bid-NoBid'!$A:$A,0))="",LEFT(INDEX('Bid-NoBid'!$U:$U,MATCH(A84,'Bid-NoBid'!$A:$A,0)),10)="Incomplete"),"Screen: "&AC84,INDEX('Bid-NoBid'!$U:$U,MATCH(A84,'Bid-NoBid'!$A:$A,0))),"Screen: "&AC84)) | W84: Watching | X84: Frank | AA84: 46302 | AB84: Small Works / Tender | AC84: Pursue | AD84: Auto (Small Works / Tender): Building works within reach of Dar | AE84: =IF(ISNUMBER(Q84),ROUNDDOWN(Q84-NOW(),1),"") | AF84: =IF(OR(A84="",AE84=""),"",IF(NOT(OR(W84="Watching",W84="Preparing")),"",IF(AE84<0,"PASSED",IF(AND(AE84<=7,W84<>"Preparing"),"RED",IF(AE84<=14,"AMBER","GREEN"))))) | AG84: =IF(OR(A84="",NOT(OR(W84="Watching",W84="Preparing"))),"",IF(AND(ISNUMBER(M84),M84>=3000000000),"YES – ≥ TZS 3bn",IF(AND(ISNUMBER(AE84),AE84>=0,AE84<10,V84=""),"YES – <10 days",""))) | AI84: Get the tender document, confirm value, CRB class, site visit and bid security; brief the MD | AJ84: Auto-scan | AK84: 75403178-54dc-4701-b739-7d0ba2e7b630 | AL84: =IF(AND(OR(W84="Watching",W84="Preparing"),ISNUMBER(Q84)),IF(AND(Q84>='Friday Summary'!$C$4,Q84<='Friday Summary'!$C$4+14),Q84+ROW()/1000000,""),"")
A85: =IF(B85="","","OP-"&TEXT(ROW()-4,"000")) | B85: 74E7/2026/2027/W/09 | C85: 46303 | D85: NeST | E85: https://nest.go.tz/tenders/published-tenders | F85: Kakonko District Council | G85: government | H85: CONSTRUCTION RCH AND WAITING BAY FOR HEALTH,SOCIAL,WALEFARE AND NUTRITION SERVICES DIVISION AT KAKONKO DISTRICT HOSPITAL | I85: From NeST notice (1 lot) – read the tender document | J85: Kigoma (from client's office – confirm site) | K85: building | L85: NeST login needed | N85: unknown | O85: NeST login needed | P85: NeST login needed | Q85: 46310.417 | R85: NeST login needed | S85: N | T85: =IF(A85="","",IFERROR(INDEX('Bid-NoBid'!$T:$T,MATCH(A85,'Bid-NoBid'!$A:$A,0)),"")) | U85: =IF(A85="","",IFERROR(IF(OR(INDEX('Bid-NoBid'!$U:$U,MATCH(A85,'Bid-NoBid'!$A:$A,0))="",LEFT(INDEX('Bid-NoBid'!$U:$U,MATCH(A85,'Bid-NoBid'!$A:$A,0)),10)="Incomplete"),"Screen: "&AC85,INDEX('Bid-NoBid'!$U:$U,MATCH(A85,'Bid-NoBid'!$A:$A,0))),"Screen: "&AC85)) | W85: Watching | X85: Frank | AA85: 46303 | AB85: Standard Invitation for Quotations -Works / Planned Tender | AC85: Check | AD85: Auto (Standard Invitation for Quotations -Works / Planned Tender): Building works but remote from Dar | AE85: =IF(ISNUMBER(Q85),ROUNDDOWN(Q85-NOW(),1),"") | AF85: =IF(OR(A85="",AE85=""),"",IF(NOT(OR(W85="Watching",W85="Preparing")),"",IF(AE85<0,"PASSED",IF(AND(AE85<=7,W85<>"Preparing"),"RED",IF(AE85<=14,"AMBER","GREEN"))))) | AG85: =IF(OR(A85="",NOT(OR(W85="Watching",W85="Preparing"))),"",IF(AND(ISNUMBER(M85),M85>=3000000000),"YES – ≥ TZS 3bn",IF(AND(ISNUMBER(AE85),AE85>=0,AE85<10,V85=""),"YES – <10 days",""))) | AI85: Read the notice and decide with the QS Director whether to pursue | AJ85: Auto-scan | AK85: 2912339b-fd1f-4162-a973-c973238584f2 | AL85: =IF(AND(OR(W85="Watching",W85="Preparing"),ISNUMBER(Q85)),IF(AND(Q85>='Friday Summary'!$C$4,Q85<='Friday Summary'!$C$4+14),Q85+ROW()/1000000,""),"")
A86: =IF(B86="","","OP-"&TEXT(ROW()-4,"000")) | B86: 8219/2026/2027/W/11 | C86: 46303 | D86: NeST | E86: https://nest.go.tz/tenders/published-tenders | F86: Songea Municipal Council | G86: government | H86: PROPOSED COMPLETION OF RESIDENTIAL HOUSE FOR COUNCIL HEAD OF DEPARTMENTS AT SONGEA MUNICIPAL | I86: From NeST notice (1 lot) – read the tender document | J86: Ruvuma (Songea) | K86: building | L86: NeST login needed | N86: unknown | O86: NeST login needed | P86: NeST login needed | Q86: 46310.417 | R86: NeST login needed | S86: N | T86: =IF(A86="","",IFERROR(INDEX('Bid-NoBid'!$T:$T,MATCH(A86,'Bid-NoBid'!$A:$A,0)),"")) | U86: =IF(A86="","",IFERROR(IF(OR(INDEX('Bid-NoBid'!$U:$U,MATCH(A86,'Bid-NoBid'!$A:$A,0))="",LEFT(INDEX('Bid-NoBid'!$U:$U,MATCH(A86,'Bid-NoBid'!$A:$A,0)),10)="Incomplete"),"Screen: "&AC86,INDEX('Bid-NoBid'!$U:$U,MATCH(A86,'Bid-NoBid'!$A:$A,0))),"Screen: "&AC86)) | W86: Watching | X86: Frank | AA86: 46303 | AB86: Small Works / Tender | AC86: Check | AD86: Auto (Small Works / Tender): Building works but remote from Dar | AE86: =IF(ISNUMBER(Q86),ROUNDDOWN(Q86-NOW(),1),"") | AF86: =IF(OR(A86="",AE86=""),"",IF(NOT(OR(W86="Watching",W86="Preparing")),"",IF(AE86<0,"PASSED",IF(AND(AE86<=7,W86<>"Preparing"),"RED",IF(AE86<=14,"AMBER","GREEN"))))) | AG86: =IF(OR(A86="",NOT(OR(W86="Watching",W86="Preparing"))),"",IF(AND(ISNUMBER(M86),M86>=3000000000),"YES – ≥ TZS 3bn",IF(AND(ISNUMBER(AE86),AE86>=0,AE86<10,V86=""),"YES – <10 days",""))) | AI86: Read the notice and decide with the QS Director whether to pursue | AJ86: Auto-scan | AK86: df22b8c6-4dfa-4955-8e3b-e1708939155e | AL86: =IF(AND(OR(W86="Watching",W86="Preparing"),ISNUMBER(Q86)),IF(AND(Q86>='Friday Summary'!$C$4,Q86<='Friday Summary'!$C$4+14),Q86+ROW()/1000000,""),"")
A87: =IF(B87="","","OP-"&TEXT(ROW()-4,"000")) | B87: 81M9/2026/2027/W/01 | C87: 46303 | D87: NeST | E87: https://nest.go.tz/tenders/published-tenders | F87: Buchosa District Council | G87: government | H87: CONSTRUCTION OF A MODERN MARKET TO BE BUILT IN NYEHUNGE TOWN ,BUCHOSA DISTRICT ,MWANZA REGION ,TANZANIA | I87: From NeST notice (1 lot) – read the tender document | J87: Mwanza | K87: building | L87: NeST login needed | N87: unknown | O87: NeST login needed | P87: NeST login needed | Q87: 46310.583 | R87: NeST login needed | S87: N | T87: =IF(A87="","",IFERROR(INDEX('Bid-NoBid'!$T:$T,MATCH(A87,'Bid-NoBid'!$A:$A,0)),"")) | U87: =IF(A87="","",IFERROR(IF(OR(INDEX('Bid-NoBid'!$U:$U,MATCH(A87,'Bid-NoBid'!$A:$A,0))="",LEFT(INDEX('Bid-NoBid'!$U:$U,MATCH(A87,'Bid-NoBid'!$A:$A,0)),10)="Incomplete"),"Screen: "&AC87,INDEX('Bid-NoBid'!$U:$U,MATCH(A87,'Bid-NoBid'!$A:$A,0))),"Screen: "&AC87)) | W87: Watching | X87: Frank | AA87: 46303 | AB87: Small Works / Tender | AC87: Check | AD87: Auto (Small Works / Tender): Building works but remote from Dar | AE87: =IF(ISNUMBER(Q87),ROUNDDOWN(Q87-NOW(),1),"") | AF87: =IF(OR(A87="",AE87=""),"",IF(NOT(OR(W87="Watching",W87="Preparing")),"",IF(AE87<0,"PASSED",IF(AND(AE87<=7,W87<>"Preparing"),"RED",IF(AE87<=14,"AMBER","GREEN"))))) | AG87: =IF(OR(A87="",NOT(OR(W87="Watching",W87="Preparing"))),"",IF(AND(ISNUMBER(M87),M87>=3000000000),"YES – ≥ TZS 3bn",IF(AND(ISNUMBER(AE87),AE87>=0,AE87<10,V87=""),"YES – <10 days",""))) | AI87: Read the notice and decide with the QS Director whether to pursue | AJ87: Auto-scan | AK87: fa83f9bd-caf5-4b4e-9539-883b0162fadc | AL87: =IF(AND(OR(W87="Watching",W87="Preparing"),ISNUMBER(Q87)),IF(AND(Q87>='Friday Summary'!$C$4,Q87<='Friday Summary'!$C$4+14),Q87+ROW()/1000000,""),"")
A88: =IF(B88="","","OP-"&TEXT(ROW()-4,"000")) | B88: TR61/2026/2027/W/06 | C88: 46303 | D88: NeST | E88: https://nest.go.tz/tenders/published-tenders | F88: Tanzania Broadcasting Corporation | G88: parastatal (verify) | H88: Procurement for construction of fance walls for TBC transmition sites | I88: From NeST notice (1 lot) – read the tender document | J88: Dar es Salaam (Temeke) (from client's office – confirm site) | K88: building | L88: NeST login needed | N88: unknown | O88: NeST login needed | P88: NeST login needed | Q88: 46310.583 | R88: NeST login needed | S88: N | T88: =IF(A88="","",IFERROR(INDEX('Bid-NoBid'!$T:$T,MATCH(A88,'Bid-NoBid'!$A:$A,0)),"")) | U88: =IF(A88="","",IFERROR(IF(OR(INDEX('Bid-NoBid'!$U:$U,MATCH(A88,'Bid-NoBid'!$A:$A,0))="",LEFT(INDEX('Bid-NoBid'!$U:$U,MATCH(A88,'Bid-NoBid'!$A:$A,0)),10)="Incomplete"),"Screen: "&AC88,INDEX('Bid-NoBid'!$U:$U,MATCH(A88,'Bid-NoBid'!$A:$A,0))),"Screen: "&AC88)) | W88: Watching | X88: Frank | AA88: 46303 | AB88: Standard Invitation for Quotations -Works / Planned Tender | AC88: Check | AD88: Auto (Standard Invitation for Quotations -Works / Planned Tender): Quotation route – value may be below TZS 200m | AE88: =IF(ISNUMBER(Q88),ROUNDDOWN(Q88-NOW(),1),"") | AF88: =IF(OR(A88="",AE88=""),"",IF(NOT(OR(W88="Watching",W88="Preparing")),"",IF(AE88<0,"PASSED",IF(AND(AE88<=7,W88<>"Preparing"),"RED",IF(AE88<=14,"AMBER","GREEN"))))) | AG88: =IF(OR(A88="",NOT(OR(W88="Watching",W88="Preparing"))),"",IF(AND(ISNUMBER(M88),M88>=3000000000),"YES – ≥ TZS 3bn",IF(AND(ISNUMBER(AE88),AE88>=0,AE88<10,V88=""),"YES – <10 days",""))) | AI88: Read the notice and decide with the QS Director whether to pursue | AJ88: Auto-scan | AK88: 596820cb-5b8c-431f-bff5-0de6b9e72096 | AL88: =IF(AND(OR(W88="Watching",W88="Preparing"),ISNUMBER(Q88)),IF(AND(Q88>='Friday Summary'!$C$4,Q88<='Friday Summary'!$C$4+14),Q88+ROW()/1000000,""),"")
A89: =IF(B89="","","OP-"&TEXT(ROW()-4,"000")) | B89: 75F4/2026/2027/W/24 | C89: 46303 | D89: NeST | E89: https://nest.go.tz/tenders/published-tenders | F89: Hai District Council | G89: government | H89: Construction & Rehabilitation work of Single Box Culvert (1mx1m) Kalali-Kasau Road and Nkwashowa Pedestrian Bridge at Machame Kaskazini - Hai district | I89: From NeST notice (1 lot) – read the tender document | J89: Kilimanjaro (Hai) (from client's office – confirm site) | K89: renovation | L89: NeST login needed | N89: unknown | O89: NeST login needed | P89: NeST login needed | Q89: 46310.583 | R89: NeST login needed | S89: N | T89: =IF(A89="","",IFERROR(INDEX('Bid-NoBid'!$T:$T,MATCH(A89,'Bid-NoBid'!$A:$A,0)),"")) | U89: =IF(A89="","",IFERROR(IF(OR(INDEX('Bid-NoBid'!$U:$U,MATCH(A89,'Bid-NoBid'!$A:$A,0))="",LEFT(INDEX('Bid-NoBid'!$U:$U,MATCH(A89,'Bid-NoBid'!$A:$A,0)),10)="Incomplete"),"Screen: "&AC89,INDEX('Bid-NoBid'!$U:$U,MATCH(A89,'Bid-NoBid'!$A:$A,0))),"Screen: "&AC89)) | W89: Watching | X89: Frank | AA89: 46302 | AB89: Small Works / Tender | AC89: Check | AD89: Auto (Small Works / Tender): Building works but remote from Dar | AE89: =IF(ISNUMBER(Q89),ROUNDDOWN(Q89-NOW(),1),"") | AF89: =IF(OR(A89="",AE89=""),"",IF(NOT(OR(W89="Watching",W89="Preparing")),"",IF(AE89<0,"PASSED",IF(AND(AE89<=7,W89<>"Preparing"),"RED",IF(AE89<=14,"AMBER","GREEN"))))) | AG89: =IF(OR(A89="",NOT(OR(W89="Watching",W89="Preparing"))),"",IF(AND(ISNUMBER(M89),M89>=3000000000),"YES – ≥ TZS 3bn",IF(AND(ISNUMBER(AE89),AE89>=0,AE89<10,V89=""),"YES – <10 days",""))) | AI89: Read the notice and decide with the QS Director whether to pursue | AJ89: Auto-scan | AK89: 0e6c7ba8-cc19-46a9-b5cc-8735d6214c9d | AL89: =IF(AND(OR(W89="Watching",W89="Preparing"),ISNUMBER(Q89)),IF(AND(Q89>='Friday Summary'!$C$4,Q89<='Friday Summary'!$C$4+14),Q89+ROW()/1000000,""),"")
A90: =IF(B90="","","OP-"&TEXT(ROW()-4,"000")) | B90: 83P9/2026/2027/W/04 | C90: 46303 | D90: NeST | E90: https://nest.go.tz/tenders/published-tenders | F90: Ushetu District Council | G90: government | H90: CONSTRUCTION OF KALO SECONDARY SCHOOL USHETU DISTRICT COUNCIL- PRIMARY EDUCATION DIVISION | I90: From NeST notice (1 lot) – read the tender document | J90: Shinyanga (Kahama) (from client's office – confirm site) | K90: building | L90: NeST login needed | N90: unknown | O90: NeST login needed | P90: NeST login needed | Q90: 46310.583 | R90: NeST login needed | S90: N | T90: =IF(A90="","",IFERROR(INDEX('Bid-NoBid'!$T:$T,MATCH(A90,'Bid-NoBid'!$A:$A,0)),"")) | U90: =IF(A90="","",IFERROR(IF(OR(INDEX('Bid-NoBid'!$U:$U,MATCH(A90,'Bid-NoBid'!$A:$A,0))="",LEFT(INDEX('Bid-NoBid'!$U:$U,MATCH(A90,'Bid-NoBid'!$A:$A,0)),10)="Incomplete"),"Screen: "&AC90,INDEX('Bid-NoBid'!$U:$U,MATCH(A90,'Bid-NoBid'!$A:$A,0))),"Screen: "&AC90)) | W90: Watching | X90: Frank | AA90: 46302 | AB90: Small Works / Tender | AC90: Check | AD90: Auto (Small Works / Tender): Building works but remote from Dar | AE90: =IF(ISNUMBER(Q90),ROUNDDOWN(Q90-NOW(),1),"") | AF90: =IF(OR(A90="",AE90=""),"",IF(NOT(OR(W90="Watching",W90="Preparing")),"",IF(AE90<0,"PASSED",IF(AND(AE90<=7,W90<>"Preparing"),"RED",IF(AE90<=14,"AMBER","GREEN"))))) | AG90: =IF(OR(A90="",NOT(OR(W90="Watching",W90="Preparing"))),"",IF(AND(ISNUMBER(M90),M90>=3000000000),"YES – ≥ TZS 3bn",IF(AND(ISNUMBER(AE90),AE90>=0,AE90<10,V90=""),"YES – <10 days",""))) | AI90: Read the notice and decide with the QS Director whether to pursue | AJ90: Auto-scan | AK90: 324d730a-a16a-4b9c-b3f6-5cea96733864 | AL90: =IF(AND(OR(W90="Watching",W90="Preparing"),ISNUMBER(Q90)),IF(AND(Q90>='Friday Summary'!$C$4,Q90<='Friday Summary'!$C$4+14),Q90+ROW()/1000000,""),"")
A91: =IF(B91="","","OP-"&TEXT(ROW()-4,"000")) | B91: TR219/2026/2027/W/10 | C91: 46303 | D91: NeST | E91: https://nest.go.tz/tenders/published-tenders | F91: Tanzania National Parks | G91: government | H91: CONSTRUCTION OF BRIDGES AT VIBOKO VYA NAABI, BANAGI AND WARANGI YA JUU IN SERENGETI NATIONAL PARK | I91: From NeST notice (1 lot) – read the tender document | J91: Arusha (from client's office – confirm site) | K91: civil | L91: NeST login needed | N91: unknown | O91: NeST login needed | P91: NeST login needed | Q91: 46310.583 | R91: NeST login needed | S91: N | T91: =IF(A91="","",IFERROR(INDEX('Bid-NoBid'!$T:$T,MATCH(A91,'Bid-NoBid'!$A:$A,0)),"")) | U91: =IF(A91="","",IFERROR(IF(OR(INDEX('Bid-NoBid'!$U:$U,MATCH(A91,'Bid-NoBid'!$A:$A,0))="",LEFT(INDEX('Bid-NoBid'!$U:$U,MATCH(A91,'Bid-NoBid'!$A:$A,0)),10)="Incomplete"),"Screen: "&AC91,INDEX('Bid-NoBid'!$U:$U,MATCH(A91,'Bid-NoBid'!$A:$A,0))),"Screen: "&AC91)) | W91: Watching | X91: Frank | AA91: 46302 | AB91: Small Works / Tender | AC91: Check | AD91: Auto (Small Works / Tender): Construction tender kept for review (would have been dropped: Remote civil works) | AE91: =IF(ISNUMBER(Q91),ROUNDDOWN(Q91-NOW(),1),"") | AF91: =IF(OR(A91="",AE91=""),"",IF(NOT(OR(W91="Watching",W91="Preparing")),"",IF(AE91<0,"PASSED",IF(AND(AE91<=7,W91<>"Preparing"),"RED",IF(AE91<=14,"AMBER","GREEN"))))) | AG91: =IF(OR(A91="",NOT(OR(W91="Watching",W91="Preparing"))),"",IF(AND(ISNUMBER(M91),M91>=3000000000),"YES – ≥ TZS 3bn",IF(AND(ISNUMBER(AE91),AE91>=0,AE91<10,V91=""),"YES – <10 days",""))) | AI91: Read the notice and decide with the QS Director whether to pursue | AJ91: Auto-scan | AK91: 6183745f-14c8-4916-a02c-a704776621e4 | AL91: =IF(AND(OR(W91="Watching",W91="Preparing"),ISNUMBER(Q91)),IF(AND(Q91>='Friday Summary'!$C$4,Q91<='Friday Summary'!$C$4+14),Q91+ROW()/1000000,""),"")
... A96: =IF(B96="","","OP-"&TEXT(ROW()-4,"000")) | B96: TZ-POFP-575401-CW-RFB | C96: 46304 | D96: donor | E96: https://projects.worldbank.org/en/projects-operations/procurement-detail/OP00473952 | F96: President's Office-finance and Planning | G96: donor | H96: Integrated Tourism Development, Infrastructure and Livelihood Improvement in Unguja, (Nungwi village) - Construction of Village Square, Tourist Information Centre, Fish Market, Parking, Urban Furniture, Tide-Defence Embankment and Food Vending Stalls | I96: World Bank project: Boosting Inclusive Growth for Zanzibar: Integrated Development Project (P165128) | J96: Zanzibar (Unguja) | K96: civil | L96: See tender document | N96: Y | O96: See tender document | P96: See tender document | Q96: 46336.458 | R96: See tender document | S96: N | T96: =IF(A96="","",IFERROR(INDEX('Bid-NoBid'!$T:$T,MATCH(A96,'Bid-NoBid'!$A:$A,0)),"")) | U96: =IF(A96="","",IFERROR(IF(OR(INDEX('Bid-NoBid'!$U:$U,MATCH(A96,'Bid-NoBid'!$A:$A,0))="",LEFT(INDEX('Bid-NoBid'!$U:$U,MATCH(A96,'Bid-NoBid'!$A:$A,0)),10)="Incomplete"),"Screen: "&AC96,INDEX('Bid-NoBid'!$U:$U,MATCH(A96,'Bid-NoBid'!$A:$A,0))),"Screen: "&AC96)) | W96: Watching | X96: Frank | AA96: 46303 | AB96: World Bank – Invitation for Bids (Request for Bids) | AC96: Check | AD96: Auto (World Bank – Invitation for Bids): Civil works – confirm site, CRB class and margin | AE96: =IF(ISNUMBER(Q96),ROUNDDOWN(Q96-NOW(),1),"") | AF96: =IF(OR(A96="",AE96=""),"",IF(NOT(OR(W96="Watching",W96="Preparing")),"",IF(AE96<0,"PASSED",IF(AND(AE96<=7,W96<>"Preparing"),"RED",IF(AE96<=14,"AMBER","GREEN"))))) | AG96: =IF(OR(A96="",NOT(OR(W96="Watching",W96="Preparing"))),"",IF(AND(ISNUMBER(M96),M96>=3000000000),"YES – ≥ TZS 3bn",IF(AND(ISNUMBER(AE96),AE96>=0,AE96<10,V96=""),"YES – <10 days",""))) | AI96: Read the notice and decide with the QS Director whether to pursue | AJ96: Auto-scan | AK96: WB:OP00473952 | AL96: =IF(AND(OR(W96="Watching",W96="Preparing"),ISNUMBER(Q96)),IF(AND(Q96>='Friday Summary'!$C$4,Q96<='Friday Summary'!$C$4+14),Q96+ROW()/1000000,""),"")
A97: =IF(B97="","","OP-"&TEXT(ROW()-4,"000")) | B97: (not shown) | C97: 46305 | D97: client site | E97: https://www.trc.co.tz/uploads/vacancies/sw1776962195-23042026-INVITATION TO EME WORKSHOP.pdf | F97: Tanzania Railways Corporation (TRC) | G97: parastatal | H97: INVITATION TO EARLY MARKET ENGAGEMENT (EME) WORKSHOP (PHYSICAL AND VIRTUAL CONSULTATIVE MEETING) | I97: From client site notice (1 lot) – read the tender document | J97: Not stated – read the notice | K97: building | L97: See tender document | N97: unknown | O97: See tender document | P97: See tender document | R97: See tender document | S97: N | T97: =IF(A97="","",IFERROR(INDEX('Bid-NoBid'!$T:$T,MATCH(A97,'Bid-NoBid'!$A:$A,0)),"")) | U97: =IF(A97="","",IFERROR(IF(OR(INDEX('Bid-NoBid'!$U:$U,MATCH(A97,'Bid-NoBid'!$A:$A,0))="",LEFT(INDEX('Bid-NoBid'!$U:$U,MATCH(A97,'Bid-NoBid'!$A:$A,0)),10)="Incomplete"),"Screen: "&AC97,INDEX('Bid-NoBid'!$U:$U,MATCH(A97,'Bid-NoBid'!$A:$A,0))),"Screen: "&AC97)) | W97: Watching | X97: Frank | AB97: TRC tenders (web page) | AC97: Check | AD97: Auto (TRC tenders): Deadline not shown on the source page – open the link and read the notice | AE97: =IF(ISNUMBER(Q97),ROUNDDOWN(Q97-NOW(),1),"") | AF97: =IF(OR(A97="",AE97=""),"",IF(NOT(OR(W97="Watching",W97="Preparing")),"",IF(AE97<0,"PASSED",IF(AND(AE97<=7,W97<>"Preparing"),"RED",IF(AE97<=14,"AMBER","GREEN"))))) | AG97: =IF(OR(A97="",NOT(OR(W97="Watching",W97="Preparing"))),"",IF(AND(ISNUMBER(M97),M97>=3000000000),"YES – ≥ TZS 3bn",IF(AND(ISNUMBER(AE97),AE97>=0,AE97<10,V97=""),"YES – <10 days",""))) | AI97: Read the notice and decide with the QS Director whether to pursue | AJ97: Auto-scan | AK97: WEB:trc_tenders:2d2c9dbdb237c3a4 | AL97: =IF(AND(OR(W97="Watching",W97="Preparing"),ISNUMBER(Q97)),IF(AND(Q97>='Friday Summary'!$C$4,Q97<='Friday Summary'!$C$4+14),Q97+ROW()/1000000,""),"")
A98: =IF(B98="","","OP-"&TEXT(ROW()-4,"000")) | B98: (not shown) | C98: 46305 | D98: client site | E98: https://www.tcra.go.tz/tcra-tovuti/2022/mamlaka-website/documents/tenders/en_1669799349_INVITATION_FOR_TENDERS_Conference_Hall_Facilities_PAPU_House_b8fc297abe.pdf | F98: Tanzania Communications Regulatory Authority (TCRA) | G98: government | H98: Tenders 0 5 29 th Nov, 2022 DESIGN AND INSTALLATION OF MULTIPURPOSE CONFERENCE HALL FACILITIES TO THE PAPU HOUSE Download View | I98: From client site notice (1 lot) – read the tender document | J98: Not stated – read the notice | K98: building | L98: See tender document | N98: unknown | O98: See tender document | P98: See tender document | R98: See tender document | S98: N | T98: =IF(A98="","",IFERROR(INDEX('Bid-NoBid'!$T:$T,MATCH(A98,'Bid-NoBid'!$A:$A,0)),"")) | U98: =IF(A98="","",IFERROR(IF(OR(INDEX('Bid-NoBid'!$U:$U,MATCH(A98,'Bid-NoBid'!$A:$A,0))="",LEFT(INDEX('Bid-NoBid'!$U:$U,MATCH(A98,'Bid-NoBid'!$A:$A,0)),10)="Incomplete"),"Screen: "&AC98,INDEX('Bid-NoBid'!$U:$U,MATCH(A98,'Bid-NoBid'!$A:$A,0))),"Screen: "&AC98)) | W98: Watching | X98: Frank | AB98: TCRA tenders (web page) | AC98: Check | AD98: Auto (TCRA tenders): Deadline not shown on the source page – open the link and read the notice | AE98: =IF(ISNUMBER(Q98),ROUNDDOWN(Q98-NOW(),1),"") | AF98: =IF(OR(A98="",AE98=""),"",IF(NOT(OR(W98="Watching",W98="Preparing")),"",IF(AE98<0,"PASSED",IF(AND(AE98<=7,W98<>"Preparing"),"RED",IF(AE98<=14,"AMBER","GREEN"))))) | AG98: =IF(OR(A98="",NOT(OR(W98="Watching",W98="Preparing"))),"",IF(AND(ISNUMBER(M98),M98>=3000000000),"YES – ≥ TZS 3bn",IF(AND(ISNUMBER(AE98),AE98>=0,AE98<10,V98=""),"YES – <10 days",""))) | AI98: Read the notice and decide with the QS Director whether to pursue | AJ98: Auto-scan | AK98: WEB:tcra_tenders:8741399c3b5cdb7b | AL98: =IF(AND(OR(W98="Watching",W98="Preparing"),ISNUMBER(Q98)),IF(AND(Q98>='Friday Summary'!$C$4,Q98<='Friday Summary'!$C$4+14),Q98+ROW()/1000000,""),"")
A99: =IF(B99="","","OP-"&TEXT(ROW()-4,"000")) | B99: 020/HQ/2022-23/W/05 | C99: 46305 | D99: client site | E99: https://www.tcra.go.tz/tcra-tovuti/2023/mamlaka-website/documents/tenders/en_1673772233_Extension_of_Tender_Submission_Deadline_for_Proposed_design_and_Installation_of_Multipurpose_Conference_Hall_06b81863fa.pdf | F99: Tanzania Communications Regulatory Authority (TCRA) | G99: government | H99: EXTENSION OF TENDER SUBMISSION DEADLINE FOR PROPOSED DESIGN AND INSTALLATION OF MULTIPURPOSE CONFERENCE HALL FACILITIES AT PAPU HOUSE PROJECT (TENDER NO. AE-020/HQ/2022-23/W/05) | I99: From client site notice (1 lot) – read the tender document | J99: Not stated – read the notice | K99: building | L99: See tender document | N99: unknown | O99: See tender document | P99: See tender document | R99: See tender document | S99: N | T99: =IF(A99="","",IFERROR(INDEX('Bid-NoBid'!$T:$T,MATCH(A99,'Bid-NoBid'!$A:$A,0)),"")) | U99: =IF(A99="","",IFERROR(IF(OR(INDEX('Bid-NoBid'!$U:$U,MATCH(A99,'Bid-NoBid'!$A:$A,0))="",LEFT(INDEX('Bid-NoBid'!$U:$U,MATCH(A99,'Bid-NoBid'!$A:$A,0)),10)="Incomplete"),"Screen: "&AC99,INDEX('Bid-NoBid'!$U:$U,MATCH(A99,'Bid-NoBid'!$A:$A,0))),"Screen: "&AC99)) | W99: Watching | X99: Frank | AB99: TCRA tenders (web page) | AC99: Check | AD99: Auto (TCRA tenders): Deadline not shown on the source page – open the link and read the notice | AE99: =IF(ISNUMBER(Q99),ROUNDDOWN(Q99-NOW(),1),"") | AF99: =IF(OR(A99="",AE99=""),"",IF(NOT(OR(W99="Watching",W99="Preparing")),"",IF(AE99<0,"PASSED",IF(AND(AE99<=7,W99<>"Preparing"),"RED",IF(AE99<=14,"AMBER","GREEN"))))) | AG99: =IF(OR(A99="",NOT(OR(W99="Watching",W99="Preparing"))),"",IF(AND(ISNUMBER(M99),M99>=3000000000),"YES – ≥ TZS 3bn",IF(AND(ISNUMBER(AE99),AE99>=0,AE99<10,V99=""),"YES – <10 days",""))) | AI99: Read the notice and decide with the QS Director whether to pursue | AJ99: Auto-scan | AK99: WEB:tcra_tenders:020hq202223w05 | AL99: =IF(AND(OR(W99="Watching",W99="Preparing"),ISNUMBER(Q99)),IF(AND(Q99>='Friday Summary'!$C$4,Q99<='Friday Summary'!$C$4+14),Q99+ROW()/1000000,""),"")
A100: =IF(B100="","","OP-"&TEXT(ROW()-4,"000")) | B100: (not shown) | C100: 46305 | D100: client site | E100: https://www.azaniabank.co.tz/tenders | F100: Azania Bank | G100: bank | H100: Tender Document General Office Stationary(Feb 2026) | I100: From client site notice (1 lot) – read the tender document | J100: Not stated – read the notice | K100: building | L100: See tender document | N100: unknown | O100: See tender document | P100: See tender document | R100: See tender document | S100: N | T100: =IF(A100="","",IFERROR(INDEX('Bid-NoBid'!$T:$T,MATCH(A100,'Bid-NoBid'!$A:$A,0)),"")) | U100: =IF(A100="","",IFERROR(IF(OR(INDEX('Bid-NoBid'!$U:$U,MATCH(A100,'Bid-NoBid'!$A:$A,0))="",LEFT(INDEX('Bid-NoBid'!$U:$U,MATCH(A100,'Bid-NoBid'!$A:$A,0)),10)="Incomplete"),"Screen: "&AC100,INDEX('Bid-NoBid'!$U:$U,MATCH(A100,'Bid-NoBid'!$A:$A,0))),"Screen: "&AC100)) | W100: Watching | X100: Frank | AB100: Azania Bank tenders (web page) | AC100: Check | AD100: Auto (Azania Bank tenders): Deadline not shown on the source page – open the link and read the notice | AE100: =IF(ISNUMBER(Q100),ROUNDDOWN(Q100-NOW(),1),"") | AF100: =IF(OR(A100="",AE100=""),"",IF(NOT(OR(W100="Watching",W100="Preparing")),"",IF(AE100<0,"PASSED",IF(AND(AE100<=7,W100<>"Preparing"),"RED",IF(AE100<=14,"AMBER","GREEN"))))) | AG100: =IF(OR(A100="",NOT(OR(W100="Watching",W100="Preparing"))),"",IF(AND(ISNUMBER(M100),M100>=3000000000),"YES – ≥ TZS 3bn",IF(AND(ISNUMBER(AE100),AE100>=0,AE100<10,V100=""),"YES – <10 days",""))) | AI100: Read the notice and decide with the QS Director whether to pursue | AJ100: Auto-scan | AK100: WEB:azania_bank_tenders:10518268ac56a68d | AL100: =IF(AND(OR(W100="Watching",W100="Preparing"),ISNUMBER(Q100)),IF(AND(Q100>='Friday Summary'!$C$4,Q100<='Friday Summary'!$C$4+14),Q100+ROW()/1000000,""),"")
A101: =IF(B101="","","OP-"&TEXT(ROW()-4,"000")) | B101: (not shown) | C101: 46305 | D101: client site | E101: https://www.azaniabank.co.tz/tenders | F101: Azania Bank | G101: bank | H101: Call Center System with CRM Capabilities View Tender View Notice View Clarification | I101: From client site notice (1 lot) – read the tender document | J101: Not stated – read the notice | K101: building | L101: See tender document | N101: unknown | O101: See tender document | P101: See tender document | R101: See tender document | S101: N | T101: =IF(A101="","",IFERROR(INDEX('Bid-NoBid'!$T:$T,MATCH(A101,'Bid-NoBid'!$A:$A,0)),"")) | U101: =IF(A101="","",IFERROR(IF(OR(INDEX('Bid-NoBid'!$U:$U,MATCH(A101,'Bid-NoBid'!$A:$A,0))="",LEFT(INDEX('Bid-NoBid'!$U:$U,MATCH(A101,'Bid-NoBid'!$A:$A,0)),10)="Incomplete"),"Screen: "&AC101,INDEX('Bid-NoBid'!$U:$U,MATCH(A101,'Bid-NoBid'!$A:$A,0))),"Screen: "&AC101)) | W101: Watching | X101: Frank | AB101: Azania Bank tenders (web page) | AC101: Check | AD101: Auto (Azania Bank tenders): Deadline not shown on the source page – open the link and read the notice | AE101: =IF(ISNUMBER(Q101),ROUNDDOWN(Q101-NOW(),1),"") | AF101: =IF(OR(A101="",AE101=""),"",IF(NOT(OR(W101="Watching",W101="Preparing")),"",IF(AE101<0,"PASSED",IF(AND(AE101<=7,W101<>"Preparing"),"RED",IF(AE101<=14,"AMBER","GREEN"))))) | AG101: =IF(OR(A101="",NOT(OR(W101="Watching",W101="Preparing"))),"",IF(AND(ISNUMBER(M101),M101>=3000000000),"YES – ≥ TZS 3bn",IF(AND(ISNUMBER(AE101),AE101>=0,AE101<10,V101=""),"YES – <10 days",""))) | AI101: Read the notice and decide with the QS Director whether to pursue | AJ101: Auto-scan | AK101: WEB:azania_bank_tenders:d11dd6cf8d033172 | AL101: =IF(AND(OR(W101="Watching",W101="Preparing"),ISNUMBER(Q101)),IF(AND(Q101>='Friday Summary'!$C$4,Q101<='Friday Summary'!$C$4+14),Q101+ROW()/1000000,""),"")
A102: =IF(B102="","","OP-"&TEXT(ROW()-4,"000")) | B102: (not shown) | C102: 46305 | D102: client site | E102: https://www.azaniabank.co.tz/tenders | F102: Azania Bank | G102: bank | H102: Pre-qualification for Contractors for Remodeling, Fit-out, Refurbishment Works for Bank Branches (May 2025) | I102: From client site notice (1 lot) – read the tender document | J102: Not stated – read the notice | K102: fit-out | L102: See tender document | N102: unknown | O102: See tender document | P102: See tender document | R102: See tender document | S102: N | T102: =IF(A102="","",IFERROR(INDEX('Bid-NoBid'!$T:$T,MATCH(A102,'Bid-NoBid'!$A:$A,0)),"")) | U102: =IF(A102="","",IFERROR(IF(OR(INDEX('Bid-NoBid'!$U:$U,MATCH(A102,'Bid-NoBid'!$A:$A,0))="",LEFT(INDEX('Bid-NoBid'!$U:$U,MATCH(A102,'Bid-NoBid'!$A:$A,0)),10)="Incomplete"),"Screen: "&AC102,INDEX('Bid-NoBid'!$U:$U,MATCH(A102,'Bid-NoBid'!$A:$A,0))),"Screen: "&AC102)) | W102: Watching | X102: Frank | AB102: Azania Bank tenders (web page) | AC102: Check | AD102: Auto (Azania Bank tenders): Deadline not shown on the source page – open the link and read the notice | AE102: =IF(ISNUMBER(Q102),ROUNDDOWN(Q102-NOW(),1),"") | AF102: =IF(OR(A102="",AE102=""),"",IF(NOT(OR(W102="Watching",W102="Preparing")),"",IF(AE102<0,"PASSED",IF(AND(AE102<=7,W102<>"Preparing"),"RED",IF(AE102<=14,"AMBER","GREEN"))))) | AG102: =IF(OR(A102="",NOT(OR(W102="Watching",W102="Preparing"))),"",IF(AND(ISNUMBER(M102),M102>=3000000000),"YES – ≥ TZS 3bn",IF(AND(ISNUMBER(AE102),AE102>=0,AE102<10,V102=""),"YES – <10 days",""))) | AI102: Read the notice and decide with the QS Director whether to pursue | AJ102: Auto-scan | AK102: WEB:azania_bank_tenders:49ead9be51bae7b0 | AL102: =IF(AND(OR(W102="Watching",W102="Preparing"),ISNUMBER(Q102)),IF(AND(Q102>='Friday Summary'!$C$4,Q102<='Friday Summary'!$C$4+14),Q102+ROW()/1000000,""),"")
A103: =IF(B103="","","OP-"&TEXT(ROW()-4,"000")) | B103: (not shown) | C103: 46305 | D103: client site | E103: https://azaniabank.co.tz/wp-content/uploads/2022/05/PROVISION-OF-REFURBISHMENT-RENOVATION-REMODELING-OFFICE-PARTITIONING-AND-FIT-OUT-WORKS-OF-BANK-PREMISES-2022.-.pdf | F103: Azania Bank | G103: bank | H103: Pre-Qualification Document: Provision of Refurbishment, Renovation, Remodelling, Office Partitioning and Fit-Out Works of Bank Premises | I103: From client site notice (1 lot) – read the tender document | J103: Not stated – read the notice | K103: fit-out | L103: See tender document | N103: unknown | O103: See tender document | P103: See tender document | R103: See tender document | S103: N | T103: =IF(A103="","",IFERROR(INDEX('Bid-NoBid'!$T:$T,MATCH(A103,'Bid-NoBid'!$A:$A,0)),"")) | U103: =IF(A103="","",IFERROR(IF(OR(INDEX('Bid-NoBid'!$U:$U,MATCH(A103,'Bid-NoBid'!$A:$A,0))="",LEFT(INDEX('Bid-NoBid'!$U:$U,MATCH(A103,'Bid-NoBid'!$A:$A,0)),10)="Incomplete"),"Screen: "&AC103,INDEX('Bid-NoBid'!$U:$U,MATCH(A103,'Bid-NoBid'!$A:$A,0))),"Screen: "&AC103)) | W103: Watching | X103: Frank | AB103: Azania Bank tenders (web page) | AC103: Check | AD103: Auto (Azania Bank tenders): Deadline not shown on the source page – open the link and read the notice | AE103: =IF(ISNUMBER(Q103),ROUNDDOWN(Q103-NOW(),1),"") | AF103: =IF(OR(A103="",AE103=""),"",IF(NOT(OR(W103="Watching",W103="Preparing")),"",IF(AE103<0,"PASSED",IF(AND(AE103<=7,W103<>"Preparing"),"RED",IF(AE103<=14,"AMBER","GREEN"))))) | AG103: =IF(OR(A103="",NOT(OR(W103="Watching",W103="Preparing"))),"",IF(AND(ISNUMBER(M103),M103>=3000000000),"YES – ≥ TZS 3bn",IF(AND(ISNUMBER(AE103),AE103>=0,AE103<10,V103=""),"YES – <10 days",""))) | AI103: Read the notice and decide with the QS Director whether to pursue | AJ103: Auto-scan | AK103: WEB:azania_bank_tenders:6006675b441973b9 | AL103: =IF(AND(OR(W103="Watching",W103="Preparing"),ISNUMBER(Q103)),IF(AND(Q103>='Friday Summary'!$C$4,Q103<='Friday Summary'!$C$4+14),Q103+ROW()/1000000,""),"")
A104: =IF(B104="","","OP-"&TEXT(ROW()-4,"000")) | B104: (not shown) | C104: 46305 | D104: client site | E104: https://www.sua.ac.tz/zabuni | F104: Sokoine University of Agriculture (SUA) | G104: government | H104: TANGAZO LA ZABUNI:HUDUMA YA KUWAPATA MAFUNDI WA KUFANYA UKARABATI WA MAJENGO MBALIMBALI YA OFISI, NYUMBA ZA WANYAMA NA UTAFITI KAMPASI KUU YA SUA | I104: From client site notice (1 lot) – read the tender document | J104: Morogoro (from client's office – confirm site) | K104: renovation | L104: See tender document | N104: unknown | O104: See tender document | P104: See tender document | R104: See tender document | S104: N | T104: =IF(A104="","",IFERROR(INDEX('Bid-NoBid'!$T:$T,MATCH(A104,'Bid-NoBid'!$A:$A,0)),"")) | U104: =IF(A104="","",IFERROR(IF(OR(INDEX('Bid-NoBid'!$U:$U,MATCH(A104,'Bid-NoBid'!$A:$A,0))="",LEFT(INDEX('Bid-NoBid'!$U:$U,MATCH(A104,'Bid-NoBid'!$A:$A,0)),10)="Incomplete"),"Screen: "&AC104,INDEX('Bid-NoBid'!$U:$U,MATCH(A104,'Bid-NoBid'!$A:$A,0))),"Screen: "&AC104)) | W104: Watching | X104: Frank | AB104: SUA tenders (zabuni) (web page) | AC104: Check | AD104: Auto (SUA tenders): Deadline not shown on the source page – open the link and read the notice | AE104: =IF(ISNUMBER(Q104),ROUNDDOWN(Q104-NOW(),1),"") | AF104: =IF(OR(A104="",AE104=""),"",IF(NOT(OR(W104="Watching",W104="Preparing")),"",IF(AE104<0,"PASSED",IF(AND(AE104<=7,W104<>"Preparing"),"RED",IF(AE104<=14,"AMBER","GREEN"))))) | AG104: =IF(OR(A104="",NOT(OR(W104="Watching",W104="Preparing"))),"",IF(AND(ISNUMBER(M104),M104>=3000000000),"YES – ≥ TZS 3bn",IF(AND(ISNUMBER(AE104),AE104>=0,AE104<10,V104=""),"YES – <10 days",""))) | AI104: Read the notice and decide with the QS Director whether to pursue | AJ104: Auto-scan | AK104: WEB:sua_tenders_zabuni:089c72bd6abcbeb5 | AL104: =IF(AND(OR(W104="Watching",W104="Preparing"),ISNUMBER(Q104)),IF(AND(Q104>='Friday Summary'!$C$4,Q104<='Friday Summary'!$C$4+14),Q104+ROW()/1000000,""),"")
A105: =IF(B105="","","OP-"&TEXT(ROW()-4,"000")) | B105: PA/012/2019-2020/HQ/W/22 | C105: 46305 | D105: client site | E105: https://www.sua.ac.tz/zabuni | F105: Sokoine University of Agriculture (SUA) | G105: government | H105: 5.Kotesheni zote katika uhalisia wake ( original ) pamoja na nakala [ moja ] zinazofanana, zilizojazwa kwa usahihi na kuwekwa kwenye bahasha isiyo na maandishi juu na kuandikwa “Kotesheni Na. PA/012/2019-2020/HQ/W/22, Kundi Na….., ‘’HUDUMA YA KUWAPATA MAFUNDI WA KUFANYA UKARABATI WA MAJENGO MBALIMBA | I105: From client site notice (1 lot) – read the tender document | J105: Morogoro (from client's office – confirm site) | K105: renovation | L105: See tender document | N105: unknown | O105: See tender document | P105: See tender document | R105: See tender document | S105: N | T105: =IF(A105="","",IFERROR(INDEX('Bid-NoBid'!$T:$T,MATCH(A105,'Bid-NoBid'!$A:$A,0)),"")) | U105: =IF(A105="","",IFERROR(IF(OR(INDEX('Bid-NoBid'!$U:$U,MATCH(A105,'Bid-NoBid'!$A:$A,0))="",LEFT(INDEX('Bid-NoBid'!$U:$U,MATCH(A105,'Bid-NoBid'!$A:$A,0)),10)="Incomplete"),"Screen: "&AC105,INDEX('Bid-NoBid'!$U:$U,MATCH(A105,'Bid-NoBid'!$A:$A,0))),"Screen: "&AC105)) | W105: Watching | X105: Frank | AB105: SUA tenders (zabuni) (web page) | AC105: Check | AD105: Auto (SUA tenders): Deadline not shown on the source page – open the link and read the notice | AE105: =IF(ISNUMBER(Q105),ROUNDDOWN(Q105-NOW(),1),"") | AF105: =IF(OR(A105="",AE105=""),"",IF(NOT(OR(W105="Watching",W105="Preparing")),"",IF(AE105<0,"PASSED",IF(AND(AE105<=7,W105<>"Preparing"),"RED",IF(AE105<=14,"AMBER","GREEN"))))) | AG105: =IF(OR(A105="",NOT(OR(W105="Watching",W105="Preparing"))),"",IF(AND(ISNUMBER(M105),M105>=3000000000),"YES – ≥ TZS 3bn",IF(AND(ISNUMBER(AE105),AE105>=0,AE105<10,V105=""),"YES – <10 days",""))) | AI105: Read the notice and decide with the QS Director whether to pursue | AJ105: Auto-scan | AK105: WEB:sua_tenders_zabuni:pa01220192020hqw22 | AL105: =IF(AND(OR(W105="Watching",W105="Preparing"),ISNUMBER(Q105)),IF(AND(Q105>='Friday Summary'!$C$4,Q105<='Friday Summary'!$C$4+14),Q105+ROW()/1000000,""),"")
A106: =IF(B106="","","OP-"&TEXT(ROW()-4,"000")) | B106: (not shown) | C106: 46305 | D106: aggregator | E106: https://www.biddetail.com/tanzania-tenders/construction-tenders | F106: See notice | G106: government | H106: Construction Tenders | I106: From aggregator notice (1 lot) – read the tender document | J106: Not stated – read the notice | K106: building | L106: See tender document | N106: unknown | O106: See tender document | P106: See tender document | R106: See tender document | S106: N | T106: =IF(A106="","",IFERROR(INDEX('Bid-NoBid'!$T:$T,MATCH(A106,'Bid-NoBid'!$A:$A,0)),"")) | U106: =IF(A106="","",IFERROR(IF(OR(INDEX('Bid-NoBid'!$U:$U,MATCH(A106,'Bid-NoBid'!$A:$A,0))="",LEFT(INDEX('Bid-NoBid'!$U:$U,MATCH(A106,'Bid-NoBid'!$A:$A,0)),10)="Incomplete"),"Screen: "&AC106,INDEX('Bid-NoBid'!$U:$U,MATCH(A106,'Bid-NoBid'!$A:$A,0))),"Screen: "&AC106)) | W106: Watching | X106: Frank | AB106: BidDetail – Tanzania tenders (web page) | AC106: Check | AD106: Auto (BidDetail – Tanzania tenders): Deadline not shown on the source page – open the link and read the notice | AE106: =IF(ISNUMBER(Q106),ROUNDDOWN(Q106-NOW(),1),"") | AF106: =IF(OR(A106="",AE106=""),"",IF(NOT(OR(W106="Watching",W106="Preparing")),"",IF(AE106<0,"PASSED",IF(AND(AE106<=7,W106<>"Preparing"),"RED",IF(AE106<=14,"AMBER","GREEN"))))) | AG106: =IF(OR(A106="",NOT(OR(W106="Watching",W106="Preparing"))),"",IF(AND(ISNUMBER(M106),M106>=3000000000),"YES – ≥ TZS 3bn",IF(AND(ISNUMBER(AE106),AE106>=0,AE106<10,V106=""),"YES – <10 days",""))) | AI106: Read the notice and decide with the QS Director whether to pursue | AJ106: Auto-scan | AK106: WEB:biddetail_tanzania_tenders:5c649ceca911fe55 | AL106: =IF(AND(OR(W106="Watching",W106="Preparing"),ISNUMBER(Q106)),IF(AND(Q106>='Friday Summary'!$C$4,Q106<='Friday Summary'!$C$4+14),Q106+ROW()/1000000,""),"")
A107: =IF(B107="","","OP-"&TEXT(ROW()-4,"000")) | B107: (not shown) | C107: 46305 | D107: aggregator | E107: https://www.biddetail.com/latest-tenders/118925699$c13e5f5e-7a4b-4be7-a2f2-2558c7049441 | F107: See notice | G107: government | H107: Tenders Are Invited For Construction Of Perimeter Fence And Site ...... | I107: From aggregator notice (1 lot) – read the tender document | J107: Not stated – read the notice | K107: building | L107: See tender document | N107: unknown | O107: See tender document | P107: See tender document | R107: See tender document | S107: N | T107: =IF(A107="","",IFERROR(INDEX('Bid-NoBid'!$T:$T,MATCH(A107,'Bid-NoBid'!$A:$A,0)),"")) | U107: =IF(A107="","",IFERROR(IF(OR(INDEX('Bid-NoBid'!$U:$U,MATCH(A107,'Bid-NoBid'!$A:$A,0))="",LEFT(INDEX('Bid-NoBid'!$U:$U,MATCH(A107,'Bid-NoBid'!$A:$A,0)),10)="Incomplete"),"Screen: "&AC107,INDEX('Bid-NoBid'!$U:$U,MATCH(A107,'Bid-NoBid'!$A:$A,0))),"Screen: "&AC107)) | W107: Watching | X107: Frank | AB107: BidDetail – Tanzania tenders (web page) | AC107: Check | AD107: Auto (BidDetail – Tanzania tenders): Deadline not shown on the source page – open the link and read the notice | AE107: =IF(ISNUMBER(Q107),ROUNDDOWN(Q107-NOW(),1),"") | AF107: =IF(OR(A107="",AE107=""),"",IF(NOT(OR(W107="Watching",W107="Preparing")),"",IF(AE107<0,"PASSED",IF(AND(AE107<=7,W107<>"Preparing"),"RED",IF(AE107<=14,"AMBER","GREEN"))))) | AG107: =IF(OR(A107="",NOT(OR(W107="Watching",W107="Preparing"))),"",IF(AND(ISNUMBER(M107),M107>=3000000000),"YES – ≥ TZS 3bn",IF(AND(ISNUMBER(AE107),AE107>=0,AE107<10,V107=""),"YES – <10 days",""))) | AI107: Read the notice and decide with the QS Director whether to pursue | AJ107: Auto-scan | AK107: WEB:biddetail_tanzania_tenders:e57e334c02ac1ab7 | AL107: =IF(AND(OR(W107="Watching",W107="Preparing"),ISNUMBER(Q107)),IF(AND(Q107>='Friday Summary'!$C$4,Q107<='Friday Summary'!$C$4+14),Q107+ROW()/1000000,""),"")
A108: =IF(B108="","","OP-"&TEXT(ROW()-4,"000")) | B108: (not shown) | C108: 46305 | D108: aggregator | E108: https://www.biddetail.com/latest-tenders/119128722$8a01940b-aa90-4a08-9217-c0af8103e7de | F108: See notice | G108: government | H108: Tenders are invited for Construction Of Lwanji I Bridge (200M) Sp ...... | I108: From aggregator notice (1 lot) – read the tender document | J108: Not stated – read the notice | K108: civil | L108: See tender document | N108: unknown | O108: See tender document | P108: See tender document | R108: See tender document | S108: N | T108: =IF(A108="","",IFERROR(INDEX('Bid-NoBid'!$T:$T,MATCH(A108,'Bid-NoBid'!$A:$A,0)),"")) | U108: =IF(A108="","",IFERROR(IF(OR(INDEX('Bid-NoBid'!$U:$U,MATCH(A108,'Bid-NoBid'!$A:$A,0))="",LEFT(INDEX('Bid-NoBid'!$U:$U,MATCH(A108,'Bid-NoBid'!$A:$A,0)),10)="Incomplete"),"Screen: "&AC108,INDEX('Bid-NoBid'!$U:$U,MATCH(A108,'Bid-NoBid'!$A:$A,0))),"Screen: "&AC108)) | W108: Watching | X108: Frank | AB108: BidDetail – Tanzania tenders (web page) | AC108: Check | AD108: Auto (BidDetail – Tanzania tenders): Deadline not shown on the source page – open the link and read the notice | AE108: =IF(ISNUMBER(Q108),ROUNDDOWN(Q108-NOW(),1),"") | AF108: =IF(OR(A108="",AE108=""),"",IF(NOT(OR(W108="Watching",W108="Preparing")),"",IF(AE108<0,"PASSED",IF(AND(AE108<=7,W108<>"Preparing"),"RED",IF(AE108<=14,"AMBER","GREEN"))))) | AG108: =IF(OR(A108="",NOT(OR(W108="Watching",W108="Preparing"))),"",IF(AND(ISNUMBER(M108),M108>=3000000000),"YES – ≥ TZS 3bn",IF(AND(ISNUMBER(AE108),AE108>=0,AE108<10,V108=""),"YES – <10 days",""))) | AI108: Read the notice and decide with the QS Director whether to pursue | AJ108: Auto-scan | AK108: WEB:biddetail_tanzania_tenders:6747e3d0e5f9315b | AL108: =IF(AND(OR(W108="Watching",W108="Preparing"),ISNUMBER(Q108)),IF(AND(Q108>='Friday Summary'!$C$4,Q108<='Friday Summary'!$C$4+14),Q108+ROW()/1000000,""),"")
A109: =IF(B109="","","OP-"&TEXT(ROW()-4,"000")) | B109: TR36/002/2026/2027/W/35 | C109: 46305 | D109: NeST | E109: https://nest.go.tz/tenders/published-tenders | F109: TANROADS - Dar es Salaam Regional Office | G109: government | H109: Maintenance of Traffic signals and street lights along trunk and regional roads - Lot 6C: Mandela road, Ubungo Bus Terminal-Kigogo (Shungashunga jct), Ubungo External-Korogwe, Mjimwema Jct, Tabata Barakuda jct | I109: From NeST notice (1 lot) – read the tender document | J109: Dar es Salaam (Ubungo) | K109: civil | L109: NeST login needed | N109: unknown | O109: NeST login needed | P109: NeST login needed | Q109: 46311.583 | R109: NeST login needed | S109: N | T109: =IF(A109="","",IFERROR(INDEX('Bid-NoBid'!$T:$T,MATCH(A109,'Bid-NoBid'!$A:$A,0)),"")) | U109: =IF(A109="","",IFERROR(IF(OR(INDEX('Bid-NoBid'!$U:$U,MATCH(A109,'Bid-NoBid'!$A:$A,0))="",LEFT(INDEX('Bid-NoBid'!$U:$U,MATCH(A109,'Bid-NoBid'!$A:$A,0)),10)="Incomplete"),"Screen: "&AC109,INDEX('Bid-NoBid'!$U:$U,MATCH(A109,'Bid-NoBid'!$A:$A,0))),"Screen: "&AC109)) | W109: Watching | X109: Frank | AA109: 46304 | AB109: Small Works / Tender | AC109: Check | AD109: Auto (Small Works / Tender): Civil works in Dar/Coast – confirm CRB class and margin | AE109: =IF(ISNUMBER(Q109),ROUNDDOWN(Q109-NOW(),1),"") | AF109: =IF(OR(A109="",AE109=""),"",IF(NOT(OR(W109="Watching",W109="Preparing")),"",IF(AE109<0,"PASSED",IF(AND(AE109<=7,W109<>"Preparing"),"RED",IF(AE109<=14,"AMBER","GREEN"))))) | AG109: =IF(OR(A109="",NOT(OR(W109="Watching",W109="Preparing"))),"",IF(AND(ISNUMBER(M109),M109>=3000000000),"YES – ≥ TZS 3bn",IF(AND(ISNUMBER(AE109),AE109>=0,AE109<10,V109=""),"YES – <10 days",""))) | AI109: Read the notice and decide with the QS Director whether to pursue | AJ109: Auto-scan | AK109: 53f1e6ac-4eae-4da9-ae17-d59c416a01d7 | AL109: =IF(AND(OR(W109="Watching",W109="Preparing"),ISNUMBER(Q109)),IF(AND(Q109>='Friday Summary'!$C$4,Q109<='Friday Summary'!$C$4+14),Q109+ROW()/1000000,""),"")
A110: =IF(B110="","","OP-"&TEXT(ROW()-4,"000")) | B110: TR36/002/2026/2027/W/20 | C110: 46305 | D110: NeST | E110: https://nest.go.tz/tenders/published-tenders | F110: TANROADS - Dar es Salaam Regional Office | G110: government | H110: Road marking and signage along paved regional roads - Lot 4b: Mbezi Malamba Mawili-Kinyerezi, Morocco-Mlalakuwa, Fire Station-Selander,Bunju A-Bunju, Goba-Wazohill-Tegeta Kibaoni, Ununio-Mbweni-Bunju,Kawe-Lugalo, Mlimani City-Goba, Drive Inn-Namanga, Kunduchi-Mbuyuni-Boko, Kimara-Korogwe-External, Mbezi Mwisho-Goba-Samaki Wabichi | I110: From NeST notice (1 lot) – read the tender document | J110: Dar es Salaam (Mbezi) | K110: civil | L110: NeST login needed | N110: unknown | O110: NeST login needed | P110: NeST login needed | Q110: 46311.583 | R110: NeST login needed | S110: N | T110: =IF(A110="","",IFERROR(INDEX('Bid-NoBid'!$T:$T,MATCH(A110,'Bid-NoBid'!$A:$A,0)),"")) | U110: =IF(A110="","",IFERROR(IF(OR(INDEX('Bid-NoBid'!$U:$U,MATCH(A110,'Bid-NoBid'!$A:$A,0))="",LEFT(INDEX('Bid-NoBid'!$U:$U,MATCH(A110,'Bid-NoBid'!$A:$A,0)),10)="Incomplete"),"Screen: "&AC110,INDEX('Bid-NoBid'!$U:$U,MATCH(A110,'Bid-NoBid'!$A:$A,0))),"Screen: "&AC110)) | W110: Watching | X110: Frank | AA110: 46304 | AB110: Small Works / Tender | AC110: Check | AD110: Auto (Small Works / Tender): Civil works in Dar/Coast – confirm CRB class and margin | AE110: =IF(ISNUMBER(Q110),ROUNDDOWN(Q110-NOW(),1),"") | AF110: =IF(OR(A110="",AE110=""),"",IF(NOT(OR(W110="Watching",W110="Preparing")),"",IF(AE110<0,"PASSED",IF(AND(AE110<=7,W110<>"Preparing"),"RED",IF(AE110<=14,"AMBER","GREEN"))))) | AG110: =IF(OR(A110="",NOT(OR(W110="Watching",W110="Preparing"))),"",IF(AND(ISNUMBER(M110),M110>=3000000000),"YES – ≥ TZS 3bn",IF(AND(ISNUMBER(AE110),AE110>=0,AE110<10,V110=""),"YES – <10 days",""))) | AI110: Read the notice and decide with the QS Director whether to pursue | AJ110: Auto-scan | AK110: 3655ca4d-0eee-45f8-a362-d775e03135fb | AL110: =IF(AND(OR(W110="Watching",W110="Preparing"),ISNUMBER(Q110)),IF(AND(Q110>='Friday Summary'!$C$4,Q110<='Friday Summary'!$C$4+14),Q110+ROW()/1000000,""),"")
A111: =IF(B111="","","OP-"&TEXT(ROW()-4,"000")) | B111: TR36/002/2026/2027/W/43 | C111: 46305 | D111: NeST | E111: https://nest.go.tz/tenders/published-tenders | F111: TANROADS - Dar es Salaam Regional Office | G111: government | H111: Routine and Recurrent, Spot Improvement of Unpaved Regional roads - Lot 6B: Mbezi Victoria- Bunju Sport Motel (24.67km), Ununio - Mpiji Bridge road (6.18km) | I111: From NeST notice (1 lot) – read the tender document | J111: Dar es Salaam (Mbezi) | K111: civil | L111: NeST login needed | N111: unknown | O111: NeST login needed | P111: NeST login needed | Q111: 46311.583 | R111: NeST login needed | S111: N | T111: =IF(A111="","",IFERROR(INDEX('Bid-NoBid'!$T:$T,MATCH(A111,'Bid-NoBid'!$A:$A,0)),"")) | U111: =IF(A111="","",IFERROR(IF(OR(INDEX('Bid-NoBid'!$U:$U,MATCH(A111,'Bid-NoBid'!$A:$A,0))="",LEFT(INDEX('Bid-NoBid'!$U:$U,MATCH(A111,'Bid-NoBid'!$A:$A,0)),10)="Incomplete"),"Screen: "&AC111,INDEX('Bid-NoBid'!$U:$U,MATCH(A111,'Bid-NoBid'!$A:$A,0))),"Screen: "&AC111)) | W111: Watching | X111: Frank | AA111: 46304 | AB111: Small Works / Tender | AC111: Check | AD111: Auto (Small Works / Tender): Civil works in Dar/Coast – confirm CRB class and margin | AE111: =IF(ISNUMBER(Q111),ROUNDDOWN(Q111-NOW(),1),"") | AF111: =IF(OR(A111="",AE111=""),"",IF(NOT(OR(W111="Watching",W111="Preparing")),"",IF(AE111<0,"PASSED",IF(AND(AE111<=7,W111<>"Preparing"),"RED",IF(AE111<=14,"AMBER","GREEN"))))) | AG111: =IF(OR(A111="",NOT(OR(W111="Watching",W111="Preparing"))),"",IF(AND(ISNUMBER(M111),M111>=3000000000),"YES – ≥ TZS 3bn",IF(AND(ISNUMBER(AE111),AE111>=0,AE111<10,V111=""),"YES – <10 days",""))) | AI111: Read the notice and decide with the QS Director whether to pursue | AJ111: Auto-scan | AK111: 32cf441a-46ee-4483-b3a7-1cff183a4772 | AL111: =IF(AND(OR(W111="Watching",W111="Preparing"),ISNUMBER(Q111)),IF(AND(Q111>='Friday Summary'!$C$4,Q111<='Friday Summary'!$C$4+14),Q111+ROW()/1000000,""),"")
A112: =IF(B112="","","OP-"&TEXT(ROW()-4,"000")) | B112: TR36/002/2026/2027/W/21 | C112: 46305 | D112: NeST | E112: https://nest.go.tz/tenders/published-tenders | F112: TANROADS - Dar es Salaam Regional Office | G112: government | H112: Routine and Recurrent Maintenance of paved regional roads - Lot 12: Temboni-Goba-Wazo Hill- Tegeta Kibaoni (15.7km), Kawe - Lugalo, Tanki bovu-Rainbow, Mbezi Mwisho-Goba - Samaki Wabichi, Kawe - TPDF Range (2.88km). | I112: From NeST notice (1 lot) – read the tender document | J112: Dar es Salaam (Goba) | K112: civil | L112: NeST login needed | N112: unknown | O112: NeST login needed | P112: NeST login needed | Q112: 46311.583 | R112: NeST login needed | S112: N | T112: =IF(A112="","",IFERROR(INDEX('Bid-NoBid'!$T:$T,MATCH(A112,'Bid-NoBid'!$A:$A,0)),"")) | U112: =IF(A112="","",IFERROR(IF(OR(INDEX('Bid-NoBid'!$U:$U,MATCH(A112,'Bid-NoBid'!$A:$A,0))="",LEFT(INDEX('Bid-NoBid'!$U:$U,MATCH(A112,'Bid-NoBid'!$A:$A,0)),10)="Incomplete"),"Screen: "&AC112,INDEX('Bid-NoBid'!$U:$U,MATCH(A112,'Bid-NoBid'!$A:$A,0))),"Screen: "&AC112)) | W112: Watching | X112: Frank | AA112: 46304 | AB112: Small Works / Tender | AC112: Check | AD112: Auto (Small Works / Tender): Civil works in Dar/Coast – confirm CRB class and margin | AE112: =IF(ISNUMBER(Q112),ROUNDDOWN(Q112-NOW(),1),"") | AF112: =IF(OR(A112="",AE112=""),"",IF(NOT(OR(W112="Watching",W112="Preparing")),"",IF(AE112<0,"PASSED",IF(AND(AE112<=7,W112<>"Preparing"),"RED",IF(AE112<=14,"AMBER","GREEN"))))) | AG112: =IF(OR(A112="",NOT(OR(W112="Watching",W112="Preparing"))),"",IF(AND(ISNUMBER(M112),M112>=3000000000),"YES – ≥ TZS 3bn",IF(AND(ISNUMBER(AE112),AE112>=0,AE112<10,V112=""),"YES – <10 days",""))) | AI112: Read the notice and decide with the QS Director whether to pursue | AJ112: Auto-scan | AK112: 8c0debb4-a114-4e55-bd3c-1b91c3a09452 | AL112: =IF(AND(OR(W112="Watching",W112="Preparing"),ISNUMBER(Q112)),IF(AND(Q112>='Friday Summary'!$C$4,Q112<='Friday Summary'!$C$4+14),Q112+ROW()/1000000,""),"")
A113: =IF(B113="","","OP-"&TEXT(ROW()-4,"000")) | B113: TR152/006/2026/2027/W/04 | C113: 46305 | D113: NeST | E113: https://nest.go.tz/tenders/published-tenders | F113: Bank of Tanzania - Mwanza Branch | G113: government | H113: Proposed Rehabilitation of Stone Cladding, Mosaic Tiles, and Repainting of the Boundary Wall at the Bank of Tanzania Office Premises, Plot No. 50, Chief Makongoro Avenue, Mwanza | I113: From NeST notice (1 lot) – read the tender document | J113: Mwanza | K113: renovation | L113: NeST login needed | N113: unknown | O113: NeST login needed | P113: NeST login needed | Q113: 46314.583 | R113: NeST login needed | S113: N | T113: =IF(A113="","",IFERROR(INDEX('Bid-NoBid'!$T:$T,MATCH(A113,'Bid-NoBid'!$A:$A,0)),"")) | U113: =IF(A113="","",IFERROR(IF(OR(INDEX('Bid-NoBid'!$U:$U,MATCH(A113,'Bid-NoBid'!$A:$A,0))="",LEFT(INDEX('Bid-NoBid'!$U:$U,MATCH(A113,'Bid-NoBid'!$A:$A,0)),10)="Incomplete"),"Screen: "&AC113,INDEX('Bid-NoBid'!$U:$U,MATCH(A113,'Bid-NoBid'!$A:$A,0))),"Screen: "&AC113)) | W113: Watching | X113: Frank | AA113: 46304 | AB113: Small Works / Tender | AC113: Check | AD113: Auto (Small Works / Tender): Building works but remote from Dar | AE113: =IF(ISNUMBER(Q113),ROUNDDOWN(Q113-NOW(),1),"") | AF113: =IF(OR(A113="",AE113=""),"",IF(NOT(OR(W113="Watching",W113="Preparing")),"",IF(AE113<0,"PASSED",IF(AND(AE113<=7,W113<>"Preparing"),"RED",IF(AE113<=14,"AMBER","GREEN"))))) | AG113: =IF(OR(A113="",NOT(OR(W113="Watching",W113="Preparing"))),"",IF(AND(ISNUMBER(M113),M113>=3000000000),"YES – ≥ TZS 3bn",IF(AND(ISNUMBER(AE113),AE113>=0,AE113<10,V113=""),"YES – <10 days",""))) | AI113: Read the notice and decide with the QS Director whether to pursue | AJ113: Auto-scan | AK113: 5a9f0d6a-563b-42b1-aa4e-e5ac7ccadc19 | AL113: =IF(AND(OR(W113="Watching",W113="Preparing"),ISNUMBER(Q113)),IF(AND(Q113>='Friday Summary'!$C$4,Q113<='Friday Summary'!$C$4+14),Q113+ROW()/1000000,""),"")
A114: =IF(B114="","","OP-"&TEXT(ROW()-4,"000")) | B114: (not shown) | C114: 46305 | D114: donor / international | E114: https://www.find-tender.service.gov.uk/Notice/095873-2026?origin=SearchResults&p=1 | F114: UK Government (FCDO / British High Commission) | G114: donor | H114: Malaysia Penang Centre Regear and Refit British Council The British Council currently occupies Wisma Great Eastern, Penang - No. 25, Lebuh Light, 10200 Level 3A, Suite 3A.1. The British Council is required to fitout the premises to reconfigure the office to add exam function. Notice type UK4: Tender | I114: From donor / international notice (1 lot) – read the tender document | J114: Not stated – read the notice | K114: fit-out | L114: See tender document | N114: unknown | O114: See tender document | P114: See tender document | Q114: 46318.688 | R114: See tender document | S114: N | T114: =IF(A114="","",IFERROR(INDEX('Bid-NoBid'!$T:$T,MATCH(A114,'Bid-NoBid'!$A:$A,0)),"")) | U114: =IF(A114="","",IFERROR(IF(OR(INDEX('Bid-NoBid'!$U:$U,MATCH(A114,'Bid-NoBid'!$A:$A,0))="",LEFT(INDEX('Bid-NoBid'!$U:$U,MATCH(A114,'Bid-NoBid'!$A:$A,0)),10)="Incomplete"),"Screen: "&AC114,INDEX('Bid-NoBid'!$U:$U,MATCH(A114,'Bid-NoBid'!$A:$A,0))),"Screen: "&AC114)) | W114: Watching | X114: Frank | AB114: UK Find a Tender – Tanzania (web page) | AC114: Check | AD114: Auto (UK Find a Tender – Tanzania): Site not stated in the listing – read the notice · deadline read from the web page – confirm | AE114: =IF(ISNUMBER(Q114),ROUNDDOWN(Q114-NOW(),1),"") | AF114: =IF(OR(A114="",AE114=""),"",IF(NOT(OR(W114="Watching",W114="Preparing")),"",IF(AE114<0,"PASSED",IF(AND(AE114<=7,W114<>"Preparing"),"RED",IF(AE114<=14,"AMBER","GREEN"))))) | AG114: =IF(OR(A114="",NOT(OR(W114="Watching",W114="Preparing"))),"",IF(AND(ISNUMBER(M114),M114>=3000000000),"YES – ≥ TZS 3bn",IF(AND(ISNUMBER(AE114),AE114>=0,AE114<10,V114=""),"YES – <10 days",""))) | AI114: Read the notice and decide with the QS Director whether to pursue | AJ114: Auto-scan | AK114: WEB:uk_find_a_tender_tanzania:152d508ec3c6cea1 | AL114: =IF(AND(OR(W114="Watching",W114="Preparing"),ISNUMBER(Q114)),IF(AND(Q114>='Friday Summary'!$C$4,Q114<='Friday Summary'!$C$4+14),Q114+ROW()/1000000,""),"")
A115: =IF(B115="","","OP-"&TEXT(ROW()-4,"000")) | B115: (not shown) | C115: 46305 | D115: donor / international | E115: https://www.find-tender.service.gov.uk/Search/Results?keywords=Tanzania | F115: UK Government (FCDO / British High Commission) | G115: donor | H115: Utilities dynamic market - A dynamic market that can only be used by utility organisations to award utilities contracts. Tender notices may optionally be provided only to members of the market. (Not included in the DM/DPS filter option.) | I115: From donor / international notice (1 lot) – read the tender document | J115: Not stated – read the notice | K115: building | L115: See tender document | N115: unknown | O115: See tender document | P115: See tender document | R115: See tender document | S115: N | T115: =IF(A115="","",IFERROR(INDEX('Bid-NoBid'!$T:$T,MATCH(A115,'Bid-NoBid'!$A:$A,0)),"")) | U115: =IF(A115="","",IFERROR(IF(OR(INDEX('Bid-NoBid'!$U:$U,MATCH(A115,'Bid-NoBid'!$A:$A,0))="",LEFT(INDEX('Bid-NoBid'!$U:$U,MATCH(A115,'Bid-NoBid'!$A:$A,0)),10)="Incomplete"),"Screen: "&AC115,INDEX('Bid-NoBid'!$U:$U,MATCH(A115,'Bid-NoBid'!$A:$A,0))),"Screen: "&AC115)) | W115: Watching | X115: Frank | AB115: UK Find a Tender – Tanzania (web page) | AC115: Check | AD115: Auto (UK Find a Tender – Tanzania): Deadline not shown on the source page – open the link and read the notice | AE115: =IF(ISNUMBER(Q115),ROUNDDOWN(Q115-NOW(),1),"") | AF115: =IF(OR(A115="",AE115=""),"",IF(NOT(OR(W115="Watching",W115="Preparing")),"",IF(AE115<0,"PASSED",IF(AND(AE115<=7,W115<>"Preparing"),"RED",IF(AE115<=14,"AMBER","GREEN"))))) | AG115: =IF(OR(A115="",NOT(OR(W115="Watching",W115="Preparing"))),"",IF(AND(ISNUMBER(M115),M115>=3000000000),"YES – ≥ TZS 3bn",IF(AND(ISNUMBER(AE115),AE115>=0,AE115<10,V115=""),"YES – <10 days",""))) | AI115: Read the notice and decide with the QS Director whether to pursue | AJ115: Auto-scan | AK115: WEB:uk_find_a_tender_tanzania:51cdf20411b36bee | AL115: =IF(AND(OR(W115="Watching",W115="Preparing"),ISNUMBER(Q115)),IF(AND(Q115>='Friday Summary'!$C$4,Q115<='Friday Summary'!$C$4+14),Q115+ROW()/1000000,""),"")
A116: =IF(B116="","","OP-"&TEXT(ROW()-4,"000")) | B116: (not shown) | C116: 46305 | D116: donor / international | E116: https://www.find-tender.service.gov.uk/Search/Results?keywords=Tanzania | F116: UK Government (FCDO / British High Commission) | G116: donor | H116: Dynamic market - Arrangements that suppliers who meet the conditions for membership can join, which allow them to bid for future contracts restricted to members of the market. Future contracts must be advertised in tender notices. New suppliers can join at any time during the term of the market. | I116: From donor / international notice (1 lot) – read the tender document | J116: Not stated – read the notice | K116: building | L116: See tender document | N116: unknown | O116: See tender document | P116: See tender document | R116: See tender document | S116: N | T116: =IF(A116="","",IFERROR(INDEX('Bid-NoBid'!$T:$T,MATCH(A116,'Bid-NoBid'!$A:$A,0)),"")) | U116: =IF(A116="","",IFERROR(IF(OR(INDEX('Bid-NoBid'!$U:$U,MATCH(A116,'Bid-NoBid'!$A:$A,0))="",LEFT(INDEX('Bid-NoBid'!$U:$U,MATCH(A116,'Bid-NoBid'!$A:$A,0)),10)="Incomplete"),"Screen: "&AC116,INDEX('Bid-NoBid'!$U:$U,MATCH(A116,'Bid-NoBid'!$A:$A,0))),"Screen: "&AC116)) | W116: Watching | X116: Frank | AB116: UK Find a Tender – Tanzania (web page) | AC116: Check | AD116: Auto (UK Find a Tender – Tanzania): Deadline not shown on the source page – open the link and read the notice | AE116: =IF(ISNUMBER(Q116),ROUNDDOWN(Q116-NOW(),1),"") | AF116: =IF(OR(A116="",AE116=""),"",IF(NOT(OR(W116="Watching",W116="Preparing")),"",IF(AE116<0,"PASSED",IF(AND(AE116<=7,W116<>"Preparing"),"RED",IF(AE116<=14,"AMBER","GREEN"))))) | AG116: =IF(OR(A116="",NOT(OR(W116="Watching",W116="Preparing"))),"",IF(AND(ISNUMBER(M116),M116>=3000000000),"YES – ≥ TZS 3bn",IF(AND(ISNUMBER(AE116),AE116>=0,AE116<10,V116=""),"YES – <10 days",""))) | AI116: Read the notice and decide with the QS Director whether to pursue | AJ116: Auto-scan | AK116: WEB:uk_find_a_tender_tanzania:d7df2948c5ca33aa | AL116: =IF(AND(OR(W116="Watching",W116="Preparing"),ISNUMBER(Q116)),IF(AND(Q116>='Friday Summary'!$C$4,Q116<='Friday Summary'!$C$4+14),Q116+ROW()/1000000,""),"")
A117: =IF(B117="","","OP-"&TEXT(ROW()-4,"000")) | B117: (not shown) | C117: 46305 | D117: donor / international | E117: https://www.find-tender.service.gov.uk/Search/Results?keywords=Tanzania | F117: UK Government (FCDO / British High Commission) | G117: donor | H117: Dynamic purchasing system - Similar to a dynamic market, but only allowed for commonly used purchases. Tender notices are not required for future contracts. New suppliers can join at any time during the term of the market. Established under the Public Contracts Regulations 2015 or Utilities Contract | I117: From donor / international notice (1 lot) – read the tender document | J117: Not stated – read the notice | K117: building | L117: See tender document | N117: unknown | O117: See tender document | P117: See tender document | R117: See tender document | S117: N | T117: =IF(A117="","",IFERROR(INDEX('Bid-NoBid'!$T:$T,MATCH(A117,'Bid-NoBid'!$A:$A,0)),"")) | U117: =IF(A117="","",IFERROR(IF(OR(INDEX('Bid-NoBid'!$U:$U,MATCH(A117,'Bid-NoBid'!$A:$A,0))="",LEFT(INDEX('Bid-NoBid'!$U:$U,MATCH(A117,'Bid-NoBid'!$A:$A,0)),10)="Incomplete"),"Screen: "&AC117,INDEX('Bid-NoBid'!$U:$U,MATCH(A117,'Bid-NoBid'!$A:$A,0))),"Screen: "&AC117)) | W117: Watching | X117: Frank | AB117: UK Find a Tender – Tanzania (web page) | AC117: Check | AD117: Auto (UK Find a Tender – Tanzania): Deadline not shown on the source page – open the link and read the notice | AE117: =IF(ISNUMBER(Q117),ROUNDDOWN(Q117-NOW(),1),"") | AF117: =IF(OR(A117="",AE117=""),"",IF(NOT(OR(W117="Watching",W117="Preparing")),"",IF(AE117<0,"PASSED",IF(AND(AE117<=7,W117<>"Preparing"),"RED",IF(AE117<=14,"AMBER","GREEN"))))) | AG117: =IF(OR(A117="",NOT(OR(W117="Watching",W117="Preparing"))),"",IF(AND(ISNUMBER(M117),M117>=3000000000),"YES – ≥ TZS 3bn",IF(AND(ISNUMBER(AE117),AE117>=0,AE117<10,V117=""),"YES – <10 days",""))) | AI117: Read the notice and decide with the QS Director whether to pursue | AJ117: Auto-scan | AK117: WEB:uk_find_a_tender_tanzania:3988ff1eb778713a | AL117: =IF(AND(OR(W117="Watching",W117="Preparing"),ISNUMBER(Q117)),IF(AND(Q117>='Friday Summary'!$C$4,Q117<='Friday Summary'!$C$4+14),Q117+ROW()/1000000,""),"")
A118: =IF(B118="","","OP-"&TEXT(ROW()-4,"000")) | B118: (not shown) | C118: 46305 | D118: donor / international | E118: https://www.find-tender.service.gov.uk/Search/Results?keywords=Tanzania | F118: UK Government (FCDO / British High Commission) | G118: donor | H118: Select all Deselect all UK1: Pipeline notice UK2: Preliminary market engagement notice UK3: Planned procurement notice UK4: Tender notice UK5: Transparency notice UK6: Contract award notice UK7: Contract details notice UK9: Contract performance notice UK10: Contract change notice UK11: Contract term | I118: From donor / international notice (1 lot) – read the tender document | J118: Not stated – read the notice | K118: civil | L118: See tender document | N118: unknown | O118: See tender document | P118: See tender document | R118: See tender document | S118: N | T118: =IF(A118="","",IFERROR(INDEX('Bid-NoBid'!$T:$T,MATCH(A118,'Bid-NoBid'!$A:$A,0)),"")) | U118: =IF(A118="","",IFERROR(IF(OR(INDEX('Bid-NoBid'!$U:$U,MATCH(A118,'Bid-NoBid'!$A:$A,0))="",LEFT(INDEX('Bid-NoBid'!$U:$U,MATCH(A118,'Bid-NoBid'!$A:$A,0)),10)="Incomplete"),"Screen: "&AC118,INDEX('Bid-NoBid'!$U:$U,MATCH(A118,'Bid-NoBid'!$A:$A,0))),"Screen: "&AC118)) | W118: Watching | X118: Frank | AB118: UK Find a Tender – Tanzania (web page) | AC118: Check | AD118: Auto (UK Find a Tender – Tanzania): Deadline not shown on the source page – open the link and read the notice | AE118: =IF(ISNUMBER(Q118),ROUNDDOWN(Q118-NOW(),1),"") | AF118: =IF(OR(A118="",AE118=""),"",IF(NOT(OR(W118="Watching",W118="Preparing")),"",IF(AE118<0,"PASSED",IF(AND(AE118<=7,W118<>"Preparing"),"RED",IF(AE118<=14,"AMBER","GREEN"))))) | AG118: =IF(OR(A118="",NOT(OR(W118="Watching",W118="Preparing"))),"",IF(AND(ISNUMBER(M118),M118>=3000000000),"YES – ≥ TZS 3bn",IF(AND(ISNUMBER(AE118),AE118>=0,AE118<10,V118=""),"YES – <10 days",""))) | AI118: Read the notice and decide with the QS Director whether to pursue | AJ118: Auto-scan | AK118: WEB:uk_find_a_tender_tanzania:4530a50e6ff49889 | AL118: =IF(AND(OR(W118="Watching",W118="Preparing"),ISNUMBER(Q118)),IF(AND(Q118>='Friday Summary'!$C$4,Q118<='Friday Summary'!$C$4+14),Q118+ROW()/1000000,""),"")
A119: =IF(B119="","","OP-"&TEXT(ROW()-4,"000")) | B119: (not shown) | C119: 46305 | D119: donor / international | E119: https://www.find-tender.service.gov.uk/Search/Results?keywords=Tanzania | F119: UK Government (FCDO / British High Commission) | G119: donor | H119: Procurement Act 2023 Select all Deselect all UK1: Pipeline notice UK2: Preliminary market engagement notice UK3: Planned procurement notice UK4: Tender notice UK5: Transparency notice UK6: Contract award notice UK7: Contract details notice UK9: Contract performance notice UK10: Contract change notic | I119: From donor / international notice (1 lot) – read the tender document | J119: Not stated – read the notice | K119: civil | L119: See tender document | N119: unknown | O119: See tender document | P119: See tender document | R119: See tender document | S119: N | T119: =IF(A119="","",IFERROR(INDEX('Bid-NoBid'!$T:$T,MATCH(A119,'Bid-NoBid'!$A:$A,0)),"")) | U119: =IF(A119="","",IFERROR(IF(OR(INDEX('Bid-NoBid'!$U:$U,MATCH(A119,'Bid-NoBid'!$A:$A,0))="",LEFT(INDEX('Bid-NoBid'!$U:$U,MATCH(A119,'Bid-NoBid'!$A:$A,0)),10)="Incomplete"),"Screen: "&AC119,INDEX('Bid-NoBid'!$U:$U,MATCH(A119,'Bid-NoBid'!$A:$A,0))),"Screen: "&AC119)) | W119: Watching | X119: Frank | AB119: UK Find a Tender – Tanzania (web page) | AC119: Check | AD119: Auto (UK Find a Tender – Tanzania): Deadline not shown on the source page – open the link and read the notice | AE119: =IF(ISNUMBER(Q119),ROUNDDOWN(Q119-NOW(),1),"") | AF119: =IF(OR(A119="",AE119=""),"",IF(NOT(OR(W119="Watching",W119="Preparing")),"",IF(AE119<0,"PASSED",IF(AND(AE119<=7,W119<>"Preparing"),"RED",IF(AE119<=14,"AMBER","GREEN"))))) | AG119: =IF(OR(A119="",NOT(OR(W119="Watching",W119="Preparing"))),"",IF(AND(ISNUMBER(M119),M119>=3000000000),"YES – ≥ TZS 3bn",IF(AND(ISNUMBER(AE119),AE119>=0,AE119<10,V119=""),"YES – <10 days",""))) | AI119: Read the notice and decide with the QS Director whether to pursue | AJ119: Auto-scan | AK119: WEB:uk_find_a_tender_tanzania:e0dc09032992961b | AL119: =IF(AND(OR(W119="Watching",W119="Preparing"),ISNUMBER(Q119)),IF(AND(Q119>='Friday Summary'!$C$4,Q119<='Friday Summary'!$C$4+14),Q119+ROW()/1000000,""),"")
A120: =IF(B120="","","OP-"&TEXT(ROW()-4,"000")) | B120: (not shown) | C120: 46305 | D120: donor / international | E120: https://www.find-tender.service.gov.uk/Search/Results?keywords=Tanzania | F120: UK Government (FCDO / British High Commission) | G120: donor | H120: Open opportunities - Planning or Tender stage notices with deadlines in the future Pipeline - Potential future contracts and dynamic markets - required for contracts over £2 million Planning - Early information or engagement about future contracts - bids not yet possible Tender - Bids can be submitt | I120: From donor / international notice (1 lot) – read the tender document | J120: Not stated – read the notice | K120: civil | L120: See tender document | N120: unknown | O120: See tender document | P120: See tender document | R120: See tender document | S120: N | T120: =IF(A120="","",IFERROR(INDEX('Bid-NoBid'!$T:$T,MATCH(A120,'Bid-NoBid'!$A:$A,0)),"")) | U120: =IF(A120="","",IFERROR(IF(OR(INDEX('Bid-NoBid'!$U:$U,MATCH(A120,'Bid-NoBid'!$A:$A,0))="",LEFT(INDEX('Bid-NoBid'!$U:$U,MATCH(A120,'Bid-NoBid'!$A:$A,0)),10)="Incomplete"),"Screen: "&AC120,INDEX('Bid-NoBid'!$U:$U,MATCH(A120,'Bid-NoBid'!$A:$A,0))),"Screen: "&AC120)) | W120: Watching | X120: Frank | AB120: UK Find a Tender – Tanzania (web page) | AC120: Check | AD120: Auto (UK Find a Tender – Tanzania): Deadline not shown on the source page – open the link and read the notice | AE120: =IF(ISNUMBER(Q120),ROUNDDOWN(Q120-NOW(),1),"") | AF120: =IF(OR(A120="",AE120=""),"",IF(NOT(OR(W120="Watching",W120="Preparing")),"",IF(AE120<0,"PASSED",IF(AND(AE120<=7,W120<>"Preparing"),"RED",IF(AE120<=14,"AMBER","GREEN"))))) | AG120: =IF(OR(A120="",NOT(OR(W120="Watching",W120="Preparing"))),"",IF(AND(ISNUMBER(M120),M120>=3000000000),"YES – ≥ TZS 3bn",IF(AND(ISNUMBER(AE120),AE120>=0,AE120<10,V120=""),"YES – <10 days",""))) | AI120: Read the notice and decide with the QS Director whether to pursue | AJ120: Auto-scan | AK120: WEB:uk_find_a_tender_tanzania:b27950ee1a9074a0 | AL120: =IF(AND(OR(W120="Watching",W120="Preparing"),ISNUMBER(Q120)),IF(AND(Q120>='Friday Summary'!$C$4,Q120<='Friday Summary'!$C$4+14),Q120+ROW()/1000000,""),"")
A121: =IF(B121="","","OP-"&TEXT(ROW()-4,"000")) | B121: (not shown) | C121: 46305 | D121: aggregator | E121: https://www.globaltenders.com/tanzania-tenders.php | F121: See notice | G121: government | H121: How big is the Tanzania tender market? | I121: From aggregator notice (1 lot) – read the tender document | J121: Not stated – read the notice | K121: building | L121: See tender document | N121: unknown | O121: See tender document | P121: See tender document | R121: See tender document | S121: N | T121: =IF(A121="","",IFERROR(INDEX('Bid-NoBid'!$T:$T,MATCH(A121,'Bid-NoBid'!$A:$A,0)),"")) | U121: =IF(A121="","",IFERROR(IF(OR(INDEX('Bid-NoBid'!$U:$U,MATCH(A121,'Bid-NoBid'!$A:$A,0))="",LEFT(INDEX('Bid-NoBid'!$U:$U,MATCH(A121,'Bid-NoBid'!$A:$A,0)),10)="Incomplete"),"Screen: "&AC121,INDEX('Bid-NoBid'!$U:$U,MATCH(A121,'Bid-NoBid'!$A:$A,0))),"Screen: "&AC121)) | W121: Watching | X121: Frank | AB121: GlobalTenders – Tanzania (web page) | AC121: Check | AD121: Auto (GlobalTenders – Tanzania): Deadline not shown on the source page – open the link and read the notice | AE121: =IF(ISNUMBER(Q121),ROUNDDOWN(Q121-NOW(),1),"") | AF121: =IF(OR(A121="",AE121=""),"",IF(NOT(OR(W121="Watching",W121="Preparing")),"",IF(AE121<0,"PASSED",IF(AND(AE121<=7,W121<>"Preparing"),"RED",IF(AE121<=14,"AMBER","GREEN"))))) | AG121: =IF(OR(A121="",NOT(OR(W121="Watching",W121="Preparing"))),"",IF(AND(ISNUMBER(M121),M121>=3000000000),"YES – ≥ TZS 3bn",IF(AND(ISNUMBER(AE121),AE121>=0,AE121<10,V121=""),"YES – <10 days",""))) | AI121: Read the notice and decide with the QS Director whether to pursue | AJ121: Auto-scan | AK121: WEB:globaltenders_tanzania:a0d13a4cbcf28fc7 | AL121: =IF(AND(OR(W121="Watching",W121="Preparing"),ISNUMBER(Q121)),IF(AND(Q121>='Friday Summary'!$C$4,Q121<='Friday Summary'!$C$4+14),Q121+ROW()/1000000,""),"")
A122: =IF(B122="","","OP-"&TEXT(ROW()-4,"000")) | B122: (not shown) | C122: 46305 | D122: aggregator | E122: https://www.globaltenders.com/contract-awards/tender-awards-tanzania | F122: See notice | G122: government | H122: Research Tanzania market rates and competitor pricing by searching past Tanzania tenders and contract awards - Tanzania tender winners | I122: From aggregator notice (1 lot) – read the tender document | J122: Not stated – read the notice | K122: building | L122: See tender document | N122: unknown | O122: See tender document | P122: See tender document | R122: See tender document | S122: N | T122: =IF(A122="","",IFERROR(INDEX('Bid-NoBid'!$T:$T,MATCH(A122,'Bid-NoBid'!$A:$A,0)),"")) | U122: =IF(A122="","",IFERROR(IF(OR(INDEX('Bid-NoBid'!$U:$U,MATCH(A122,'Bid-NoBid'!$A:$A,0))="",LEFT(INDEX('Bid-NoBid'!$U:$U,MATCH(A122,'Bid-NoBid'!$A:$A,0)),10)="Incomplete"),"Screen: "&AC122,INDEX('Bid-NoBid'!$U:$U,MATCH(A122,'Bid-NoBid'!$A:$A,0))),"Screen: "&AC122)) | W122: Watching | X122: Frank | AB122: GlobalTenders – Tanzania (web page) | AC122: Check | AD122: Auto (GlobalTenders – Tanzania): Deadline not shown on the source page – open the link and read the notice | AE122: =IF(ISNUMBER(Q122),ROUNDDOWN(Q122-NOW(),1),"") | AF122: =IF(OR(A122="",AE122=""),"",IF(NOT(OR(W122="Watching",W122="Preparing")),"",IF(AE122<0,"PASSED",IF(AND(AE122<=7,W122<>"Preparing"),"RED",IF(AE122<=14,"AMBER","GREEN"))))) | AG122: =IF(OR(A122="",NOT(OR(W122="Watching",W122="Preparing"))),"",IF(AND(ISNUMBER(M122),M122>=3000000000),"YES – ≥ TZS 3bn",IF(AND(ISNUMBER(AE122),AE122>=0,AE122<10,V122=""),"YES – <10 days",""))) | AI122: Read the notice and decide with the QS Director whether to pursue | AJ122: Auto-scan | AK122: WEB:globaltenders_tanzania:63b1de7562d8ed23 | AL122: =IF(AND(OR(W122="Watching",W122="Preparing"),ISNUMBER(Q122)),IF(AND(Q122>='Friday Summary'!$C$4,Q122<='Friday Summary'!$C$4+14),Q122+ROW()/1000000,""),"")
A123: =IF(B123="","","OP-"&TEXT(ROW()-4,"000")) | B123: (not shown) | C123: 46305 | D123: aggregator | E123: https://www.globaltenders.com/tanzania-tenders.php | F123: See notice | G123: government | H123: The Tanzania tender market is estimated to be worth over US$10 billion per year. This includes tenders for all types of goods, services, and works. | I123: From aggregator notice (1 lot) – read the tender document | J123: Not stated – read the notice | K123: building | L123: See tender document | N123: unknown | O123: See tender document | P123: See tender document | R123: See tender document | S123: N | T123: =IF(A123="","",IFERROR(INDEX('Bid-NoBid'!$T:$T,MATCH(A123,'Bid-NoBid'!$A:$A,0)),"")) | U123: =IF(A123="","",IFERROR(IF(OR(INDEX('Bid-NoBid'!$U:$U,MATCH(A123,'Bid-NoBid'!$A:$A,0))="",LEFT(INDEX('Bid-NoBid'!$U:$U,MATCH(A123,'Bid-NoBid'!$A:$A,0)),10)="Incomplete"),"Screen: "&AC123,INDEX('Bid-NoBid'!$U:$U,MATCH(A123,'Bid-NoBid'!$A:$A,0))),"Screen: "&AC123)) | W123: Watching | X123: Frank | AB123: GlobalTenders – Tanzania (web page) | AC123: Check | AD123: Auto (GlobalTenders – Tanzania): Deadline not shown on the source page – open the link and read the notice | AE123: =IF(ISNUMBER(Q123),ROUNDDOWN(Q123-NOW(),1),"") | AF123: =IF(OR(A123="",AE123=""),"",IF(NOT(OR(W123="Watching",W123="Preparing")),"",IF(AE123<0,"PASSED",IF(AND(AE123<=7,W123<>"Preparing"),"RED",IF(AE123<=14,"AMBER","GREEN"))))) | AG123: =IF(OR(A123="",NOT(OR(W123="Watching",W123="Preparing"))),"",IF(AND(ISNUMBER(M123),M123>=3000000000),"YES – ≥ TZS 3bn",IF(AND(ISNUMBER(AE123),AE123>=0,AE123<10,V123=""),"YES – <10 days",""))) | AI123: Read the notice and decide with the QS Director whether to pursue | AJ123: Auto-scan | AK123: WEB:globaltenders_tanzania:f5fa7079d06711e1 | AL123: =IF(AND(OR(W123="Watching",W123="Preparing"),ISNUMBER(Q123)),IF(AND(Q123>='Friday Summary'!$C$4,Q123<='Friday Summary'!$C$4+14),Q123+ROW()/1000000,""),"")
A124: =IF(B124="","","OP-"&TEXT(ROW()-4,"000")) | B124: (not shown) | C124: 46305 | D124: aggregator | E124: https://www.globaltenders.com/contract-awards/tender-awards-tanzania | F124: See notice | G124: government | H124: Find relevant Tanzania tenders on official and local websites, journals, newspapers or on aggregator portals like Global tenders. Check Eligibility to bid for the Tanzania tender. Research Tanzania market rates and competitor pricing by searching past Tanzania tenders and contract awards - Tanzania | I124: From aggregator notice (1 lot) – read the tender document | J124: Not stated – read the notice | K124: building | L124: See tender document | N124: unknown | O124: See tender document | P124: See tender document | R124: See tender document | S124: N | T124: =IF(A124="","",IFERROR(INDEX('Bid-NoBid'!$T:$T,MATCH(A124,'Bid-NoBid'!$A:$A,0)),"")) | U124: =IF(A124="","",IFERROR(IF(OR(INDEX('Bid-NoBid'!$U:$U,MATCH(A124,'Bid-NoBid'!$A:$A,0))="",LEFT(INDEX('Bid-NoBid'!$U:$U,MATCH(A124,'Bid-NoBid'!$A:$A,0)),10)="Incomplete"),"Screen: "&AC124,INDEX('Bid-NoBid'!$U:$U,MATCH(A124,'Bid-NoBid'!$A:$A,0))),"Screen: "&AC124)) | W124: Watching | X124: Frank | AB124: GlobalTenders – Tanzania (web page) | AC124: Check | AD124: Auto (GlobalTenders – Tanzania): Deadline not shown on the source page – open the link and read the notice | AE124: =IF(ISNUMBER(Q124),ROUNDDOWN(Q124-NOW(),1),"") | AF124: =IF(OR(A124="",AE124=""),"",IF(NOT(OR(W124="Watching",W124="Preparing")),"",IF(AE124<0,"PASSED",IF(AND(AE124<=7,W124<>"Preparing"),"RED",IF(AE124<=14,"AMBER","GREEN"))))) | AG124: =IF(OR(A124="",NOT(OR(W124="Watching",W124="Preparing"))),"",IF(AND(ISNUMBER(M124),M124>=3000000000),"YES – ≥ TZS 3bn",IF(AND(ISNUMBER(AE124),AE124>=0,AE124<10,V124=""),"YES – <10 days",""))) | AI124: Read the notice and decide with the QS Director whether to pursue | AJ124: Auto-scan | AK124: WEB:globaltenders_tanzania:0df4cf4d46a06988 | AL124: =IF(AND(OR(W124="Watching",W124="Preparing"),ISNUMBER(Q124)),IF(AND(Q124>='Friday Summary'!$C$4,Q124<='Friday Summary'!$C$4+14),Q124+ROW()/1000000,""),"")
A125: =IF(B125="","","OP-"&TEXT(ROW()-4,"000")) | B125: (not shown) | C125: 46305 | D125: aggregator | E125: https://www.globaltenders.com/contract-awards/tender-awards-tanzania | F125: See notice | G125: government | H125: How to bid on Tanzania tenders? Find relevant Tanzania tenders on official and local websites, journals, newspapers or on aggregator portals like Global tenders. Check Eligibility to bid for the Tanzania tender. Research Tanzania market rates and competitor pricing by searching past Tanzania tenders | I125: From aggregator notice (1 lot) – read the tender document | J125: Not stated – read the notice | K125: building | L125: See tender document | N125: unknown | O125: See tender document | P125: See tender document | R125: See tender document | S125: N | T125: =IF(A125="","",IFERROR(INDEX('Bid-NoBid'!$T:$T,MATCH(A125,'Bid-NoBid'!$A:$A,0)),"")) | U125: =IF(A125="","",IFERROR(IF(OR(INDEX('Bid-NoBid'!$U:$U,MATCH(A125,'Bid-NoBid'!$A:$A,0))="",LEFT(INDEX('Bid-NoBid'!$U:$U,MATCH(A125,'Bid-NoBid'!$A:$A,0)),10)="Incomplete"),"Screen: "&AC125,INDEX('Bid-NoBid'!$U:$U,MATCH(A125,'Bid-NoBid'!$A:$A,0))),"Screen: "&AC125)) | W125: Watching | X125: Frank | AB125: GlobalTenders – Tanzania (web page) | AC125: Check | AD125: Auto (GlobalTenders – Tanzania): Deadline not shown on the source page – open the link and read the notice | AE125: =IF(ISNUMBER(Q125),ROUNDDOWN(Q125-NOW(),1),"") | AF125: =IF(OR(A125="",AE125=""),"",IF(NOT(OR(W125="Watching",W125="Preparing")),"",IF(AE125<0,"PASSED",IF(AND(AE125<=7,W125<>"Preparing"),"RED",IF(AE125<=14,"AMBER","GREEN"))))) | AG125: =IF(OR(A125="",NOT(OR(W125="Watching",W125="Preparing"))),"",IF(AND(ISNUMBER(M125),M125>=3000000000),"YES – ≥ TZS 3bn",IF(AND(ISNUMBER(AE125),AE125>=0,AE125<10,V125=""),"YES – <10 days",""))) | AI125: Read the notice and decide with the QS Director whether to pursue | AJ125: Auto-scan | AK125: WEB:globaltenders_tanzania:0ae0892e821e9b9e | AL125: =IF(AND(OR(W125="Watching",W125="Preparing"),ISNUMBER(Q125)),IF(AND(Q125>='Friday Summary'!$C$4,Q125<='Friday Summary'!$C$4+14),Q125+ROW()/1000000,""),"")
A126: =IF(B126="","","OP-"&TEXT(ROW()-4,"000")) | B126: (not shown) | C126: 46305 | D126: aggregator | E126: https://www.tenderimpulse.com/infrastructure-and-construction-tenders | F126: See notice | G126: government | H126: Infrastructure & Construction Tenders | I126: From aggregator notice (1 lot) – read the tender document | J126: Not stated – read the notice | K126: building | L126: See tender document | N126: unknown | O126: See tender document | P126: See tender document | R126: See tender document | S126: N | T126: =IF(A126="","",IFERROR(INDEX('Bid-NoBid'!$T:$T,MATCH(A126,'Bid-NoBid'!$A:$A,0)),"")) | U126: =IF(A126="","",IFERROR(IF(OR(INDEX('Bid-NoBid'!$U:$U,MATCH(A126,'Bid-NoBid'!$A:$A,0))="",LEFT(INDEX('Bid-NoBid'!$U:$U,MATCH(A126,'Bid-NoBid'!$A:$A,0)),10)="Incomplete"),"Screen: "&AC126,INDEX('Bid-NoBid'!$U:$U,MATCH(A126,'Bid-NoBid'!$A:$A,0))),"Screen: "&AC126)) | W126: Watching | X126: Frank | AB126: TenderImpulse – Tanzania (web page) | AC126: Check | AD126: Auto (TenderImpulse – Tanzania): Deadline not shown on the source page – open the link and read the notice | AE126: =IF(ISNUMBER(Q126),ROUNDDOWN(Q126-NOW(),1),"") | AF126: =IF(OR(A126="",AE126=""),"",IF(NOT(OR(W126="Watching",W126="Preparing")),"",IF(AE126<0,"PASSED",IF(AND(AE126<=7,W126<>"Preparing"),"RED",IF(AE126<=14,"AMBER","GREEN"))))) | AG126: =IF(OR(A126="",NOT(OR(W126="Watching",W126="Preparing"))),"",IF(AND(ISNUMBER(M126),M126>=3000000000),"YES – ≥ TZS 3bn",IF(AND(ISNUMBER(AE126),AE126>=0,AE126<10,V126=""),"YES – <10 days",""))) | AI126: Read the notice and decide with the QS Director whether to pursue | AJ126: Auto-scan | AK126: WEB:tenderimpulse_tanzania:491217e64d5d9d48 | AL126: =IF(AND(OR(W126="Watching",W126="Preparing"),ISNUMBER(Q126)),IF(AND(Q126>='Friday Summary'!$C$4,Q126<='Friday Summary'!$C$4+14),Q126+ROW()/1000000,""),"")
... A128: =IF(B128="","","OP-"&TEXT(ROW()-4,"000")) | B128: (not shown) | C128: 46305 | D128: aggregator | E128: https://www.tenderimpulse.com/tanzania-tenders | F128: See notice | G128: government | H128: Looking for the most updated opportunities in Tanzania's procurement market? Look no more. Tender Impulse is your first stop. We provide daily updated information on all Tanzania government tenders, projects, contracts, and tender notices. Whether you are looking for RFPs, Bids, RFQs, General Procur | I128: From aggregator notice (1 lot) – read the tender document | J128: Not stated – read the notice | K128: building | L128: See tender document | N128: unknown | O128: See tender document | P128: See tender document | R128: See tender document | S128: N | T128: =IF(A128="","",IFERROR(INDEX('Bid-NoBid'!$T:$T,MATCH(A128,'Bid-NoBid'!$A:$A,0)),"")) | U128: =IF(A128="","",IFERROR(IF(OR(INDEX('Bid-NoBid'!$U:$U,MATCH(A128,'Bid-NoBid'!$A:$A,0))="",LEFT(INDEX('Bid-NoBid'!$U:$U,MATCH(A128,'Bid-NoBid'!$A:$A,0)),10)="Incomplete"),"Screen: "&AC128,INDEX('Bid-NoBid'!$U:$U,MATCH(A128,'Bid-NoBid'!$A:$A,0))),"Screen: "&AC128)) | W128: Watching | X128: Frank | AB128: TenderImpulse – Tanzania (web page) | AC128: Check | AD128: Auto (TenderImpulse – Tanzania): Deadline not shown on the source page – open the link and read the notice | AE128: =IF(ISNUMBER(Q128),ROUNDDOWN(Q128-NOW(),1),"") | AF128: =IF(OR(A128="",AE128=""),"",IF(NOT(OR(W128="Watching",W128="Preparing")),"",IF(AE128<0,"PASSED",IF(AND(AE128<=7,W128<>"Preparing"),"RED",IF(AE128<=14,"AMBER","GREEN"))))) | AG128: =IF(OR(A128="",NOT(OR(W128="Watching",W128="Preparing"))),"",IF(AND(ISNUMBER(M128),M128>=3000000000),"YES – ≥ TZS 3bn",IF(AND(ISNUMBER(AE128),AE128>=0,AE128<10,V128=""),"YES – <10 days",""))) | AI128: Read the notice and decide with the QS Director whether to pursue | AJ128: Auto-scan | AK128: WEB:tenderimpulse_tanzania:3102f7c795847a65 | AL128: =IF(AND(OR(W128="Watching",W128="Preparing"),ISNUMBER(Q128)),IF(AND(Q128>='Friday Summary'!$C$4,Q128<='Friday Summary'!$C$4+14),Q128+ROW()/1000000,""),"")
A129: =IF(B129="","","OP-"&TEXT(ROW()-4,"000")) | B129: (not shown) | C129: 46305 | D129: press | E129: https://www.tanzaniatenders.com/tender/provision-labour-charges-constructions-tafori-buildings-ifinga-and-isinga-madaba-district-ruvuma-re-8fc1ee5.php | F129: See advert | G129: government | H129: Provision of Labour Charges for Constructions of Tafori Buildings at Ifinga and Isinga in Madaba District, Ruvuma Region | I129: From press notice (1 lot) – read the tender document | J129: Ruvuma | K129: building | L129: See tender document | N129: unknown | O129: See tender document | P129: See tender document | Q129: 46316.417 | R129: See tender document | S129: N | T129: =IF(A129="","",IFERROR(INDEX('Bid-NoBid'!$T:$T,MATCH(A129,'Bid-NoBid'!$A:$A,0)),"")) | U129: =IF(A129="","",IFERROR(IF(OR(INDEX('Bid-NoBid'!$U:$U,MATCH(A129,'Bid-NoBid'!$A:$A,0))="",LEFT(INDEX('Bid-NoBid'!$U:$U,MATCH(A129,'Bid-NoBid'!$A:$A,0)),10)="Incomplete"),"Screen: "&AC129,INDEX('Bid-NoBid'!$U:$U,MATCH(A129,'Bid-NoBid'!$A:$A,0))),"Screen: "&AC129)) | W129: Watching | X129: Frank | AB129: TanzaniaTenders.com (newspapers / portals / private) | AC129: Check | AD129: Auto (TanzaniaTenders.com): Building works but remote from Dar · deadline read from the web page – confirm | AE129: =IF(ISNUMBER(Q129),ROUNDDOWN(Q129-NOW(),1),"") | AF129: =IF(OR(A129="",AE129=""),"",IF(NOT(OR(W129="Watching",W129="Preparing")),"",IF(AE129<0,"PASSED",IF(AND(AE129<=7,W129<>"Preparing"),"RED",IF(AE129<=14,"AMBER","GREEN"))))) | AG129: =IF(OR(A129="",NOT(OR(W129="Watching",W129="Preparing"))),"",IF(AND(ISNUMBER(M129),M129>=3000000000),"YES – ≥ TZS 3bn",IF(AND(ISNUMBER(AE129),AE129>=0,AE129<10,V129=""),"YES – <10 days",""))) | AI129: Read the notice and decide with the QS Director whether to pursue | AJ129: Auto-scan | AK129: TZT:150740709 | AL129: =IF(AND(OR(W129="Watching",W129="Preparing"),ISNUMBER(Q129)),IF(AND(Q129>='Friday Summary'!$C$4,Q129<='Friday Summary'!$C$4+14),Q129+ROW()/1000000,""),"")
A130: =IF(B130="","","OP-"&TEXT(ROW()-4,"000")) | B130: (not shown) | C130: 46305 | D130: press | E130: https://www.tanzaniatenders.com/tender/kufagia-barabara-kukusanya-takataka-na-ushuru-wa-takataka-kwenye-maeneo-ya-makazi-biashara-barab-8fc1ee0.php | F130: See advert | G130: government | H130: Kufagia Barabara, Kukusanya Takataka Na Ushuru Wa Takataka, Kwenye Maeneo Ya Makazi, Biashara, Barabara Na Taasisi Mbalimbali | I130: From press notice (1 lot) – read the tender document | J130: Not stated – read the notice | K130: civil | L130: See tender document | N130: unknown | O130: See tender document | P130: See tender document | Q130: 46317.417 | R130: See tender document | S130: N | T130: =IF(A130="","",IFERROR(INDEX('Bid-NoBid'!$T:$T,MATCH(A130,'Bid-NoBid'!$A:$A,0)),"")) | U130: =IF(A130="","",IFERROR(IF(OR(INDEX('Bid-NoBid'!$U:$U,MATCH(A130,'Bid-NoBid'!$A:$A,0))="",LEFT(INDEX('Bid-NoBid'!$U:$U,MATCH(A130,'Bid-NoBid'!$A:$A,0)),10)="Incomplete"),"Screen: "&AC130,INDEX('Bid-NoBid'!$U:$U,MATCH(A130,'Bid-NoBid'!$A:$A,0))),"Screen: "&AC130)) | W130: Watching | X130: Frank | AB130: TanzaniaTenders.com (newspapers / portals / private) | AC130: Check | AD130: Auto (TanzaniaTenders.com): Civil works – confirm site, CRB class and margin · deadline read from the web page – confirm | AE130: =IF(ISNUMBER(Q130),ROUNDDOWN(Q130-NOW(),1),"") | AF130: =IF(OR(A130="",AE130=""),"",IF(NOT(OR(W130="Watching",W130="Preparing")),"",IF(AE130<0,"PASSED",IF(AND(AE130<=7,W130<>"Preparing"),"RED",IF(AE130<=14,"AMBER","GREEN"))))) | AG130: =IF(OR(A130="",NOT(OR(W130="Watching",W130="Preparing"))),"",IF(AND(ISNUMBER(M130),M130>=3000000000),"YES – ≥ TZS 3bn",IF(AND(ISNUMBER(AE130),AE130>=0,AE130<10,V130=""),"YES – <10 days",""))) | AI130: Read the notice and decide with the QS Director whether to pursue | AJ130: Auto-scan | AK130: TZT:150740704 | AL130: =IF(AND(OR(W130="Watching",W130="Preparing"),ISNUMBER(Q130)),IF(AND(Q130>='Friday Summary'!$C$4,Q130<='Friday Summary'!$C$4+14),Q130+ROW()/1000000,""),"")
A131: =IF(B131="","","OP-"&TEXT(ROW()-4,"000")) | B131: TR212/2026/2027/W/23 | C131: 46307 | D131: NeST | E131: https://nest.go.tz/tenders/published-tenders | F131: Tanzania Electric Supply Company Limited | G131: parastatal (verify) | H131: Repair of Substation Yard Concrete Roads and Kerbstones at Ubungo Substation | I131: From NeST notice (1 lot) – read the tender document | J131: Dar es Salaam (Ubungo) | K131: civil | L131: NeST login needed | N131: unknown | O131: NeST login needed | P131: NeST login needed | Q131: 46314.583 | R131: NeST login needed | S131: N | T131: =IF(A131="","",IFERROR(INDEX('Bid-NoBid'!$T:$T,MATCH(A131,'Bid-NoBid'!$A:$A,0)),"")) | U131: =IF(A131="","",IFERROR(IF(OR(INDEX('Bid-NoBid'!$U:$U,MATCH(A131,'Bid-NoBid'!$A:$A,0))="",LEFT(INDEX('Bid-NoBid'!$U:$U,MATCH(A131,'Bid-NoBid'!$A:$A,0)),10)="Incomplete"),"Screen: "&AC131,INDEX('Bid-NoBid'!$U:$U,MATCH(A131,'Bid-NoBid'!$A:$A,0))),"Screen: "&AC131)) | W131: Watching | X131: Frank | AA131: 46307 | AB131: Small Works / Tender | AC131: Check | AD131: Auto (Small Works / Tender): Civil works in Dar/Coast – confirm CRB class and margin | AE131: =IF(ISNUMBER(Q131),ROUNDDOWN(Q131-NOW(),1),"") | AF131: =IF(OR(A131="",AE131=""),"",IF(NOT(OR(W131="Watching",W131="Preparing")),"",IF(AE131<0,"PASSED",IF(AND(AE131<=7,W131<>"Preparing"),"RED",IF(AE131<=14,"AMBER","GREEN"))))) | AG131: =IF(OR(A131="",NOT(OR(W131="Watching",W131="Preparing"))),"",IF(AND(ISNUMBER(M131),M131>=3000000000),"YES – ≥ TZS 3bn",IF(AND(ISNUMBER(AE131),AE131>=0,AE131<10,V131=""),"YES – <10 days",""))) | AI131: Read the notice and decide with the QS Director whether to pursue | AJ131: Auto-scan | AK131: 97b7d5a5-18af-4ac9-bd29-f26652a06ad1 | AL131: =IF(AND(OR(W131="Watching",W131="Preparing"),ISNUMBER(Q131)),IF(AND(Q131>='Friday Summary'!$C$4,Q131<='Friday Summary'!$C$4+14),Q131+ROW()/1000000,""),"")
A132: =IF(B132="","","OP-"&TEXT(ROW()-4,"000")) | B132: TR61/2026/2027/W/04 | C132: 46307 | D132: NeST | E132: https://nest.go.tz/tenders/published-tenders | F132: Tanzania Broadcasting Corporation | G132: parastatal (verify) | H132: Rehabilitation of Tanzania Safari Channel Office Building | I132: From NeST notice (1 lot) – read the tender document | J132: Dar es Salaam (Temeke) (from client's office – confirm site) | K132: renovation | L132: NeST login needed | N132: unknown | O132: NeST login needed | P132: NeST login needed | Q132: 46314.583 | R132: NeST login needed | S132: N | T132: =IF(A132="","",IFERROR(INDEX('Bid-NoBid'!$T:$T,MATCH(A132,'Bid-NoBid'!$A:$A,0)),"")) | U132: =IF(A132="","",IFERROR(IF(OR(INDEX('Bid-NoBid'!$U:$U,MATCH(A132,'Bid-NoBid'!$A:$A,0))="",LEFT(INDEX('Bid-NoBid'!$U:$U,MATCH(A132,'Bid-NoBid'!$A:$A,0)),10)="Incomplete"),"Screen: "&AC132,INDEX('Bid-NoBid'!$U:$U,MATCH(A132,'Bid-NoBid'!$A:$A,0))),"Screen: "&AC132)) | W132: Watching | X132: Frank | AA132: 46307 | AB132: Standard Invitation for Quotations -Works / Planned Tender | AC132: Check | AD132: Auto (Standard Invitation for Quotations -Works / Planned Tender): Quotation route – value may be below TZS 200m | AE132: =IF(ISNUMBER(Q132),ROUNDDOWN(Q132-NOW(),1),"") | AF132: =IF(OR(A132="",AE132=""),"",IF(NOT(OR(W132="Watching",W132="Preparing")),"",IF(AE132<0,"PASSED",IF(AND(AE132<=7,W132<>"Preparing"),"RED",IF(AE132<=14,"AMBER","GREEN"))))) | AG132: =IF(OR(A132="",NOT(OR(W132="Watching",W132="Preparing"))),"",IF(AND(ISNUMBER(M132),M132>=3000000000),"YES – ≥ TZS 3bn",IF(AND(ISNUMBER(AE132),AE132>=0,AE132<10,V132=""),"YES – <10 days",""))) | AI132: Read the notice and decide with the QS Director whether to pursue | AJ132: Auto-scan | AK132: 979dd485-d9ba-4160-8bf7-d100a0b4db7b | AL132: =IF(AND(OR(W132="Watching",W132="Preparing"),ISNUMBER(Q132)),IF(AND(Q132>='Friday Summary'!$C$4,Q132<='Friday Summary'!$C$4+14),Q132+ROW()/1000000,""),"")
A133: =IF(B133="","","OP-"&TEXT(ROW()-4,"000")) | B133: (not shown) | C133: 46307 | D133: press | E133: https://www.tanzaniatenders.com/tender/procurement-therapeutic-and-patient-support-equipment-mri-compatible-anesthesia-machine-ventilator-8fcd741.php | F133: See advert | G133: government | H133: Procurement of Therapeutic and Patient Support Equipment (Mri Compatible Anesthesia Machine, Ventilators, Suction Machine, Rehabilitation Instrument, Ect Machine, Child and Adolescent Ot Tools, Perine... | I133: From press notice (1 lot) – read the tender document | J133: Not stated – read the notice | K133: renovation | L133: See tender document | N133: unknown | O133: See tender document | P133: See tender document | Q133: 46314.417 | R133: See tender document | S133: N | T133: =IF(A133="","",IFERROR(INDEX('Bid-NoBid'!$T:$T,MATCH(A133,'Bid-NoBid'!$A:$A,0)),"")) | U133: =IF(A133="","",IFERROR(IF(OR(INDEX('Bid-NoBid'!$U:$U,MATCH(A133,'Bid-NoBid'!$A:$A,0))="",LEFT(INDEX('Bid-NoBid'!$U:$U,MATCH(A133,'Bid-NoBid'!$A:$A,0)),10)="Incomplete"),"Screen: "&AC133,INDEX('Bid-NoBid'!$U:$U,MATCH(A133,'Bid-NoBid'!$A:$A,0))),"Screen: "&AC133)) | W133: Watching | X133: Frank | AB133: TanzaniaTenders.com (newspapers / portals / private) | AC133: Check | AD133: Auto (TanzaniaTenders.com): Site not stated in the listing – read the notice · deadline read from the web page – confirm | AE133: =IF(ISNUMBER(Q133),ROUNDDOWN(Q133-NOW(),1),"") | AF133: =IF(OR(A133="",AE133=""),"",IF(NOT(OR(W133="Watching",W133="Preparing")),"",IF(AE133<0,"PASSED",IF(AND(AE133<=7,W133<>"Preparing"),"RED",IF(AE133<=14,"AMBER","GREEN"))))) | AG133: =IF(OR(A133="",NOT(OR(W133="Watching",W133="Preparing"))),"",IF(AND(ISNUMBER(M133),M133>=3000000000),"YES – ≥ TZS 3bn",IF(AND(ISNUMBER(AE133),AE133>=0,AE133<10,V133=""),"YES – <10 days",""))) | AI133: Read the notice and decide with the QS Director whether to pursue | AJ133: Auto-scan | AK133: TZT:150787905 | AL133: =IF(AND(OR(W133="Watching",W133="Preparing"),ISNUMBER(Q133)),IF(AND(Q133>='Friday Summary'!$C$4,Q133<='Friday Summary'!$C$4+14),Q133+ROW()/1000000,""),"")
...

Sheet Bid-NoBid
A1: Bid / No-Bid scoring sheet (F-02 · Appendix A)
A2: One row per opportunity ID. Gates: Pass/Fail/TBC. Scores 0–5 (see Scoring Guide). Result appears when all 12 are scored. Criterion 8 pre-filled from the notice location – confirm.
B3: Weight → | G3: ='Scoring Guide'!C11 | H3: ='Scoring Guide'!C12 | I3: ='Scoring Guide'!C13 | J3: ='Scoring Guide'!C14 | K3: ='Scoring Guide'!C15 | L3: ='Scoring Guide'!C16 | M3: ='Scoring Guide'!C17 | N3: ='Scoring Guide'!C18 | O3: ='Scoring Guide'!C19 | P3: ='Scoring Guide'!C20 | Q3: ='Scoring Guide'!C21 | R3: ='Scoring Guide'!C22
A4: ID | B4: Tender title | C4: G1 CRB class | D4: G2 Turnover / experience | E4: G3 Securities within bank limits | F4: G4 Deadline achievable | G4: 1. Client payment record and funding confirmed | H4: 2. Relationship / access to decision-maker | I4: 3. Client type strategic value (bank, oil & gas, donor, government) | J4: 4. Expected number and strength of competitors | K4: 5. Evaluation basis favours us (technical weight, past performance) | L4: 6. Margin potential at market rates (from rate library) | M4: 7. Key staff and equipment available in the period | N4: 8. Location and logistics (distance from base, site conditions) | O4: 9. Advance payment / payment terms / retention | P4: 10. Risk profile: design responsibility, LDs, unusual conditions | Q4: 11. Strategic fit: new sector entry, reference value, repeat work | R4: 12. Cost of bidding (site visit, design, bid bond) vs value | S4: Criteria scored | T4: Weighted score | U4: Result | V4: Scored by | W4: Date scored | X4: MD decision | Y4: Evidence / notes
A5: =IF(Pipeline!A5="","",Pipeline!A5) | B5: =IF(A5="","",INDEX(Pipeline!$H:$H,MATCH(A5,Pipeline!$A:$A,0))) | N5: 4 | S5: =IF(A5="","",COUNT(G5:R5)) | T5: =IF(OR(A5="",S5<12),"",SUMPRODUCT($G$3:$R$3,G5:R5)/5) | U5: =IF(A5="","",IF(COUNTIF(C5:F5,"Fail")>0,"No-Bid (gate failed)",IF(S5<12,"Incomplete ("&S5&"/12)",IF(T5>='Scoring Guide'!$C$26,"Bid",IF(T5>='Scoring Guide'!$C$27,"Conditional (MD)","No-Bid")))))
A6: =IF(Pipeline!A6="","",Pipeline!A6) | B6: =IF(A6="","",INDEX(Pipeline!$H:$H,MATCH(A6,Pipeline!$A:$A,0))) | N6: 4 | S6: =IF(A6="","",COUNT(G6:R6)) | T6: =IF(OR(A6="",S6<12),"",SUMPRODUCT($G$3:$R$3,G6:R6)/5) | U6: =IF(A6="","",IF(COUNTIF(C6:F6,"Fail")>0,"No-Bid (gate failed)",IF(S6<12,"Incomplete ("&S6&"/12)",IF(T6>='Scoring Guide'!$C$26,"Bid",IF(T6>='Scoring Guide'!$C$27,"Conditional (MD)","No-Bid")))))
A7: =IF(Pipeline!A7="","",Pipeline!A7) | B7: =IF(A7="","",INDEX(Pipeline!$H:$H,MATCH(A7,Pipeline!$A:$A,0))) | S7: =IF(A7="","",COUNT(G7:R7)) | T7: =IF(OR(A7="",S7<12),"",SUMPRODUCT($G$3:$R$3,G7:R7)/5) | U7: =IF(A7="","",IF(COUNTIF(C7:F7,"Fail")>0,"No-Bid (gate failed)",IF(S7<12,"Incomplete ("&S7&"/12)",IF(T7>='Scoring Guide'!$C$26,"Bid",IF(T7>='Scoring Guide'!$C$27,"Conditional (MD)","No-Bid")))))
A8: =IF(Pipeline!A8="","",Pipeline!A8) | B8: =IF(A8="","",INDEX(Pipeline!$H:$H,MATCH(A8,Pipeline!$A:$A,0))) | N8: 5 | S8: =IF(A8="","",COUNT(G8:R8)) | T8: =IF(OR(A8="",S8<12),"",SUMPRODUCT($G$3:$R$3,G8:R8)/5) | U8: =IF(A8="","",IF(COUNTIF(C8:F8,"Fail")>0,"No-Bid (gate failed)",IF(S8<12,"Incomplete ("&S8&"/12)",IF(T8>='Scoring Guide'!$C$26,"Bid",IF(T8>='Scoring Guide'!$C$27,"Conditional (MD)","No-Bid")))))
A9: =IF(Pipeline!A9="","",Pipeline!A9) | B9: =IF(A9="","",INDEX(Pipeline!$H:$H,MATCH(A9,Pipeline!$A:$A,0))) | N9: 5 | S9: =IF(A9="","",COUNT(G9:R9)) | T9: =IF(OR(A9="",S9<12),"",SUMPRODUCT($G$3:$R$3,G9:R9)/5) | U9: =IF(A9="","",IF(COUNTIF(C9:F9,"Fail")>0,"No-Bid (gate failed)",IF(S9<12,"Incomplete ("&S9&"/12)",IF(T9>='Scoring Guide'!$C$26,"Bid",IF(T9>='Scoring Guide'!$C$27,"Conditional (MD)","No-Bid")))))
A10: =IF(Pipeline!A10="","",Pipeline!A10) | B10: =IF(A10="","",INDEX(Pipeline!$H:$H,MATCH(A10,Pipeline!$A:$A,0))) | S10: =IF(A10="","",COUNT(G10:R10)) | T10: =IF(OR(A10="",S10<12),"",SUMPRODUCT($G$3:$R$3,G10:R10)/5) | U10: =IF(A10="","",IF(COUNTIF(C10:F10,"Fail")>0,"No-Bid (gate failed)",IF(S10<12,"Incomplete ("&S10&"/12)",IF(T10>='Scoring Guide'!$C$26,"Bid",IF(T10>='Scoring Guide'!$C$27,"Conditional (MD)","No-Bid")))))
A11: =IF(Pipeline!A11="","",Pipeline!A11) | B11: =IF(A11="","",INDEX(Pipeline!$H:$H,MATCH(A11,Pipeline!$A:$A,0))) | N11: 5 | S11: =IF(A11="","",COUNT(G11:R11)) | T11: =IF(OR(A11="",S11<12),"",SUMPRODUCT($G$3:$R$3,G11:R11)/5) | U11: =IF(A11="","",IF(COUNTIF(C11:F11,"Fail")>0,"No-Bid (gate failed)",IF(S11<12,"Incomplete ("&S11&"/12)",IF(T11>='Scoring Guide'!$C$26,"Bid",IF(T11>='Scoring Guide'!$C$27,"Conditional (MD)","No-Bid")))))
A12: =IF(Pipeline!A12="","",Pipeline!A12) | B12: =IF(A12="","",INDEX(Pipeline!$H:$H,MATCH(A12,Pipeline!$A:$A,0))) | N12: 5 | S12: =IF(A12="","",COUNT(G12:R12)) | T12: =IF(OR(A12="",S12<12),"",SUMPRODUCT($G$3:$R$3,G12:R12)/5) | U12: =IF(A12="","",IF(COUNTIF(C12:F12,"Fail")>0,"No-Bid (gate failed)",IF(S12<12,"Incomplete ("&S12&"/12)",IF(T12>='Scoring Guide'!$C$26,"Bid",IF(T12>='Scoring Guide'!$C$27,"Conditional (MD)","No-Bid")))))
A13: =IF(Pipeline!A13="","",Pipeline!A13) | B13: =IF(A13="","",INDEX(Pipeline!$H:$H,MATCH(A13,Pipeline!$A:$A,0))) | N13: 1 | S13: =IF(A13="","",COUNT(G13:R13)) | T13: =IF(OR(A13="",S13<12),"",SUMPRODUCT($G$3:$R$3,G13:R13)/5) | U13: =IF(A13="","",IF(COUNTIF(C13:F13,"Fail")>0,"No-Bid (gate failed)",IF(S13<12,"Incomplete ("&S13&"/12)",IF(T13>='Scoring Guide'!$C$26,"Bid",IF(T13>='Scoring Guide'!$C$27,"Conditional (MD)","No-Bid")))))
A14: =IF(Pipeline!A14="","",Pipeline!A14) | B14: =IF(A14="","",INDEX(Pipeline!$H:$H,MATCH(A14,Pipeline!$A:$A,0))) | N14: 2 | S14: =IF(A14="","",COUNT(G14:R14)) | T14: =IF(OR(A14="",S14<12),"",SUMPRODUCT($G$3:$R$3,G14:R14)/5) | U14: =IF(A14="","",IF(COUNTIF(C14:F14,"Fail")>0,"No-Bid (gate failed)",IF(S14<12,"Incomplete ("&S14&"/12)",IF(T14>='Scoring Guide'!$C$26,"Bid",IF(T14>='Scoring Guide'!$C$27,"Conditional (MD)","No-Bid")))))
A15: =IF(Pipeline!A15="","",Pipeline!A15) | B15: =IF(A15="","",INDEX(Pipeline!$H:$H,MATCH(A15,Pipeline!$A:$A,0))) | N15: 2 | S15: =IF(A15="","",COUNT(G15:R15)) | T15: =IF(OR(A15="",S15<12),"",SUMPRODUCT($G$3:$R$3,G15:R15)/5) | U15: =IF(A15="","",IF(COUNTIF(C15:F15,"Fail")>0,"No-Bid (gate failed)",IF(S15<12,"Incomplete ("&S15&"/12)",IF(T15>='Scoring Guide'!$C$26,"Bid",IF(T15>='Scoring Guide'!$C$27,"Conditional (MD)","No-Bid")))))
A16: =IF(Pipeline!A16="","",Pipeline!A16) | B16: =IF(A16="","",INDEX(Pipeline!$H:$H,MATCH(A16,Pipeline!$A:$A,0))) | N16: 2 | S16: =IF(A16="","",COUNT(G16:R16)) | T16: =IF(OR(A16="",S16<12),"",SUMPRODUCT($G$3:$R$3,G16:R16)/5) | U16: =IF(A16="","",IF(COUNTIF(C16:F16,"Fail")>0,"No-Bid (gate failed)",IF(S16<12,"Incomplete ("&S16&"/12)",IF(T16>='Scoring Guide'!$C$26,"Bid",IF(T16>='Scoring Guide'!$C$27,"Conditional (MD)","No-Bid")))))
A17: =IF(Pipeline!A17="","",Pipeline!A17) | B17: =IF(A17="","",INDEX(Pipeline!$H:$H,MATCH(A17,Pipeline!$A:$A,0))) | N17: 1 | S17: =IF(A17="","",COUNT(G17:R17)) | T17: =IF(OR(A17="",S17<12),"",SUMPRODUCT($G$3:$R$3,G17:R17)/5) | U17: =IF(A17="","",IF(COUNTIF(C17:F17,"Fail")>0,"No-Bid (gate failed)",IF(S17<12,"Incomplete ("&S17&"/12)",IF(T17>='Scoring Guide'!$C$26,"Bid",IF(T17>='Scoring Guide'!$C$27,"Conditional (MD)","No-Bid")))))
A18: =IF(Pipeline!A18="","",Pipeline!A18) | B18: =IF(A18="","",INDEX(Pipeline!$H:$H,MATCH(A18,Pipeline!$A:$A,0))) | N18: 1 | S18: =IF(A18="","",COUNT(G18:R18)) | T18: =IF(OR(A18="",S18<12),"",SUMPRODUCT($G$3:$R$3,G18:R18)/5) | U18: =IF(A18="","",IF(COUNTIF(C18:F18,"Fail")>0,"No-Bid (gate failed)",IF(S18<12,"Incomplete ("&S18&"/12)",IF(T18>='Scoring Guide'!$C$26,"Bid",IF(T18>='Scoring Guide'!$C$27,"Conditional (MD)","No-Bid")))))
A19: =IF(Pipeline!A19="","",Pipeline!A19) | B19: =IF(A19="","",INDEX(Pipeline!$H:$H,MATCH(A19,Pipeline!$A:$A,0))) | N19: 1 | S19: =IF(A19="","",COUNT(G19:R19)) | T19: =IF(OR(A19="",S19<12),"",SUMPRODUCT($G$3:$R$3,G19:R19)/5) | U19: =IF(A19="","",IF(COUNTIF(C19:F19,"Fail")>0,"No-Bid (gate failed)",IF(S19<12,"Incomplete ("&S19&"/12)",IF(T19>='Scoring Guide'!$C$26,"Bid",IF(T19>='Scoring Guide'!$C$27,"Conditional (MD)","No-Bid")))))
A20: =IF(Pipeline!A20="","",Pipeline!A20) | B20: =IF(A20="","",INDEX(Pipeline!$H:$H,MATCH(A20,Pipeline!$A:$A,0))) | N20: 1 | S20: =IF(A20="","",COUNT(G20:R20)) | T20: =IF(OR(A20="",S20<12),"",SUMPRODUCT($G$3:$R$3,G20:R20)/5) | U20: =IF(A20="","",IF(COUNTIF(C20:F20,"Fail")>0,"No-Bid (gate failed)",IF(S20<12,"Incomplete ("&S20&"/12)",IF(T20>='Scoring Guide'!$C$26,"Bid",IF(T20>='Scoring Guide'!$C$27,"Conditional (MD)","No-Bid")))))
A21: =IF(Pipeline!A21="","",Pipeline!A21) | B21: =IF(A21="","",INDEX(Pipeline!$H:$H,MATCH(A21,Pipeline!$A:$A,0))) | N21: 1 | S21: =IF(A21="","",COUNT(G21:R21)) | T21: =IF(OR(A21="",S21<12),"",SUMPRODUCT($G$3:$R$3,G21:R21)/5) | U21: =IF(A21="","",IF(COUNTIF(C21:F21,"Fail")>0,"No-Bid (gate failed)",IF(S21<12,"Incomplete ("&S21&"/12)",IF(T21>='Scoring Guide'!$C$26,"Bid",IF(T21>='Scoring Guide'!$C$27,"Conditional (MD)","No-Bid")))))
A22: =IF(Pipeline!A22="","",Pipeline!A22) | B22: =IF(A22="","",INDEX(Pipeline!$H:$H,MATCH(A22,Pipeline!$A:$A,0))) | N22: 0 | S22: =IF(A22="","",COUNT(G22:R22)) | T22: =IF(OR(A22="",S22<12),"",SUMPRODUCT($G$3:$R$3,G22:R22)/5) | U22: =IF(A22="","",IF(COUNTIF(C22:F22,"Fail")>0,"No-Bid (gate failed)",IF(S22<12,"Incomplete ("&S22&"/12)",IF(T22>='Scoring Guide'!$C$26,"Bid",IF(T22>='Scoring Guide'!$C$27,"Conditional (MD)","No-Bid")))))
... A26: =IF(Pipeline!A26="","",Pipeline!A26) | B26: =IF(A26="","",INDEX(Pipeline!$H:$H,MATCH(A26,Pipeline!$A:$A,0))) | N26: 5 | S26: =IF(A26="","",COUNT(G26:R26)) | T26: =IF(OR(A26="",S26<12),"",SUMPRODUCT($G$3:$R$3,G26:R26)/5) | U26: =IF(A26="","",IF(COUNTIF(C26:F26,"Fail")>0,"No-Bid (gate failed)",IF(S26<12,"Incomplete ("&S26&"/12)",IF(T26>='Scoring Guide'!$C$26,"Bid",IF(T26>='Scoring Guide'!$C$27,"Conditional (MD)","No-Bid")))))
A27: =IF(Pipeline!A27="","",Pipeline!A27) | B27: =IF(A27="","",INDEX(Pipeline!$H:$H,MATCH(A27,Pipeline!$A:$A,0))) | S27: =IF(A27="","",COUNT(G27:R27)) | T27: =IF(OR(A27="",S27<12),"",SUMPRODUCT($G$3:$R$3,G27:R27)/5) | U27: =IF(A27="","",IF(COUNTIF(C27:F27,"Fail")>0,"No-Bid (gate failed)",IF(S27<12,"Incomplete ("&S27&"/12)",IF(T27>='Scoring Guide'!$C$26,"Bid",IF(T27>='Scoring Guide'!$C$27,"Conditional (MD)","No-Bid")))))
A28: =IF(Pipeline!A28="","",Pipeline!A28) | B28: =IF(A28="","",INDEX(Pipeline!$H:$H,MATCH(A28,Pipeline!$A:$A,0))) | N28: 5 | S28: =IF(A28="","",COUNT(G28:R28)) | T28: =IF(OR(A28="",S28<12),"",SUMPRODUCT($G$3:$R$3,G28:R28)/5) | U28: =IF(A28="","",IF(COUNTIF(C28:F28,"Fail")>0,"No-Bid (gate failed)",IF(S28<12,"Incomplete ("&S28&"/12)",IF(T28>='Scoring Guide'!$C$26,"Bid",IF(T28>='Scoring Guide'!$C$27,"Conditional (MD)","No-Bid")))))
A29: =IF(Pipeline!A29="","",Pipeline!A29) | B29: =IF(A29="","",INDEX(Pipeline!$H:$H,MATCH(A29,Pipeline!$A:$A,0))) | N29: 5 | S29: =IF(A29="","",COUNT(G29:R29)) | T29: =IF(OR(A29="",S29<12),"",SUMPRODUCT($G$3:$R$3,G29:R29)/5) | U29: =IF(A29="","",IF(COUNTIF(C29:F29,"Fail")>0,"No-Bid (gate failed)",IF(S29<12,"Incomplete ("&S29&"/12)",IF(T29>='Scoring Guide'!$C$26,"Bid",IF(T29>='Scoring Guide'!$C$27,"Conditional (MD)","No-Bid")))))
A30: =IF(Pipeline!A30="","",Pipeline!A30) | B30: =IF(A30="","",INDEX(Pipeline!$H:$H,MATCH(A30,Pipeline!$A:$A,0))) | N30: 5 | S30: =IF(A30="","",COUNT(G30:R30)) | T30: =IF(OR(A30="",S30<12),"",SUMPRODUCT($G$3:$R$3,G30:R30)/5) | U30: =IF(A30="","",IF(COUNTIF(C30:F30,"Fail")>0,"No-Bid (gate failed)",IF(S30<12,"Incomplete ("&S30&"/12)",IF(T30>='Scoring Guide'!$C$26,"Bid",IF(T30>='Scoring Guide'!$C$27,"Conditional (MD)","No-Bid")))))
A31: =IF(Pipeline!A31="","",Pipeline!A31) | B31: =IF(A31="","",INDEX(Pipeline!$H:$H,MATCH(A31,Pipeline!$A:$A,0))) | N31: 5 | S31: =IF(A31="","",COUNT(G31:R31)) | T31: =IF(OR(A31="",S31<12),"",SUMPRODUCT($G$3:$R$3,G31:R31)/5) | U31: =IF(A31="","",IF(COUNTIF(C31:F31,"Fail")>0,"No-Bid (gate failed)",IF(S31<12,"Incomplete ("&S31&"/12)",IF(T31>='Scoring Guide'!$C$26,"Bid",IF(T31>='Scoring Guide'!$C$27,"Conditional (MD)","No-Bid")))))
A32: =IF(Pipeline!A32="","",Pipeline!A32) | B32: =IF(A32="","",INDEX(Pipeline!$H:$H,MATCH(A32,Pipeline!$A:$A,0))) | N32: 1 | S32: =IF(A32="","",COUNT(G32:R32)) | T32: =IF(OR(A32="",S32<12),"",SUMPRODUCT($G$3:$R$3,G32:R32)/5) | U32: =IF(A32="","",IF(COUNTIF(C32:F32,"Fail")>0,"No-Bid (gate failed)",IF(S32<12,"Incomplete ("&S32&"/12)",IF(T32>='Scoring Guide'!$C$26,"Bid",IF(T32>='Scoring Guide'!$C$27,"Conditional (MD)","No-Bid")))))
A33: =IF(Pipeline!A33="","",Pipeline!A33) | B33: =IF(A33="","",INDEX(Pipeline!$H:$H,MATCH(A33,Pipeline!$A:$A,0))) | N33: 3 | S33: =IF(A33="","",COUNT(G33:R33)) | T33: =IF(OR(A33="",S33<12),"",SUMPRODUCT($G$3:$R$3,G33:R33)/5) | U33: =IF(A33="","",IF(COUNTIF(C33:F33,"Fail")>0,"No-Bid (gate failed)",IF(S33<12,"Incomplete ("&S33&"/12)",IF(T33>='Scoring Guide'!$C$26,"Bid",IF(T33>='Scoring Guide'!$C$27,"Conditional (MD)","No-Bid")))))
A34: =IF(Pipeline!A34="","",Pipeline!A34) | B34: =IF(A34="","",INDEX(Pipeline!$H:$H,MATCH(A34,Pipeline!$A:$A,0))) | N34: 1 | S34: =IF(A34="","",COUNT(G34:R34)) | T34: =IF(OR(A34="",S34<12),"",SUMPRODUCT($G$3:$R$3,G34:R34)/5) | U34: =IF(A34="","",IF(COUNTIF(C34:F34,"Fail")>0,"No-Bid (gate failed)",IF(S34<12,"Incomplete ("&S34&"/12)",IF(T34>='Scoring Guide'!$C$26,"Bid",IF(T34>='Scoring Guide'!$C$27,"Conditional (MD)","No-Bid")))))
A35: =IF(Pipeline!A35="","",Pipeline!A35) | B35: =IF(A35="","",INDEX(Pipeline!$H:$H,MATCH(A35,Pipeline!$A:$A,0))) | N35: 4 | S35: =IF(A35="","",COUNT(G35:R35)) | T35: =IF(OR(A35="",S35<12),"",SUMPRODUCT($G$3:$R$3,G35:R35)/5) | U35: =IF(A35="","",IF(COUNTIF(C35:F35,"Fail")>0,"No-Bid (gate failed)",IF(S35<12,"Incomplete ("&S35&"/12)",IF(T35>='Scoring Guide'!$C$26,"Bid",IF(T35>='Scoring Guide'!$C$27,"Conditional (MD)","No-Bid")))))
A36: =IF(Pipeline!A36="","",Pipeline!A36) | B36: =IF(A36="","",INDEX(Pipeline!$H:$H,MATCH(A36,Pipeline!$A:$A,0))) | N36: 5 | S36: =IF(A36="","",COUNT(G36:R36)) | T36: =IF(OR(A36="",S36<12),"",SUMPRODUCT($G$3:$R$3,G36:R36)/5) | U36: =IF(A36="","",IF(COUNTIF(C36:F36,"Fail")>0,"No-Bid (gate failed)",IF(S36<12,"Incomplete ("&S36&"/12)",IF(T36>='Scoring Guide'!$C$26,"Bid",IF(T36>='Scoring Guide'!$C$27,"Conditional (MD)","No-Bid")))))
